Workbook
Name BreakAllow: Settings!$C$6
Name DebtCap: Settings!$C$7
Name EntryTypes: Settings!$F$6:$F$8
Name RateDates: Settings!$B$13:$B$32
Name RateValues: Settings!$C$13:$C$32
Name RejectAlarm: Settings!$C$8
Name StatusList: Settings!$G$6:$G$7
Name WeekStarts: Weeks!$A$7:$A$59
Name WorkerIDs: Workers!$A$6:$A$17
Name WorkerNames: Workers!$B$6:$B$17
Name YesNo: Settings!$H$6:$H$7

Sheet Home
A1: ◆ Donabay | C1: Home | E1: Daily Log | G1: Cash Ledger | J1: Weekly Pay | M1: Payslip | O1: Workers | Q1: Settings | S1: Guide | U1: · | V1: History | X1: Weeks | Z1: Checks
T2: row
B3: Dashboard | Q3: Week of | R3: =TODAY()-WEEKDAY(TODAY(),2)+1 -> 46286 | T3: =IFERROR(MATCH($R$3,Weeks!$A$7:$A$59,0),0) -> 1
B4: ="This week · "&TEXT($R$3,"d mmm")&" – "&TEXT($R$3+6,"d mmm yyyy")&" · updates automatically every Monday" -> This week · 21 Sep – 27 Sep 2026 · updates automatically every Monday
B6: GOOD BLOCKS | E6: CREW EARNED (SO'M) | H6: CREW-DAYS | K6: REJECT RATE | N6: ADVANCES THIS WEEK | Q6: OWED TO CREW NOW
B7: {=IF($T$3=0,0,INDEX(Weeks!$E$7:$E$59,$T$3))} -> 11857 | E7: {=IF($T$3=0,0,INDEX(Weeks!$G$7:$G$59,$T$3))} -> 5928500 | H7: {=IF($T$3=0,0,INDEX(Weeks!$H$7:$H$59,$T$3))} -> 24 | K7: {=IF($T$3=0,"",INDEX(Weeks!$I$7:$I$59,$T$3))} -> 0.010101853 | N7: =SUMIFS('Cash Ledger'!$E$7:$E$1006,'Cash Ledger'!$D$7:$D$1006,"Advance",'Cash Ledger'!$B$7:$B$1006,">="&$R$3,'Cash Ledger'!$B$7:$B$1006,"<="&($R$3+6)) -> 650000 | Q7: =SUMIF($O$30:$O$41,">0") -> 5278500
B8: {="of "&TEXT(IF($T$3=0,0,INDEX(Weeks!$C$7:$C$59,$T$3)),"#,##0")&" moulded"} -> of 11,978 moulded | E8: ="the week's pot, shared by days" -> the week's pot, shared by days | H8: =IF(N(H7)=0,"no days logged yet",TEXT(B7/H7,"#,##0")&" good blocks per crew-day") -> 494 good blocks per crew-day | K8: =IF(N(K7)=0,"no production yet",IF(K7>RejectAlarm,"⚠ above the "&TEXT(RejectAlarm,"0%")&" alarm","normal · alarm at "&TEXT(RejectAlarm,"0%"))) -> normal · alarm at 8% | N8: =COUNTIFS('Cash Ledger'!$D$7:$D$1006,"Advance",'Cash Ledger'!$B$7:$B$1006,">="&$R$3,'Cash Ledger'!$B$7:$B$1006,"<="&($R$3+6))&" advance(s) given" -> 2 advance(s) given | Q8: ="earned so far minus cash given" -> earned so far minus cash given
B11: Workbook health | K11: Quick actions
B12: =Checks!C5 -> ALL CHECKS OK | K12: › Log today's production | O12: Blocks moulded, broken, who came
B13: =Checks!B8 -> Worker list is clean (names unique, status set) | I13: =IF(Checks!C8="OK","✓ OK",Checks!C8) -> ✓ OK | K13: › Record an advance | O13: Date, worker, 'Advance', amount
B14: =Checks!B9 -> Daily Log rows without problems | I14: =IF(Checks!C9="OK","✓ OK",Checks!C9) -> ✓ OK | K14: › Run payday | O14: Pay the TO PAY column, copy the list
B15: =Checks!B10 -> Cash Ledger entries are complete and valid | I15: =IF(Checks!C10="OK","✓ OK",Checks!C10) -> ✓ OK | K15: › Print a payslip | O15: Pick week + worker, print, sign
B16: =Checks!B11 -> Every week's pot is shared out | I16: =IF(Checks!C11="OK","✓ OK",Checks!C11) -> ✓ OK | K16: › See one worker's history | O16: Week-by-week earnings and cash
B17: =Checks!B12 -> Worker shares add up to each week's pot | I17: =IF(Checks!C12="OK","✓ OK",Checks!C12) -> ✓ OK | K17: › Add or remove a worker | O17: Fill a slot, or set status to Left
B18: =Checks!B13 -> A pay rate is set | I18: =IF(Checks!C13="OK","✓ OK",Checks!C13) -> ✓ OK | K18: › Change the pay rate | O18: Add a new row with a start date
B19: =Checks!B14 -> Rate dates are in order, oldest first | I19: =IF(Checks!C14="OK","✓ OK",Checks!C14) -> ✓ OK | K19: › How this works | O19: Step-by-step instructions
B20: =Checks!B15 -> Cash Ledger has room left | I20: =IF(Checks!C15="OK","✓ OK",Checks!C15) -> ✓ OK
B21: =Checks!B16 -> Worker slots left | I21: =IF(Checks!C16="OK","✓ OK",Checks!C16) -> ✓ OK
B22: =Checks!B19 -> Advances bigger than what the worker had earned so far | I22: =Checks!C19 -> 0
B23: =Checks!B20 -> Weeks with a high reject rate | I23: =Checks!C20 -> 0
B27: Crew this week
B28: ="Owed now = everything earned up to this week, minus all cash given. Positive = you owe the worker." -> Owed now = everything earned up to this week, minus all cash given. Positive = you owe the worker.
B29: WORKER | F29: DAYS | I29: EARNED THIS WEEK | L29: ADVANCES THIS WEEK | O29: OWED NOW | R29: STATUS
B30: =IF(Workers!$B$6<>"",Workers!$B$6,"") -> Davlatbek | F30: {=IF($B30="","",IF($T$3=0,0,INDEX(Weeks!$L$7:$W$59,$T$3,1)))} -> 6 | I30: {=IF($B30="","",IF($T$3=0,0,INDEX(Weeks!$X$7:$AI$59,$T$3,1)))} -> 1482125 | L30: =IF($B30="","",SUMIFS('Cash Ledger'!$E$7:$E$1006,'Cash Ledger'!$I$7:$I$1006,Workers!$A$6,'Cash Ledger'!$D$7:$D$1006,"Advance",'Cash Ledger'!$B$7:$B$1006,">="&$R$3,'Cash Ledger'!$B$7:$B$1006,"<="&($R$3+6))) -> 150000 | O30: {=IF($B30="","",SUMPRODUCT((Weeks!$A$7:$A$59<=$R$3)*(Weeks!$X$5:$AI$5=Workers!$A$6)*Weeks!$X$7:$AI$59)-SUMIFS('Cash Ledger'!$E$7:$E$1006,'Cash Ledger'!$I$7:$I$1006,Workers!$A$6))} -> 1332125 | R30: =IF($B30="","",IF(Workers!$C$6="Left","Left",IF(ROUND($O30,0)>0,"To pay",IF(ROUND($O30,0)<0,"Owes you","Settled")))) -> To pay
B31: =IF(Workers!$B$7<>"",Workers!$B$7,"") -> Xusanboy | F31: {=IF($B31="","",IF($T$3=0,0,INDEX(Weeks!$L$7:$W$59,$T$3,2)))} -> 6 | I31: {=IF($B31="","",IF($T$3=0,0,INDEX(Weeks!$X$7:$AI$59,$T$3,2)))} -> 1482125 | L31: =IF($B31="","",SUMIFS('Cash Ledger'!$E$7:$E$1006,'Cash Ledger'!$I$7:$I$1006,Workers!$A$7,'Cash Ledger'!$D$7:$D$1006,"Advance",'Cash Ledger'!$B$7:$B$1006,">="&$R$3,'Cash Ledger'!$B$7:$B$1006,"<="&($R$3+6))) -> 500000 | O31: {=IF($B31="","",SUMPRODUCT((Weeks!$A$7:$A$59<=$R$3)*(Weeks!$X$5:$AI$5=Workers!$A$7)*Weeks!$X$7:$AI$59)-SUMIFS('Cash Ledger'!$E$7:$E$1006,'Cash Ledger'!$I$7:$I$1006,Workers!$A$7))} -> 982125 | R31: =IF($B31="","",IF(Workers!$C$7="Left","Left",IF(ROUND($O31,0)>0,"To pay",IF(ROUND($O31,0)<0,"Owes you","Settled")))) -> To pay
B32: =IF(Workers!$B$8<>"",Workers!$B$8,"") -> Oybek | F32: {=IF($B32="","",IF($T$3=0,0,INDEX(Weeks!$L$7:$W$59,$T$3,3)))} -> 6 | I32: {=IF($B32="","",IF($T$3=0,0,INDEX(Weeks!$X$7:$AI$59,$T$3,3)))} -> 1482125 | L32: =IF($B32="","",SUMIFS('Cash Ledger'!$E$7:$E$1006,'Cash Ledger'!$I$7:$I$1006,Workers!$A$8,'Cash Ledger'!$D$7:$D$1006,"Advance",'Cash Ledger'!$B$7:$B$1006,">="&$R$3,'Cash Ledger'!$B$7:$B$1006,"<="&($R$3+6))) -> 0 | O32: {=IF($B32="","",SUMPRODUCT((Weeks!$A$7:$A$59<=$R$3)*(Weeks!$X$5:$AI$5=Workers!$A$8)*Weeks!$X$7:$AI$59)-SUMIFS('Cash Ledger'!$E$7:$E$1006,'Cash Ledger'!$I$7:$I$1006,Workers!$A$8))} -> 1482125 | R32: =IF($B32="","",IF(Workers!$C$8="Left","Left",IF(ROUND($O32,0)>0,"To pay",IF(ROUND($O32,0)<0,"Owes you","Settled")))) -> To pay
B33: =IF(Workers!$B$9<>"",Workers!$B$9,"") -> Abdurashid | F33: {=IF($B33="","",IF($T$3=0,0,INDEX(Weeks!$L$7:$W$59,$T$3,4)))} -> 6 | I33: {=IF($B33="","",IF($T$3=0,0,INDEX(Weeks!$X$7:$AI$59,$T$3,4)))} -> 1482125 | L33: =IF($B33="","",SUMIFS('Cash Ledger'!$E$7:$E$1006,'Cash Ledger'!$I$7:$I$1006,Workers!$A$9,'Cash Ledger'!$D$7:$D$1006,"Advance",'Cash Ledger'!$B$7:$B$1006,">="&$R$3,'Cash Ledger'!$B$7:$B$1006,"<="&($R$3+6))) -> 0 | O33: {=IF($B33="","",SUMPRODUCT((Weeks!$A$7:$A$59<=$R$3)*(Weeks!$X$5:$AI$5=Workers!$A$9)*Weeks!$X$7:$AI$59)-SUMIFS('Cash Ledger'!$E$7:$E$1006,'Cash Ledger'!$I$7:$I$1006,Workers!$A$9))} -> 1482125 | R33: =IF($B33="","",IF(Workers!$C$9="Left","Left",IF(ROUND($O33,0)>0,"To pay",IF(ROUND($O33,0)<0,"Owes you","Settled")))) -> To pay
B34: =IF(Workers!$B$10<>"",Workers!$B$10,"") | F34: {=IF($B34="","",IF($T$3=0,0,INDEX(Weeks!$L$7:$W$59,$T$3,5)))} | I34: {=IF($B34="","",IF($T$3=0,0,INDEX(Weeks!$X$7:$AI$59,$T$3,5)))} | L34: =IF($B34="","",SUMIFS('Cash Ledger'!$E$7:$E$1006,'Cash Ledger'!$I$7:$I$1006,Workers!$A$10,'Cash Ledger'!$D$7:$D$1006,"Advance",'Cash Ledger'!$B$7:$B$1006,">="&$R$3,'Cash Ledger'!$B$7:$B$1006,"<="&($R$3+6))) | O34: {=IF($B34="","",SUMPRODUCT((Weeks!$A$7:$A$59<=$R$3)*(Weeks!$X$5:$AI$5=Workers!$A$10)*Weeks!$X$7:$AI$59)-SUMIFS('Cash Ledger'!$E$7:$E$1006,'Cash Ledger'!$I$7:$I$1006,Workers!$A$10))} | R34: =IF($B34="","",IF(Workers!$C$10="Left","Left",IF(ROUND($O34,0)>0,"To pay",IF(ROUND($O34,0)<0,"Owes you","Settled"))))
B35: =IF(Workers!$B$11<>"",Workers!$B$11,"") | F35: {=IF($B35="","",IF($T$3=0,0,INDEX(Weeks!$L$7:$W$59,$T$3,6)))} | I35: {=IF($B35="","",IF($T$3=0,0,INDEX(Weeks!$X$7:$AI$59,$T$3,6)))} | L35: =IF($B35="","",SUMIFS('Cash Ledger'!$E$7:$E$1006,'Cash Ledger'!$I$7:$I$1006,Workers!$A$11,'Cash Ledger'!$D$7:$D$1006,"Advance",'Cash Ledger'!$B$7:$B$1006,">="&$R$3,'Cash Ledger'!$B$7:$B$1006,"<="&($R$3+6))) | O35: {=IF($B35="","",SUMPRODUCT((Weeks!$A$7:$A$59<=$R$3)*(Weeks!$X$5:$AI$5=Workers!$A$11)*Weeks!$X$7:$AI$59)-SUMIFS('Cash Ledger'!$E$7:$E$1006,'Cash Ledger'!$I$7:$I$1006,Workers!$A$11))} | R35: =IF($B35="","",IF(Workers!$C$11="Left","Left",IF(ROUND($O35,0)>0,"To pay",IF(ROUND($O35,0)<0,"Owes you","Settled"))))
B36: =IF(Workers!$B$12<>"",Workers!$B$12,"") | F36: {=IF($B36="","",IF($T$3=0,0,INDEX(Weeks!$L$7:$W$59,$T$3,7)))} | I36: {=IF($B36="","",IF($T$3=0,0,INDEX(Weeks!$X$7:$AI$59,$T$3,7)))} | L36: =IF($B36="","",SUMIFS('Cash Ledger'!$E$7:$E$1006,'Cash Ledger'!$I$7:$I$1006,Workers!$A$12,'Cash Ledger'!$D$7:$D$1006,"Advance",'Cash Ledger'!$B$7:$B$1006,">="&$R$3,'Cash Ledger'!$B$7:$B$1006,"<="&($R$3+6))) | O36: {=IF($B36="","",SUMPRODUCT((Weeks!$A$7:$A$59<=$R$3)*(Weeks!$X$5:$AI$5=Workers!$A$12)*Weeks!$X$7:$AI$59)-SUMIFS('Cash Ledger'!$E$7:$E$1006,'Cash Ledger'!$I$7:$I$1006,Workers!$A$12))} | R36: =IF($B36="","",IF(Workers!$C$12="Left","Left",IF(ROUND($O36,0)>0,"To pay",IF(ROUND($O36,0)<0,"Owes you","Settled"))))
B37: =IF(Workers!$B$13<>"",Workers!$B$13,"") | F37: {=IF($B37="","",IF($T$3=0,0,INDEX(Weeks!$L$7:$W$59,$T$3,8)))} | I37: {=IF($B37="","",IF($T$3=0,0,INDEX(Weeks!$X$7:$AI$59,$T$3,8)))} | L37: =IF($B37="","",SUMIFS('Cash Ledger'!$E$7:$E$1006,'Cash Ledger'!$I$7:$I$1006,Workers!$A$13,'Cash Ledger'!$D$7:$D$1006,"Advance",'Cash Ledger'!$B$7:$B$1006,">="&$R$3,'Cash Ledger'!$B$7:$B$1006,"<="&($R$3+6))) | O37: {=IF($B37="","",SUMPRODUCT((Weeks!$A$7:$A$59<=$R$3)*(Weeks!$X$5:$AI$5=Workers!$A$13)*Weeks!$X$7:$AI$59)-SUMIFS('Cash Ledger'!$E$7:$E$1006,'Cash Ledger'!$I$7:$I$1006,Workers!$A$13))} | R37: =IF($B37="","",IF(Workers!$C$13="Left","Left",IF(ROUND($O37,0)>0,"To pay",IF(ROUND($O37,0)<0,"Owes you","Settled"))))
B38: =IF(Workers!$B$14<>"",Workers!$B$14,"") | F38: {=IF($B38="","",IF($T$3=0,0,INDEX(Weeks!$L$7:$W$59,$T$3,9)))} | I38: {=IF($B38="","",IF($T$3=0,0,INDEX(Weeks!$X$7:$AI$59,$T$3,9)))} | L38: =IF($B38="","",SUMIFS('Cash Ledger'!$E$7:$E$1006,'Cash Ledger'!$I$7:$I$1006,Workers!$A$14,'Cash Ledger'!$D$7:$D$1006,"Advance",'Cash Ledger'!$B$7:$B$1006,">="&$R$3,'Cash Ledger'!$B$7:$B$1006,"<="&($R$3+6))) | O38: {=IF($B38="","",SUMPRODUCT((Weeks!$A$7:$A$59<=$R$3)*(Weeks!$X$5:$AI$5=Workers!$A$14)*Weeks!$X$7:$AI$59)-SUMIFS('Cash Ledger'!$E$7:$E$1006,'Cash Ledger'!$I$7:$I$1006,Workers!$A$14))} | R38: =IF($B38="","",IF(Workers!$C$14="Left","Left",IF(ROUND($O38,0)>0,"To pay",IF(ROUND($O38,0)<0,"Owes you","Settled"))))
B39: =IF(Workers!$B$15<>"",Workers!$B$15,"") | F39: {=IF($B39="","",IF($T$3=0,0,INDEX(Weeks!$L$7:$W$59,$T$3,10)))} | I39: {=IF($B39="","",IF($T$3=0,0,INDEX(Weeks!$X$7:$AI$59,$T$3,10)))} | L39: =IF($B39="","",SUMIFS('Cash Ledger'!$E$7:$E$1006,'Cash Ledger'!$I$7:$I$1006,Workers!$A$15,'Cash Ledger'!$D$7:$D$1006,"Advance",'Cash Ledger'!$B$7:$B$1006,">="&$R$3,'Cash Ledger'!$B$7:$B$1006,"<="&($R$3+6))) | O39: {=IF($B39="","",SUMPRODUCT((Weeks!$A$7:$A$59<=$R$3)*(Weeks!$X$5:$AI$5=Workers!$A$15)*Weeks!$X$7:$AI$59)-SUMIFS('Cash Ledger'!$E$7:$E$1006,'Cash Ledger'!$I$7:$I$1006,Workers!$A$15))} | R39: =IF($B39="","",IF(Workers!$C$15="Left","Left",IF(ROUND($O39,0)>0,"To pay",IF(ROUND($O39,0)<0,"Owes you","Settled"))))
B40: =IF(Workers!$B$16<>"",Workers!$B$16,"") | F40: {=IF($B40="","",IF($T$3=0,0,INDEX(Weeks!$L$7:$W$59,$T$3,11)))} | I40: {=IF($B40="","",IF($T$3=0,0,INDEX(Weeks!$X$7:$AI$59,$T$3,11)))} | L40: =IF($B40="","",SUMIFS('Cash Ledger'!$E$7:$E$1006,'Cash Ledger'!$I$7:$I$1006,Workers!$A$16,'Cash Ledger'!$D$7:$D$1006,"Advance",'Cash Ledger'!$B$7:$B$1006,">="&$R$3,'Cash Ledger'!$B$7:$B$1006,"<="&($R$3+6))) | O40: {=IF($B40="","",SUMPRODUCT((Weeks!$A$7:$A$59<=$R$3)*(Weeks!$X$5:$AI$5=Workers!$A$16)*Weeks!$X$7:$AI$59)-SUMIFS('Cash Ledger'!$E$7:$E$1006,'Cash Ledger'!$I$7:$I$1006,Workers!$A$16))} | R40: =IF($B40="","",IF(Workers!$C$16="Left","Left",IF(ROUND($O40,0)>0,"To pay",IF(ROUND($O40,0)<0,"Owes you","Settled"))))
B41: =IF(Workers!$B$17<>"",Workers!$B$17,"") | F41: {=IF($B41="","",IF($T$3=0,0,INDEX(Weeks!$L$7:$W$59,$T$3,12)))} | I41: {=IF($B41="","",IF($T$3=0,0,INDEX(Weeks!$X$7:$AI$59,$T$3,12)))} | L41: =IF($B41="","",SUMIFS('Cash Ledger'!$E$7:$E$1006,'Cash Ledger'!$I$7:$I$1006,Workers!$A$17,'Cash Ledger'!$D$7:$D$1006,"Advance",'Cash Ledger'!$B$7:$B$1006,">="&$R$3,'Cash Ledger'!$B$7:$B$1006,"<="&($R$3+6))) | O41: {=IF($B41="","",SUMPRODUCT((Weeks!$A$7:$A$59<=$R$3)*(Weeks!$X$5:$AI$5=Workers!$A$17)*Weeks!$X$7:$AI$59)-SUMIFS('Cash Ledger'!$E$7:$E$1006,'Cash Ledger'!$I$7:$I$1006,Workers!$A$17))} | R41: =IF($B41="","",IF(Workers!$C$17="Left","Left",IF(ROUND($O41,0)>0,"To pay",IF(ROUND($O41,0)<0,"Owes you","Settled"))))
B42: =IF(COUNTA(Workers!$B$6:$B$17)<12,"+ add another worker on the Workers page","") -> + add another worker on the Workers page
B44: Donabay · block plant payroll · type only in the tinted cells on each page

Sheet Daily Log
A1: ◆ Donabay | D1: Home | F1: Daily Log | G1: Cash Ledger | I1: Weekly Pay | K1: Payslip | X1: Workers | Y1: Settings | AA1: Guide | AC1: · | AD1: History | AF1: Weeks | AH1: Checks
A2: Daily Log
A3: One row per day. Fill: blocks moulded, blocks broken, and who worked (1 = full day, 0.5 = half day, empty = absent).
A4: All time | C4: =SUM(C7:C377) -> 11978 | D4: =SUM(D7:D377) -> 121 | E4: =SUM(E7:E377) -> 11857 | F4: =SUM(F7:F377) -> 11857 | G4: Attendance: 1 full day, 0.5 half day, empty = absent | U4: =SUM(U7:U377) -> 5928500
A5: Today's row is green · Ctrl+↓ jumps down | G5: =IF(Workers!$B$6="","",Workers!$B$6) -> Davlatbek | H5: =IF(Workers!$B$7="","",Workers!$B$7) -> Xusanboy | I5: =IF(Workers!$B$8="","",Workers!$B$8) -> Oybek | J5: =IF(Workers!$B$9="","",Workers!$B$9) -> Abdurashid | K5: =IF(Workers!$B$10="","",Workers!$B$10) | L5: =IF(Workers!$B$11="","",Workers!$B$11) | M5: =IF(Workers!$B$12="","",Workers!$B$12) | N5: =IF(Workers!$B$13="","",Workers!$B$13) | O5: =IF(Workers!$B$14="","",Workers!$B$14) | P5: =IF(Workers!$B$15="","",Workers!$B$15) | Q5: =IF(Workers!$B$16="","",Workers!$B$16) | R5: =IF(Workers!$B$17="","",Workers!$B$17)
A6: Date | B6: Day | C6: Moulded | D6: Broken | E6: Good | F6: Paid blocks | G6: =IF(Workers!$B$6="",Workers!$A$6,Workers!$B$6) -> Davlatbek | H6: =IF(Workers!$B$7="",Workers!$A$7,Workers!$B$7) -> Xusanboy | I6: =IF(Workers!$B$8="",Workers!$A$8,Workers!$B$8) -> Oybek | J6: =IF(Workers!$B$9="",Workers!$A$9,Workers!$B$9) -> Abdurashid | K6: =IF(Workers!$B$10="",Workers!$A$10,Workers!$B$10) -> W05 | L6: =IF(Workers!$B$11="",Workers!$A$11,Workers!$B$11) -> W06 | M6: =IF(Workers!$B$12="",Workers!$A$12,Workers!$B$12) -> W07 | N6: =IF(Workers!$B$13="",Workers!$A$13,Workers!$B$13) -> W08 | O6: =IF(Workers!$B$14="",Workers!$A$14,Workers!$B$14) -> W09 | P6: =IF(Workers!$B$15="",Workers!$A$15,Workers!$B$15) -> W10 | Q6: =IF(Workers!$B$16="",Workers!$A$16,Workers!$B$16) -> W11 | R6: =IF(Workers!$B$17="",Workers!$A$17,Workers!$B$17) -> W12 | S6: Crew-days | T6: Rate | U6: Pay value | V6: Week of | W6: Check | X6: Notes
A7: 46286 | B7: =CHOOSE(WEEKDAY($A7,2),"Mon","Tue","Wed","Thu","Fri","Sat","Sun") -> Mon | C7: 1500 | D7: 10 | E7: =IF($C7="","",$C7-N($D7)) -> 1490 | F7: =IF($C7="","",$C7-MAX(0,N($D7)-BreakAllow*$C7)) -> 1490 | G7: 1 | H7: 1 | I7: 1 | J7: 1 | S7: =IF(COUNT(G7:R7)=0,"",SUM(G7:R7)) -> 4 | T7: =IF($C7="","",IFERROR(INDEX(RateValues,MATCH(SUMPRODUCT(MAX((RateDates<=$A7)*RateDates)),RateDates,0)),0)) -> 500 | U7: =IF($C7="","",$F7*$T7) -> 745000 | V7: =$A7-WEEKDAY($A7,2)+1 -> 46286 | W7: {=IF(AND($C7="",S7=""),"",IF(AND(N($C7)>0,N(S7)=0),"nobody marked present",IF(N($D7)>N($C7),"more broken than moulded",IF(AND($C7="",N(S7)>0),"attendance marked but no blocks entered",IF(AND(N($C7)>0,N(T7)=0),"no pay rate for this date - see Settings",IF(SUMPRODUCT((G7:R7<>"")*(G$5:R$5=""))>0,"attendance in an empty worker slot",""))))))}
A8: 46287 | B8: =CHOOSE(WEEKDAY($A8,2),"Mon","Tue","Wed","Thu","Fri","Sat","Sun") -> Tue | C8: 2000 | D8: 21 | E8: =IF($C8="","",$C8-N($D8)) -> 1979 | F8: =IF($C8="","",$C8-MAX(0,N($D8)-BreakAllow*$C8)) -> 1979 | G8: 1 | H8: 1 | I8: 1 | J8: 1 | S8: =IF(COUNT(G8:R8)=0,"",SUM(G8:R8)) -> 4 | T8: =IF($C8="","",IFERROR(INDEX(RateValues,MATCH(SUMPRODUCT(MAX((RateDates<=$A8)*RateDates)),RateDates,0)),0)) -> 500 | U8: =IF($C8="","",$F8*$T8) -> 989500 | V8: =$A8-WEEKDAY($A8,2)+1 -> 46286 | W8: {=IF(AND($C8="",S8=""),"",IF(AND(N($C8)>0,N(S8)=0),"nobody marked present",IF(N($D8)>N($C8),"more broken than moulded",IF(AND($C8="",N(S8)>0),"attendance marked but no blocks entered",IF(AND(N($C8)>0,N(T8)=0),"no pay rate for this date - see Settings",IF(SUMPRODUCT((G8:R8<>"")*(G$5:R$5=""))>0,"attendance in an empty worker slot",""))))))}
A9: 46288 | B9: =CHOOSE(WEEKDAY($A9,2),"Mon","Tue","Wed","Thu","Fri","Sat","Sun") -> Wed | C9: 2300 | D9: 25 | E9: =IF($C9="","",$C9-N($D9)) -> 2275 | F9: =IF($C9="","",$C9-MAX(0,N($D9)-BreakAllow*$C9)) -> 2275 | G9: 1 | H9: 1 | I9: 1 | J9: 1 | S9: =IF(COUNT(G9:R9)=0,"",SUM(G9:R9)) -> 4 | T9: =IF($C9="","",IFERROR(INDEX(RateValues,MATCH(SUMPRODUCT(MAX((RateDates<=$A9)*RateDates)),RateDates,0)),0)) -> 500 | U9: =IF($C9="","",$F9*$T9) -> 1137500 | V9: =$A9-WEEKDAY($A9,2)+1 -> 46286 | W9: {=IF(AND($C9="",S9=""),"",IF(AND(N($C9)>0,N(S9)=0),"nobody marked present",IF(N($D9)>N($C9),"more broken than moulded",IF(AND($C9="",N(S9)>0),"attendance marked but no blocks entered",IF(AND(N($C9)>0,N(T9)=0),"no pay rate for this date - see Settings",IF(SUMPRODUCT((G9:R9<>"")*(G$5:R$5=""))>0,"attendance in an empty worker slot",""))))))}
A10: 46289 | B10: =CHOOSE(WEEKDAY($A10,2),"Mon","Tue","Wed","Thu","Fri","Sat","Sun") -> Thu | C10: 1900 | D10: 20 | E10: =IF($C10="","",$C10-N($D10)) -> 1880 | F10: =IF($C10="","",$C10-MAX(0,N($D10)-BreakAllow*$C10)) -> 1880 | G10: 1 | H10: 1 | I10: 1 | J10: 1 | S10: =IF(COUNT(G10:R10)=0,"",SUM(G10:R10)) -> 4 | T10: =IF($C10="","",IFERROR(INDEX(RateValues,MATCH(SUMPRODUCT(MAX((RateDates<=$A10)*RateDates)),RateDates,0)),0)) -> 500 | U10: =IF($C10="","",$F10*$T10) -> 940000 | V10: =$A10-WEEKDAY($A10,2)+1 -> 46286 | W10: {=IF(AND($C10="",S10=""),"",IF(AND(N($C10)>0,N(S10)=0),"nobody marked present",IF(N($D10)>N($C10),"more broken than moulded",IF(AND($C10="",N(S10)>0),"attendance marked but no blocks entered",IF(AND(N($C10)>0,N(T10)=0),"no pay rate for this date - see Settings",IF(SUMPRODUCT((G10:R10<>"")*(G$5:R$5=""))>0,"attendance in an empty worker slot",""))))))}
A11: 46290 | B11: =CHOOSE(WEEKDAY($A11,2),"Mon","Tue","Wed","Thu","Fri","Sat","Sun") -> Fri | C11: 2278 | D11: 25 | E11: =IF($C11="","",$C11-N($D11)) -> 2253 | F11: =IF($C11="","",$C11-MAX(0,N($D11)-BreakAllow*$C11)) -> 2253 | G11: 1 | H11: 1 | I11: 1 | J11: 1 | S11: =IF(COUNT(G11:R11)=0,"",SUM(G11:R11)) -> 4 | T11: =IF($C11="","",IFERROR(INDEX(RateValues,MATCH(SUMPRODUCT(MAX((RateDates<=$A11)*RateDates)),RateDates,0)),0)) -> 500 | U11: =IF($C11="","",$F11*$T11) -> 1126500 | V11: =$A11-WEEKDAY($A11,2)+1 -> 46286 | W11: {=IF(AND($C11="",S11=""),"",IF(AND(N($C11)>0,N(S11)=0),"nobody marked present",IF(N($D11)>N($C11),"more broken than moulded",IF(AND($C11="",N(S11)>0),"attendance marked but no blocks entered",IF(AND(N($C11)>0,N(T11)=0),"no pay rate for this date - see Settings",IF(SUMPRODUCT((G11:R11<>"")*(G$5:R$5=""))>0,"attendance in an empty worker slot",""))))))}
A12: 46291 | B12: =CHOOSE(WEEKDAY($A12,2),"Mon","Tue","Wed","Thu","Fri","Sat","Sun") -> Sat | C12: 2000 | D12: 20 | E12: =IF($C12="","",$C12-N($D12)) -> 1980 | F12: =IF($C12="","",$C12-MAX(0,N($D12)-BreakAllow*$C12)) -> 1980 | G12: 1 | H12: 1 | I12: 1 | J12: 1 | S12: =IF(COUNT(G12:R12)=0,"",SUM(G12:R12)) -> 4 | T12: =IF($C12="","",IFERROR(INDEX(RateValues,MATCH(SUMPRODUCT(MAX((RateDates<=$A12)*RateDates)),RateDates,0)),0)) -> 500 | U12: =IF($C12="","",$F12*$T12) -> 990000 | V12: =$A12-WEEKDAY($A12,2)+1 -> 46286 | W12: {=IF(AND($C12="",S12=""),"",IF(AND(N($C12)>0,N(S12)=0),"nobody marked present",IF(N($D12)>N($C12),"more broken than moulded",IF(AND($C12="",N(S12)>0),"attendance marked but no blocks entered",IF(AND(N($C12)>0,N(T12)=0),"no pay rate for this date - see Settings",IF(SUMPRODUCT((G12:R12<>"")*(G$5:R$5=""))>0,"attendance in an empty worker slot",""))))))}
A13: 46292 | B13: =CHOOSE(WEEKDAY($A13,2),"Mon","Tue","Wed","Thu","Fri","Sat","Sun") -> Sun | E13: =IF($C13="","",$C13-N($D13)) | F13: =IF($C13="","",$C13-MAX(0,N($D13)-BreakAllow*$C13)) | S13: =IF(COUNT(G13:R13)=0,"",SUM(G13:R13)) | T13: =IF($C13="","",IFERROR(INDEX(RateValues,MATCH(SUMPRODUCT(MAX((RateDates<=$A13)*RateDates)),RateDates,0)),0)) | U13: =IF($C13="","",$F13*$T13) | V13: =$A13-WEEKDAY($A13,2)+1 -> 46286 | W13: {=IF(AND($C13="",S13=""),"",IF(AND(N($C13)>0,N(S13)=0),"nobody marked present",IF(N($D13)>N($C13),"more broken than moulded",IF(AND($C13="",N(S13)>0),"attendance marked but no blocks entered",IF(AND(N($C13)>0,N(T13)=0),"no pay rate for this date - see Settings",IF(SUMPRODUCT((G13:R13<>"")*(G$5:R$5=""))>0,"attendance in an empty worker slot",""))))))}
A14: 46293 | B14: =CHOOSE(WEEKDAY($A14,2),"Mon","Tue","Wed","Thu","Fri","Sat","Sun") -> Mon | E14: =IF($C14="","",$C14-N($D14)) | F14: =IF($C14="","",$C14-MAX(0,N($D14)-BreakAllow*$C14)) | S14: =IF(COUNT(G14:R14)=0,"",SUM(G14:R14)) | T14: =IF($C14="","",IFERROR(INDEX(RateValues,MATCH(SUMPRODUCT(MAX((RateDates<=$A14)*RateDates)),RateDates,0)),0)) | U14: =IF($C14="","",$F14*$T14) | V14: =$A14-WEEKDAY($A14,2)+1 -> 46293 | W14: {=IF(AND($C14="",S14=""),"",IF(AND(N($C14)>0,N(S14)=0),"nobody marked present",IF(N($D14)>N($C14),"more broken than moulded",IF(AND($C14="",N(S14)>0),"attendance marked but no blocks entered",IF(AND(N($C14)>0,N(T14)=0),"no pay rate for this date - see Settings",IF(SUMPRODUCT((G14:R14<>"")*(G$5:R$5=""))>0,"attendance in an empty worker slot",""))))))}
A15: 46294 | B15: =CHOOSE(WEEKDAY($A15,2),"Mon","Tue","Wed","Thu","Fri","Sat","Sun") -> Tue | E15: =IF($C15="","",$C15-N($D15)) | F15: =IF($C15="","",$C15-MAX(0,N($D15)-BreakAllow*$C15)) | S15: =IF(COUNT(G15:R15)=0,"",SUM(G15:R15)) | T15: =IF($C15="","",IFERROR(INDEX(RateValues,MATCH(SUMPRODUCT(MAX((RateDates<=$A15)*RateDates)),RateDates,0)),0)) | U15: =IF($C15="","",$F15*$T15) | V15: =$A15-WEEKDAY($A15,2)+1 -> 46293 | W15: {=IF(AND($C15="",S15=""),"",IF(AND(N($C15)>0,N(S15)=0),"nobody marked present",IF(N($D15)>N($C15),"more broken than moulded",IF(AND($C15="",N(S15)>0),"attendance marked but no blocks entered",IF(AND(N($C15)>0,N(T15)=0),"no pay rate for this date - see Settings",IF(SUMPRODUCT((G15:R15<>"")*(G$5:R$5=""))>0,"attendance in an empty worker slot",""))))))}
A16: 46295 | B16: =CHOOSE(WEEKDAY($A16,2),"Mon","Tue","Wed","Thu","Fri","Sat","Sun") -> Wed | E16: =IF($C16="","",$C16-N($D16)) | F16: =IF($C16="","",$C16-MAX(0,N($D16)-BreakAllow*$C16)) | S16: =IF(COUNT(G16:R16)=0,"",SUM(G16:R16)) | T16: =IF($C16="","",IFERROR(INDEX(RateValues,MATCH(SUMPRODUCT(MAX((RateDates<=$A16)*RateDates)),RateDates,0)),0)) | U16: =IF($C16="","",$F16*$T16) | V16: =$A16-WEEKDAY($A16,2)+1 -> 46293 | W16: {=IF(AND($C16="",S16=""),"",IF(AND(N($C16)>0,N(S16)=0),"nobody marked present",IF(N($D16)>N($C16),"more broken than moulded",IF(AND($C16="",N(S16)>0),"attendance marked but no blocks entered",IF(AND(N($C16)>0,N(T16)=0),"no pay rate for this date - see Settings",IF(SUMPRODUCT((G16:R16<>"")*(G$5:R$5=""))>0,"attendance in an empty worker slot",""))))))}
A17: 46296 | B17: =CHOOSE(WEEKDAY($A17,2),"Mon","Tue","Wed","Thu","Fri","Sat","Sun") -> Thu | E17: =IF($C17="","",$C17-N($D17)) | F17: =IF($C17="","",$C17-MAX(0,N($D17)-BreakAllow*$C17)) | S17: =IF(COUNT(G17:R17)=0,"",SUM(G17:R17)) | T17: =IF($C17="","",IFERROR(INDEX(RateValues,MATCH(SUMPRODUCT(MAX((RateDates<=$A17)*RateDates)),RateDates,0)),0)) | U17: =IF($C17="","",$F17*$T17) | V17: =$A17-WEEKDAY($A17,2)+1 -> 46293 | W17: {=IF(AND($C17="",S17=""),"",IF(AND(N($C17)>0,N(S17)=0),"nobody marked present",IF(N($D17)>N($C17),"more broken than moulded",IF(AND($C17="",N(S17)>0),"attendance marked but no blocks entered",IF(AND(N($C17)>0,N(T17)=0),"no pay rate for this date - see Settings",IF(SUMPRODUCT((G17:R17<>"")*(G$5:R$5=""))>0,"attendance in an empty worker slot",""))))))}
A18: 46297 | B18: =CHOOSE(WEEKDAY($A18,2),"Mon","Tue","Wed","Thu","Fri","Sat","Sun") -> Fri | E18: =IF($C18="","",$C18-N($D18)) | F18: =IF($C18="","",$C18-MAX(0,N($D18)-BreakAllow*$C18)) | S18: =IF(COUNT(G18:R18)=0,"",SUM(G18:R18)) | T18: =IF($C18="","",IFERROR(INDEX(RateValues,MATCH(SUMPRODUCT(MAX((RateDates<=$A18)*RateDates)),RateDates,0)),0)) | U18: =IF($C18="","",$F18*$T18) | V18: =$A18-WEEKDAY($A18,2)+1 -> 46293 | W18: {=IF(AND($C18="",S18=""),"",IF(AND(N($C18)>0,N(S18)=0),"nobody marked present",IF(N($D18)>N($C18),"more broken than moulded",IF(AND($C18="",N(S18)>0),"attendance marked but no blocks entered",IF(AND(N($C18)>0,N(T18)=0),"no pay rate for this date - see Settings",IF(SUMPRODUCT((G18:R18<>"")*(G$5:R$5=""))>0,"attendance in an empty worker slot",""))))))}
A19: 46298 | B19: =CHOOSE(WEEKDAY($A19,2),"Mon","Tue","Wed","Thu","Fri","Sat","Sun") -> Sat | E19: =IF($C19="","",$C19-N($D19)) | F19: =IF($C19="","",$C19-MAX(0,N($D19)-BreakAllow*$C19)) | S19: =IF(COUNT(G19:R19)=0,"",SUM(G19:R19)) | T19: =IF($C19="","",IFERROR(INDEX(RateValues,MATCH(SUMPRODUCT(MAX((RateDates<=$A19)*RateDates)),RateDates,0)),0)) | U19: =IF($C19="","",$F19*$T19) | V19: =$A19-WEEKDAY($A19,2)+1 -> 46293 | W19: {=IF(AND($C19="",S19=""),"",IF(AND(N($C19)>0,N(S19)=0),"nobody marked present",IF(N($D19)>N($C19),"more broken than moulded",IF(AND($C19="",N(S19)>0),"attendance marked but no blocks entered",IF(AND(N($C19)>0,N(T19)=0),"no pay rate for this date - see Settings",IF(SUMPRODUCT((G19:R19<>"")*(G$5:R$5=""))>0,"attendance in an empty worker slot",""))))))}
A20: 46299 | B20: =CHOOSE(WEEKDAY($A20,2),"Mon","Tue","Wed","Thu","Fri","Sat","Sun") -> Sun | E20: =IF($C20="","",$C20-N($D20)) | F20: =IF($C20="","",$C20-MAX(0,N($D20)-BreakAllow*$C20)) | S20: =IF(COUNT(G20:R20)=0,"",SUM(G20:R20)) | T20: =IF($C20="","",IFERROR(INDEX(RateValues,MATCH(SUMPRODUCT(MAX((RateDates<=$A20)*RateDates)),RateDates,0)),0)) | U20: =IF($C20="","",$F20*$T20) | V20: =$A20-WEEKDAY($A20,2)+1 -> 46293 | W20: {=IF(AND($C20="",S20=""),"",IF(AND(N($C20)>0,N(S20)=0),"nobody marked present",IF(N($D20)>N($C20),"more broken than moulded",IF(AND($C20="",N(S20)>0),"attendance marked but no blocks entered",IF(AND(N($C20)>0,N(T20)=0),"no pay rate for this date - see Settings",IF(SUMPRODUCT((G20:R20<>"")*(G$5:R$5=""))>0,"attendance in an empty worker slot",""))))))}
A21: 46300 | B21: =CHOOSE(WEEKDAY($A21,2),"Mon","Tue","Wed","Thu","Fri","Sat","Sun") -> Mon | E21: =IF($C21="","",$C21-N($D21)) | F21: =IF($C21="","",$C21-MAX(0,N($D21)-BreakAllow*$C21)) | S21: =IF(COUNT(G21:R21)=0,"",SUM(G21:R21)) | T21: =IF($C21="","",IFERROR(INDEX(RateValues,MATCH(SUMPRODUCT(MAX((RateDates<=$A21)*RateDates)),RateDates,0)),0)) | U21: =IF($C21="","",$F21*$T21) | V21: =$A21-WEEKDAY($A21,2)+1 -> 46300 | W21: {=IF(AND($C21="",S21=""),"",IF(AND(N($C21)>0,N(S21)=0),"nobody marked present",IF(N($D21)>N($C21),"more broken than moulded",IF(AND($C21="",N(S21)>0),"attendance marked but no blocks entered",IF(AND(N($C21)>0,N(T21)=0),"no pay rate for this date - see Settings",IF(SUMPRODUCT((G21:R21<>"")*(G$5:R$5=""))>0,"attendance in an empty worker slot",""))))))}
A22: 46301 | B22: =CHOOSE(WEEKDAY($A22,2),"Mon","Tue","Wed","Thu","Fri","Sat","Sun") -> Tue | E22: =IF($C22="","",$C22-N($D22)) | F22: =IF($C22="","",$C22-MAX(0,N($D22)-BreakAllow*$C22)) | S22: =IF(COUNT(G22:R22)=0,"",SUM(G22:R22)) | T22: =IF($C22="","",IFERROR(INDEX(RateValues,MATCH(SUMPRODUCT(MAX((RateDates<=$A22)*RateDates)),RateDates,0)),0)) | U22: =IF($C22="","",$F22*$T22) | V22: =$A22-WEEKDAY($A22,2)+1 -> 46300 | W22: {=IF(AND($C22="",S22=""),"",IF(AND(N($C22)>0,N(S22)=0),"nobody marked present",IF(N($D22)>N($C22),"more broken than moulded",IF(AND($C22="",N(S22)>0),"attendance marked but no blocks entered",IF(AND(N($C22)>0,N(T22)=0),"no pay rate for this date - see Settings",IF(SUMPRODUCT((G22:R22<>"")*(G$5:R$5=""))>0,"attendance in an empty worker slot",""))))))}
A23: 46302 | B23: =CHOOSE(WEEKDAY($A23,2),"Mon","Tue","Wed","Thu","Fri","Sat","Sun") -> Wed | E23: =IF($C23="","",$C23-N($D23)) | F23: =IF($C23="","",$C23-MAX(0,N($D23)-BreakAllow*$C23)) | S23: =IF(COUNT(G23:R23)=0,"",SUM(G23:R23)) | T23: =IF($C23="","",IFERROR(INDEX(RateValues,MATCH(SUMPRODUCT(MAX((RateDates<=$A23)*RateDates)),RateDates,0)),0)) | U23: =IF($C23="","",$F23*$T23) | V23: =$A23-WEEKDAY($A23,2)+1 -> 46300 | W23: {=IF(AND($C23="",S23=""),"",IF(AND(N($C23)>0,N(S23)=0),"nobody marked present",IF(N($D23)>N($C23),"more broken than moulded",IF(AND($C23="",N(S23)>0),"attendance marked but no blocks entered",IF(AND(N($C23)>0,N(T23)=0),"no pay rate for this date - see Settings",IF(SUMPRODUCT((G23:R23<>"")*(G$5:R$5=""))>0,"attendance in an empty worker slot",""))))))}
A24: 46303 | B24: =CHOOSE(WEEKDAY($A24,2),"Mon","Tue","Wed","Thu","Fri","Sat","Sun") -> Thu | E24: =IF($C24="","",$C24-N($D24)) | F24: =IF($C24="","",$C24-MAX(0,N($D24)-BreakAllow*$C24)) | S24: =IF(COUNT(G24:R24)=0,"",SUM(G24:R24)) | T24: =IF($C24="","",IFERROR(INDEX(RateValues,MATCH(SUMPRODUCT(MAX((RateDates<=$A24)*RateDates)),RateDates,0)),0)) | U24: =IF($C24="","",$F24*$T24) | V24: =$A24-WEEKDAY($A24,2)+1 -> 46300 | W24: {=IF(AND($C24="",S24=""),"",IF(AND(N($C24)>0,N(S24)=0),"nobody marked present",IF(N($D24)>N($C24),"more broken than moulded",IF(AND($C24="",N(S24)>0),"attendance marked but no blocks entered",IF(AND(N($C24)>0,N(T24)=0),"no pay rate for this date - see Settings",IF(SUMPRODUCT((G24:R24<>"")*(G$5:R$5=""))>0,"attendance in an empty worker slot",""))))))}
... A377: 46656 | B377: =CHOOSE(WEEKDAY($A377,2),"Mon","Tue","Wed","Thu","Fri","Sat","Sun") -> Sun | E377: =IF($C377="","",$C377-N($D377)) | F377: =IF($C377="","",$C377-MAX(0,N($D377)-BreakAllow*$C377)) | S377: =IF(COUNT(G377:R377)=0,"",SUM(G377:R377)) | T377: =IF($C377="","",IFERROR(INDEX(RateValues,MATCH(SUMPRODUCT(MAX((RateDates<=$A377)*RateDates)),RateDates,0)),0)) | U377: =IF($C377="","",$F377*$T377) | V377: =$A377-WEEKDAY($A377,2)+1 -> 46650 | W377: {=IF(AND($C377="",S377=""),"",IF(AND(N($C377)>0,N(S377)=0),"nobody marked present",IF(N($D377)>N($C377),"more broken than moulded",IF(AND($C377="",N(S377)>0),"attendance marked but no blocks entered",IF(AND(N($C377)>0,N(T377)=0),"no pay rate for this date - see Settings",IF(SUMPRODUCT((G377:R377<>"")*(G$5:R$5=""))>0,"attendance in an empty worker slot",""))))))}

Sheet Cash Ledger
A1: ◆ Donabay | D1: Home | E1: Daily Log | G1: Cash Ledger | I1: Weekly Pay | N1: Payslip | P1: Workers | R1: Settings | T1: Guide | V1: · | W1: History | Y1: Weeks | AA1: Checks
A2: Cash Ledger
A3: Every som you hand a worker goes here - one row each time. Never delete a row: fix a mistake with a Correction.
C4: Totals | D4: Advances | E4: =SUMIFS($E$7:$E$1006,$D$7:$D$1006,"Advance") -> 650000 | F4: Weekly pay | G4: =SUMIFS($E$7:$E$1006,$D$7:$D$1006,"Weekly pay") -> 0 | L4: Corrections | M4: =SUMIFS($E$7:$E$1006,$D$7:$D$1006,"Correction") -> 0
A5: Tips: Ctrl+; types today's date · click B7 then Ctrl+↓ to jump to the last entry
A6: # | B6: Date | C6: Worker | D6: Type | E6: Amount (so'm) | F6: Reason | G6: Given by | H6: Signed? | I6: ID | J6: Week of | K6: key | L6: Worker balance after | M6: Check
A7: =IF($B7="","",ROW()-6) -> 1 | B7: 46286 | C7: Davlatbek | D7: Advance | E7: 150000 | F7: Karta | I7: =IF($C7="","",IFERROR(INDEX(WorkerIDs,MATCH($C7,WorkerNames,0)),"?")) -> W01 | J7: =IF($B7="","",$B7-WEEKDAY($B7,2)+1) -> 46286 | K7: =IF(OR($I7="",$I7="?",$D7<>"Advance",$B7=""),"",$I7&"|"&$J7&"|"&COUNTIFS($I$7:$I7,$I7,$J$7:$J7,$J7,$D$7:$D7,"Advance")) -> W01|46286|1 | L7: =IF(OR($I7="",$I7="?",$B7=""),"",SUMPRODUCT((Weeks!$A$7:$A$59<=$J7)*(Weeks!$X$5:$AI$5=$I7)*Weeks!$X$7:$AI$59)-SUMIFS($E$7:$E$1006,$I$7:$I$1006,$I7,$B$7:$B$1006,"<="&$B7)) -> 1332125 | M7: =IF($B7&$C7&$D7&$E7="","",IF($B7="","missing date",IF($C7="","missing worker",IF($I7="?","unknown worker - was the name changed on Workers?",IF($D7="","missing type",IF(N($E7)=0,"missing amount",IF(AND($E7<0,$D7<>"Correction"),"negative amount - use a Correction to undo",IF(OR($B7<Weeks!$A$7,$B7>Weeks!$B$59),"date outside this workbook's year",IF(AND($D7="Advance",N($L7)<0),"Warning: more than earned so far - worker now owes "&TEXT(ROUND(-$L7,0),"#,##0"),"")))))))))
A8: =IF($B8="","",ROW()-6) -> 2 | B8: 46287 | C8: Xusanboy | D8: Advance | E8: 500000 | F8: Karta+Naqd | I8: =IF($C8="","",IFERROR(INDEX(WorkerIDs,MATCH($C8,WorkerNames,0)),"?")) -> W02 | J8: =IF($B8="","",$B8-WEEKDAY($B8,2)+1) -> 46286 | K8: =IF(OR($I8="",$I8="?",$D8<>"Advance",$B8=""),"",$I8&"|"&$J8&"|"&COUNTIFS($I$7:$I8,$I8,$J$7:$J8,$J8,$D$7:$D8,"Advance")) -> W02|46286|1 | L8: =IF(OR($I8="",$I8="?",$B8=""),"",SUMPRODUCT((Weeks!$A$7:$A$59<=$J8)*(Weeks!$X$5:$AI$5=$I8)*Weeks!$X$7:$AI$59)-SUMIFS($E$7:$E$1006,$I$7:$I$1006,$I8,$B$7:$B$1006,"<="&$B8)) -> 982125 | M8: =IF($B8&$C8&$D8&$E8="","",IF($B8="","missing date",IF($C8="","missing worker",IF($I8="?","unknown worker - was the name changed on Workers?",IF($D8="","missing type",IF(N($E8)=0,"missing amount",IF(AND($E8<0,$D8<>"Correction"),"negative amount - use a Correction to undo",IF(OR($B8<Weeks!$A$7,$B8>Weeks!$B$59),"date outside this workbook's year",IF(AND($D8="Advance",N($L8)<0),"Warning: more than earned so far - worker now owes "&TEXT(ROUND(-$L8,0),"#,##0"),"")))))))))
A9: =IF($B9="","",ROW()-6) | I9: =IF($C9="","",IFERROR(INDEX(WorkerIDs,MATCH($C9,WorkerNames,0)),"?")) | J9: =IF($B9="","",$B9-WEEKDAY($B9,2)+1) | K9: =IF(OR($I9="",$I9="?",$D9<>"Advance",$B9=""),"",$I9&"|"&$J9&"|"&COUNTIFS($I$7:$I9,$I9,$J$7:$J9,$J9,$D$7:$D9,"Advance")) | L9: =IF(OR($I9="",$I9="?",$B9=""),"",SUMPRODUCT((Weeks!$A$7:$A$59<=$J9)*(Weeks!$X$5:$AI$5=$I9)*Weeks!$X$7:$AI$59)-SUMIFS($E$7:$E$1006,$I$7:$I$1006,$I9,$B$7:$B$1006,"<="&$B9)) | M9: =IF($B9&$C9&$D9&$E9="","",IF($B9="","missing date",IF($C9="","missing worker",IF($I9="?","unknown worker - was the name changed on Workers?",IF($D9="","missing type",IF(N($E9)=0,"missing amount",IF(AND($E9<0,$D9<>"Correction"),"negative amount - use a Correction to undo",IF(OR($B9<Weeks!$A$7,$B9>Weeks!$B$59),"date outside this workbook's year",IF(AND($D9="Advance",N($L9)<0),"Warning: more than earned so far - worker now owes "&TEXT(ROUND(-$L9,0),"#,##0"),"")))))))))
A10: =IF($B10="","",ROW()-6) | I10: =IF($C10="","",IFERROR(INDEX(WorkerIDs,MATCH($C10,WorkerNames,0)),"?")) | J10: =IF($B10="","",$B10-WEEKDAY($B10,2)+1) | K10: =IF(OR($I10="",$I10="?",$D10<>"Advance",$B10=""),"",$I10&"|"&$J10&"|"&COUNTIFS($I$7:$I10,$I10,$J$7:$J10,$J10,$D$7:$D10,"Advance")) | L10: =IF(OR($I10="",$I10="?",$B10=""),"",SUMPRODUCT((Weeks!$A$7:$A$59<=$J10)*(Weeks!$X$5:$AI$5=$I10)*Weeks!$X$7:$AI$59)-SUMIFS($E$7:$E$1006,$I$7:$I$1006,$I10,$B$7:$B$1006,"<="&$B10)) | M10: =IF($B10&$C10&$D10&$E10="","",IF($B10="","missing date",IF($C10="","missing worker",IF($I10="?","unknown worker - was the name changed on Workers?",IF($D10="","missing type",IF(N($E10)=0,"missing amount",IF(AND($E10<0,$D10<>"Correction"),"negative amount - use a Correction to undo",IF(OR($B10<Weeks!$A$7,$B10>Weeks!$B$59),"date outside this workbook's year",IF(AND($D10="Advance",N($L10)<0),"Warning: more than earned so far - worker now owes "&TEXT(ROUND(-$L10,0),"#,##0"),"")))))))))
A11: =IF($B11="","",ROW()-6) | I11: =IF($C11="","",IFERROR(INDEX(WorkerIDs,MATCH($C11,WorkerNames,0)),"?")) | J11: =IF($B11="","",$B11-WEEKDAY($B11,2)+1) | K11: =IF(OR($I11="",$I11="?",$D11<>"Advance",$B11=""),"",$I11&"|"&$J11&"|"&COUNTIFS($I$7:$I11,$I11,$J$7:$J11,$J11,$D$7:$D11,"Advance")) | L11: =IF(OR($I11="",$I11="?",$B11=""),"",SUMPRODUCT((Weeks!$A$7:$A$59<=$J11)*(Weeks!$X$5:$AI$5=$I11)*Weeks!$X$7:$AI$59)-SUMIFS($E$7:$E$1006,$I$7:$I$1006,$I11,$B$7:$B$1006,"<="&$B11)) | M11: =IF($B11&$C11&$D11&$E11="","",IF($B11="","missing date",IF($C11="","missing worker",IF($I11="?","unknown worker - was the name changed on Workers?",IF($D11="","missing type",IF(N($E11)=0,"missing amount",IF(AND($E11<0,$D11<>"Correction"),"negative amount - use a Correction to undo",IF(OR($B11<Weeks!$A$7,$B11>Weeks!$B$59),"date outside this workbook's year",IF(AND($D11="Advance",N($L11)<0),"Warning: more than earned so far - worker now owes "&TEXT(ROUND(-$L11,0),"#,##0"),"")))))))))
A12: =IF($B12="","",ROW()-6) | I12: =IF($C12="","",IFERROR(INDEX(WorkerIDs,MATCH($C12,WorkerNames,0)),"?")) | J12: =IF($B12="","",$B12-WEEKDAY($B12,2)+1) | K12: =IF(OR($I12="",$I12="?",$D12<>"Advance",$B12=""),"",$I12&"|"&$J12&"|"&COUNTIFS($I$7:$I12,$I12,$J$7:$J12,$J12,$D$7:$D12,"Advance")) | L12: =IF(OR($I12="",$I12="?",$B12=""),"",SUMPRODUCT((Weeks!$A$7:$A$59<=$J12)*(Weeks!$X$5:$AI$5=$I12)*Weeks!$X$7:$AI$59)-SUMIFS($E$7:$E$1006,$I$7:$I$1006,$I12,$B$7:$B$1006,"<="&$B12)) | M12: =IF($B12&$C12&$D12&$E12="","",IF($B12="","missing date",IF($C12="","missing worker",IF($I12="?","unknown worker - was the name changed on Workers?",IF($D12="","missing type",IF(N($E12)=0,"missing amount",IF(AND($E12<0,$D12<>"Correction"),"negative amount - use a Correction to undo",IF(OR($B12<Weeks!$A$7,$B12>Weeks!$B$59),"date outside this workbook's year",IF(AND($D12="Advance",N($L12)<0),"Warning: more than earned so far - worker now owes "&TEXT(ROUND(-$L12,0),"#,##0"),"")))))))))
A13: =IF($B13="","",ROW()-6) | I13: =IF($C13="","",IFERROR(INDEX(WorkerIDs,MATCH($C13,WorkerNames,0)),"?")) | J13: =IF($B13="","",$B13-WEEKDAY($B13,2)+1) | K13: =IF(OR($I13="",$I13="?",$D13<>"Advance",$B13=""),"",$I13&"|"&$J13&"|"&COUNTIFS($I$7:$I13,$I13,$J$7:$J13,$J13,$D$7:$D13,"Advance")) | L13: =IF(OR($I13="",$I13="?",$B13=""),"",SUMPRODUCT((Weeks!$A$7:$A$59<=$J13)*(Weeks!$X$5:$AI$5=$I13)*Weeks!$X$7:$AI$59)-SUMIFS($E$7:$E$1006,$I$7:$I$1006,$I13,$B$7:$B$1006,"<="&$B13)) | M13: =IF($B13&$C13&$D13&$E13="","",IF($B13="","missing date",IF($C13="","missing worker",IF($I13="?","unknown worker - was the name changed on Workers?",IF($D13="","missing type",IF(N($E13)=0,"missing amount",IF(AND($E13<0,$D13<>"Correction"),"negative amount - use a Correction to undo",IF(OR($B13<Weeks!$A$7,$B13>Weeks!$B$59),"date outside this workbook's year",IF(AND($D13="Advance",N($L13)<0),"Warning: more than earned so far - worker now owes "&TEXT(ROUND(-$L13,0),"#,##0"),"")))))))))
A14: =IF($B14="","",ROW()-6) | I14: =IF($C14="","",IFERROR(INDEX(WorkerIDs,MATCH($C14,WorkerNames,0)),"?")) | J14: =IF($B14="","",$B14-WEEKDAY($B14,2)+1) | K14: =IF(OR($I14="",$I14="?",$D14<>"Advance",$B14=""),"",$I14&"|"&$J14&"|"&COUNTIFS($I$7:$I14,$I14,$J$7:$J14,$J14,$D$7:$D14,"Advance")) | L14: =IF(OR($I14="",$I14="?",$B14=""),"",SUMPRODUCT((Weeks!$A$7:$A$59<=$J14)*(Weeks!$X$5:$AI$5=$I14)*Weeks!$X$7:$AI$59)-SUMIFS($E$7:$E$1006,$I$7:$I$1006,$I14,$B$7:$B$1006,"<="&$B14)) | M14: =IF($B14&$C14&$D14&$E14="","",IF($B14="","missing date",IF($C14="","missing worker",IF($I14="?","unknown worker - was the name changed on Workers?",IF($D14="","missing type",IF(N($E14)=0,"missing amount",IF(AND($E14<0,$D14<>"Correction"),"negative amount - use a Correction to undo",IF(OR($B14<Weeks!$A$7,$B14>Weeks!$B$59),"date outside this workbook's year",IF(AND($D14="Advance",N($L14)<0),"Warning: more than earned so far - worker now owes "&TEXT(ROUND(-$L14,0),"#,##0"),"")))))))))
A15: =IF($B15="","",ROW()-6) | I15: =IF($C15="","",IFERROR(INDEX(WorkerIDs,MATCH($C15,WorkerNames,0)),"?")) | J15: =IF($B15="","",$B15-WEEKDAY($B15,2)+1) | K15: =IF(OR($I15="",$I15="?",$D15<>"Advance",$B15=""),"",$I15&"|"&$J15&"|"&COUNTIFS($I$7:$I15,$I15,$J$7:$J15,$J15,$D$7:$D15,"Advance")) | L15: =IF(OR($I15="",$I15="?",$B15=""),"",SUMPRODUCT((Weeks!$A$7:$A$59<=$J15)*(Weeks!$X$5:$AI$5=$I15)*Weeks!$X$7:$AI$59)-SUMIFS($E$7:$E$1006,$I$7:$I$1006,$I15,$B$7:$B$1006,"<="&$B15)) | M15: =IF($B15&$C15&$D15&$E15="","",IF($B15="","missing date",IF($C15="","missing worker",IF($I15="?","unknown worker - was the name changed on Workers?",IF($D15="","missing type",IF(N($E15)=0,"missing amount",IF(AND($E15<0,$D15<>"Correction"),"negative amount - use a Correction to undo",IF(OR($B15<Weeks!$A$7,$B15>Weeks!$B$59),"date outside this workbook's year",IF(AND($D15="Advance",N($L15)<0),"Warning: more than earned so far - worker now owes "&TEXT(ROUND(-$L15,0),"#,##0"),"")))))))))
A16: =IF($B16="","",ROW()-6) | I16: =IF($C16="","",IFERROR(INDEX(WorkerIDs,MATCH($C16,WorkerNames,0)),"?")) | J16: =IF($B16="","",$B16-WEEKDAY($B16,2)+1) | K16: =IF(OR($I16="",$I16="?",$D16<>"Advance",$B16=""),"",$I16&"|"&$J16&"|"&COUNTIFS($I$7:$I16,$I16,$J$7:$J16,$J16,$D$7:$D16,"Advance")) | L16: =IF(OR($I16="",$I16="?",$B16=""),"",SUMPRODUCT((Weeks!$A$7:$A$59<=$J16)*(Weeks!$X$5:$AI$5=$I16)*Weeks!$X$7:$AI$59)-SUMIFS($E$7:$E$1006,$I$7:$I$1006,$I16,$B$7:$B$1006,"<="&$B16)) | M16: =IF($B16&$C16&$D16&$E16="","",IF($B16="","missing date",IF($C16="","missing worker",IF($I16="?","unknown worker - was the name changed on Workers?",IF($D16="","missing type",IF(N($E16)=0,"missing amount",IF(AND($E16<0,$D16<>"Correction"),"negative amount - use a Correction to undo",IF(OR($B16<Weeks!$A$7,$B16>Weeks!$B$59),"date outside this workbook's year",IF(AND($D16="Advance",N($L16)<0),"Warning: more than earned so far - worker now owes "&TEXT(ROUND(-$L16,0),"#,##0"),"")))))))))
A17: =IF($B17="","",ROW()-6) | I17: =IF($C17="","",IFERROR(INDEX(WorkerIDs,MATCH($C17,WorkerNames,0)),"?")) | J17: =IF($B17="","",$B17-WEEKDAY($B17,2)+1) | K17: =IF(OR($I17="",$I17="?",$D17<>"Advance",$B17=""),"",$I17&"|"&$J17&"|"&COUNTIFS($I$7:$I17,$I17,$J$7:$J17,$J17,$D$7:$D17,"Advance")) | L17: =IF(OR($I17="",$I17="?",$B17=""),"",SUMPRODUCT((Weeks!$A$7:$A$59<=$J17)*(Weeks!$X$5:$AI$5=$I17)*Weeks!$X$7:$AI$59)-SUMIFS($E$7:$E$1006,$I$7:$I$1006,$I17,$B$7:$B$1006,"<="&$B17)) | M17: =IF($B17&$C17&$D17&$E17="","",IF($B17="","missing date",IF($C17="","missing worker",IF($I17="?","unknown worker - was the name changed on Workers?",IF($D17="","missing type",IF(N($E17)=0,"missing amount",IF(AND($E17<0,$D17<>"Correction"),"negative amount - use a Correction to undo",IF(OR($B17<Weeks!$A$7,$B17>Weeks!$B$59),"date outside this workbook's year",IF(AND($D17="Advance",N($L17)<0),"Warning: more than earned so far - worker now owes "&TEXT(ROUND(-$L17,0),"#,##0"),"")))))))))
A18: =IF($B18="","",ROW()-6) | I18: =IF($C18="","",IFERROR(INDEX(WorkerIDs,MATCH($C18,WorkerNames,0)),"?")) | J18: =IF($B18="","",$B18-WEEKDAY($B18,2)+1) | K18: =IF(OR($I18="",$I18="?",$D18<>"Advance",$B18=""),"",$I18&"|"&$J18&"|"&COUNTIFS($I$7:$I18,$I18,$J$7:$J18,$J18,$D$7:$D18,"Advance")) | L18: =IF(OR($I18="",$I18="?",$B18=""),"",SUMPRODUCT((Weeks!$A$7:$A$59<=$J18)*(Weeks!$X$5:$AI$5=$I18)*Weeks!$X$7:$AI$59)-SUMIFS($E$7:$E$1006,$I$7:$I$1006,$I18,$B$7:$B$1006,"<="&$B18)) | M18: =IF($B18&$C18&$D18&$E18="","",IF($B18="","missing date",IF($C18="","missing worker",IF($I18="?","unknown worker - was the name changed on Workers?",IF($D18="","missing type",IF(N($E18)=0,"missing amount",IF(AND($E18<0,$D18<>"Correction"),"negative amount - use a Correction to undo",IF(OR($B18<Weeks!$A$7,$B18>Weeks!$B$59),"date outside this workbook's year",IF(AND($D18="Advance",N($L18)<0),"Warning: more than earned so far - worker now owes "&TEXT(ROUND(-$L18,0),"#,##0"),"")))))))))
A19: =IF($B19="","",ROW()-6) | I19: =IF($C19="","",IFERROR(INDEX(WorkerIDs,MATCH($C19,WorkerNames,0)),"?")) | J19: =IF($B19="","",$B19-WEEKDAY($B19,2)+1) | K19: =IF(OR($I19="",$I19="?",$D19<>"Advance",$B19=""),"",$I19&"|"&$J19&"|"&COUNTIFS($I$7:$I19,$I19,$J$7:$J19,$J19,$D$7:$D19,"Advance")) | L19: =IF(OR($I19="",$I19="?",$B19=""),"",SUMPRODUCT((Weeks!$A$7:$A$59<=$J19)*(Weeks!$X$5:$AI$5=$I19)*Weeks!$X$7:$AI$59)-SUMIFS($E$7:$E$1006,$I$7:$I$1006,$I19,$B$7:$B$1006,"<="&$B19)) | M19: =IF($B19&$C19&$D19&$E19="","",IF($B19="","missing date",IF($C19="","missing worker",IF($I19="?","unknown worker - was the name changed on Workers?",IF($D19="","missing type",IF(N($E19)=0,"missing amount",IF(AND($E19<0,$D19<>"Correction"),"negative amount - use a Correction to undo",IF(OR($B19<Weeks!$A$7,$B19>Weeks!$B$59),"date outside this workbook's year",IF(AND($D19="Advance",N($L19)<0),"Warning: more than earned so far - worker now owes "&TEXT(ROUND(-$L19,0),"#,##0"),"")))))))))
A20: =IF($B20="","",ROW()-6) | I20: =IF($C20="","",IFERROR(INDEX(WorkerIDs,MATCH($C20,WorkerNames,0)),"?")) | J20: =IF($B20="","",$B20-WEEKDAY($B20,2)+1) | K20: =IF(OR($I20="",$I20="?",$D20<>"Advance",$B20=""),"",$I20&"|"&$J20&"|"&COUNTIFS($I$7:$I20,$I20,$J$7:$J20,$J20,$D$7:$D20,"Advance")) | L20: =IF(OR($I20="",$I20="?",$B20=""),"",SUMPRODUCT((Weeks!$A$7:$A$59<=$J20)*(Weeks!$X$5:$AI$5=$I20)*Weeks!$X$7:$AI$59)-SUMIFS($E$7:$E$1006,$I$7:$I$1006,$I20,$B$7:$B$1006,"<="&$B20)) | M20: =IF($B20&$C20&$D20&$E20="","",IF($B20="","missing date",IF($C20="","missing worker",IF($I20="?","unknown worker - was the name changed on Workers?",IF($D20="","missing type",IF(N($E20)=0,"missing amount",IF(AND($E20<0,$D20<>"Correction"),"negative amount - use a Correction to undo",IF(OR($B20<Weeks!$A$7,$B20>Weeks!$B$59),"date outside this workbook's year",IF(AND($D20="Advance",N($L20)<0),"Warning: more than earned so far - worker now owes "&TEXT(ROUND(-$L20,0),"#,##0"),"")))))))))
... A1006: =IF($B1006="","",ROW()-6) | I1006: =IF($C1006="","",IFERROR(INDEX(WorkerIDs,MATCH($C1006,WorkerNames,0)),"?")) | J1006: =IF($B1006="","",$B1006-WEEKDAY($B1006,2)+1) | K1006: =IF(OR($I1006="",$I1006="?",$D1006<>"Advance",$B1006=""),"",$I1006&"|"&$J1006&"|"&COUNTIFS($I$7:$I1006,$I1006,$J$7:$J1006,$J1006,$D$7:$D1006,"Advance")) | L1006: =IF(OR($I1006="",$I1006="?",$B1006=""),"",SUMPRODUCT((Weeks!$A$7:$A$59<=$J1006)*(Weeks!$X$5:$AI$5=$I1006)*Weeks!$X$7:$AI$59)-SUMIFS($E$7:$E$1006,$I$7:$I$1006,$I1006,$B$7:$B$1006,"<="&$B1006)) | M1006: =IF($B1006&$C1006&$D1006&$E1006="","",IF($B1006="","missing date",IF($C1006="","missing worker",IF($I1006="?","unknown worker - was the name changed on Workers?",IF($D1006="","missing type",IF(N($E1006)=0,"missing amount",IF(AND($E1006<0,$D1006<>"Correction"),"negative amount - use a Correction to undo",IF(OR($B1006<Weeks!$A$7,$B1006>Weeks!$B$59),"date outside this workbook's year",IF(AND($D1006="Advance",N($L1006)<0),"Warning: more than earned so far - worker now owes "&TEXT(ROUND(-$L1006,0),"#,##0"),"")))))))))

Sheet Weekly Pay
A1: ◆ Donabay | C1: Home | D1: Daily Log | F1: Cash Ledger | H1: Weekly Pay | J1: Payslip | L1: Workers | N1: Settings | P1: Guide | R1: · | S1: History | U1: Weeks | X1: Checks
A2: Weekly Pay
A3: Payday. Pick the week, pay each worker the green TO PAY column, then copy the 'Ready for the Cash Ledger' list on the right into the Cash Ledger (Paste Values).
B5: Week starting (Monday): | C5: 46286 | D5: =$C$5+6 -> 46292
B7: Good blocks | D7: Paid blocks | F7: Pot (so'm) | H7: Crew-days | J7: Reject rate | L7: Workbook checks
B8: =IFERROR(INDEX(Weeks!$E$7:$E$59,MATCH($C$5,Weeks!$A$7:$A$59,0)),0) -> 11857 | D8: =IFERROR(INDEX(Weeks!$F$7:$F$59,MATCH($C$5,Weeks!$A$7:$A$59,0)),0) -> 11857 | F8: =IFERROR(INDEX(Weeks!$G$7:$G$59,MATCH($C$5,Weeks!$A$7:$A$59,0)),0) -> 5928500 | H8: =IFERROR(INDEX(Weeks!$H$7:$H$59,MATCH($C$5,Weeks!$A$7:$A$59,0)),0) -> 24 | J8: =IFERROR(INDEX(Weeks!$I$7:$I$59,MATCH($C$5,Weeks!$A$7:$A$59,0)),0) -> 0.010101853 | L8: =Checks!$C$5 -> ALL CHECKS OK | Q8: Ready for the Cash Ledger
Q9: After paying: select the filled rows below, copy, go to the next empty row in the Cash Ledger (column B) and Paste Values (Ctrl+Shift+V, or Paste ▸ Values).
A11: ID | B11: Worker | C11: Status | D11: Days | E11: Share | F11: Earned this week | G11: Brought forward | H11: Advances | I11: Corrections | J11: Due | K11: TO PAY | L11: Paid (in ledger) | M11: Still to pay | N11: Carried forward | O11: Note | Q11: Date | R11: Worker | S11: Type | T11: Amount (so'm) | U11: slot
A12: =Workers!$A$6 -> W01 | B12: =IF(Workers!$B$6="","",Workers!$B$6) -> Davlatbek | C12: =IF($B12="","",Workers!$C$6) -> Active | D12: =IF($B12="","",IFERROR(INDEX(Weeks!$L$7:$W$59,MATCH($C$5,Weeks!$A$7:$A$59,0),MATCH($A12,Weeks!$L$5:$W$5,0)),0)) -> 6 | E12: =IF(OR($B12="",N($H$8)=0),"",$D12/$H$8) -> 0.25 | F12: =IF($B12="","",IFERROR(INDEX(Weeks!$X$7:$AI$59,MATCH($C$5,Weeks!$A$7:$A$59,0),MATCH($A12,Weeks!$X$5:$AI$5,0)),0)) -> 1482125 | G12: =IF($B12="","",SUMPRODUCT((Weeks!$A$7:$A$59<$C$5)*(Weeks!$X$5:$AI$5=$A12)*Weeks!$X$7:$AI$59)-SUMIFS('Cash Ledger'!$E$7:$E$1006,'Cash Ledger'!$I$7:$I$1006,$A12,'Cash Ledger'!$B$7:$B$1006,"<"&$C$5)) -> 0 | H12: =IF($B12="","",SUMIFS('Cash Ledger'!$E$7:$E$1006,'Cash Ledger'!$I$7:$I$1006,$A12,'Cash Ledger'!$D$7:$D$1006,"Advance",'Cash Ledger'!$B$7:$B$1006,">="&$C$5,'Cash Ledger'!$B$7:$B$1006,"<="&($C$5+6))) -> 150000 | I12: =IF($B12="","",SUMIFS('Cash Ledger'!$E$7:$E$1006,'Cash Ledger'!$I$7:$I$1006,$A12,'Cash Ledger'!$D$7:$D$1006,"Correction",'Cash Ledger'!$B$7:$B$1006,">="&$C$5,'Cash Ledger'!$B$7:$B$1006,"<="&($C$5+6))) -> 0 | J12: =IF($B12="","",$G12+$F12-$H12-$I12) -> 1332125 | K12: =IF($B12="","",ROUND(MAX(0,IF($G12>=0,$J12,$F12-$H12-$I12-MIN(-$G12,DebtCap*$F12))),0)) -> 1332125 | L12: =IF($B12="","",SUMIFS('Cash Ledger'!$E$7:$E$1006,'Cash Ledger'!$I$7:$I$1006,$A12,'Cash Ledger'!$D$7:$D$1006,"Weekly pay",'Cash Ledger'!$B$7:$B$1006,">="&$C$5,'Cash Ledger'!$B$7:$B$1006,"<="&($C$5+6))) -> 0 | M12: =IF($B12="","",MAX(0,$K12-$L12)) -> 1332125 | N12: =IF($B12="","",$J12-$L12) -> 1332125 | O12: =IF($B12="","",IF(ROUND($N12,0)<0,"owes you "&TEXT(ROUND(-$N12,0),"#,##0"),IF(AND(ROUND($N12,0)>0,$M12>0),"not yet paid",IF(ROUND($N12,0)>0,"you owe "&TEXT(ROUND($N12,0),"#,##0"),"settled")))) -> not yet paid | Q12: =IF($U12="","",MEDIAN($C$5,$C$5+6,TODAY())) -> 46289 | R12: {=IF($U12="","",INDEX($B$12:$B$23,$U12))} -> Davlatbek | S12: =IF($U12="","","Weekly pay") -> Weekly pay | T12: {=IF($U12="","",INDEX($M$12:$M$23,$U12))} -> 1332125 | U12: {=IFERROR(_xlfn.AGGREGATE(15,6,(ROW($M$12:$M$23)-ROW($M$12)+1)/(ISNUMBER($M$12:$M$23)*($M$12:$M$23>0)),ROWS($U$12:U12)),"")} -> 1
A13: =Workers!$A$7 -> W02 | B13: =IF(Workers!$B$7="","",Workers!$B$7) -> Xusanboy | C13: =IF($B13="","",Workers!$C$7) -> Active | D13: =IF($B13="","",IFERROR(INDEX(Weeks!$L$7:$W$59,MATCH($C$5,Weeks!$A$7:$A$59,0),MATCH($A13,Weeks!$L$5:$W$5,0)),0)) -> 6 | E13: =IF(OR($B13="",N($H$8)=0),"",$D13/$H$8) -> 0.25 | F13: =IF($B13="","",IFERROR(INDEX(Weeks!$X$7:$AI$59,MATCH($C$5,Weeks!$A$7:$A$59,0),MATCH($A13,Weeks!$X$5:$AI$5,0)),0)) -> 1482125 | G13: =IF($B13="","",SUMPRODUCT((Weeks!$A$7:$A$59<$C$5)*(Weeks!$X$5:$AI$5=$A13)*Weeks!$X$7:$AI$59)-SUMIFS('Cash Ledger'!$E$7:$E$1006,'Cash Ledger'!$I$7:$I$1006,$A13,'Cash Ledger'!$B$7:$B$1006,"<"&$C$5)) -> 0 | H13: =IF($B13="","",SUMIFS('Cash Ledger'!$E$7:$E$1006,'Cash Ledger'!$I$7:$I$1006,$A13,'Cash Ledger'!$D$7:$D$1006,"Advance",'Cash Ledger'!$B$7:$B$1006,">="&$C$5,'Cash Ledger'!$B$7:$B$1006,"<="&($C$5+6))) -> 500000 | I13: =IF($B13="","",SUMIFS('Cash Ledger'!$E$7:$E$1006,'Cash Ledger'!$I$7:$I$1006,$A13,'Cash Ledger'!$D$7:$D$1006,"Correction",'Cash Ledger'!$B$7:$B$1006,">="&$C$5,'Cash Ledger'!$B$7:$B$1006,"<="&($C$5+6))) -> 0 | J13: =IF($B13="","",$G13+$F13-$H13-$I13) -> 982125 | K13: =IF($B13="","",ROUND(MAX(0,IF($G13>=0,$J13,$F13-$H13-$I13-MIN(-$G13,DebtCap*$F13))),0)) -> 982125 | L13: =IF($B13="","",SUMIFS('Cash Ledger'!$E$7:$E$1006,'Cash Ledger'!$I$7:$I$1006,$A13,'Cash Ledger'!$D$7:$D$1006,"Weekly pay",'Cash Ledger'!$B$7:$B$1006,">="&$C$5,'Cash Ledger'!$B$7:$B$1006,"<="&($C$5+6))) -> 0 | M13: =IF($B13="","",MAX(0,$K13-$L13)) -> 982125 | N13: =IF($B13="","",$J13-$L13) -> 982125 | O13: =IF($B13="","",IF(ROUND($N13,0)<0,"owes you "&TEXT(ROUND(-$N13,0),"#,##0"),IF(AND(ROUND($N13,0)>0,$M13>0),"not yet paid",IF(ROUND($N13,0)>0,"you owe "&TEXT(ROUND($N13,0),"#,##0"),"settled")))) -> not yet paid | Q13: =IF($U13="","",MEDIAN($C$5,$C$5+6,TODAY())) -> 46289 | R13: {=IF($U13="","",INDEX($B$12:$B$23,$U13))} -> Xusanboy | S13: =IF($U13="","","Weekly pay") -> Weekly pay | T13: {=IF($U13="","",INDEX($M$12:$M$23,$U13))} -> 982125 | U13: {=IFERROR(_xlfn.AGGREGATE(15,6,(ROW($M$12:$M$23)-ROW($M$12)+1)/(ISNUMBER($M$12:$M$23)*($M$12:$M$23>0)),ROWS($U$12:U13)),"")} -> 2
A14: =Workers!$A$8 -> W03 | B14: =IF(Workers!$B$8="","",Workers!$B$8) -> Oybek | C14: =IF($B14="","",Workers!$C$8) -> Active | D14: =IF($B14="","",IFERROR(INDEX(Weeks!$L$7:$W$59,MATCH($C$5,Weeks!$A$7:$A$59,0),MATCH($A14,Weeks!$L$5:$W$5,0)),0)) -> 6 | E14: =IF(OR($B14="",N($H$8)=0),"",$D14/$H$8) -> 0.25 | F14: =IF($B14="","",IFERROR(INDEX(Weeks!$X$7:$AI$59,MATCH($C$5,Weeks!$A$7:$A$59,0),MATCH($A14,Weeks!$X$5:$AI$5,0)),0)) -> 1482125 | G14: =IF($B14="","",SUMPRODUCT((Weeks!$A$7:$A$59<$C$5)*(Weeks!$X$5:$AI$5=$A14)*Weeks!$X$7:$AI$59)-SUMIFS('Cash Ledger'!$E$7:$E$1006,'Cash Ledger'!$I$7:$I$1006,$A14,'Cash Ledger'!$B$7:$B$1006,"<"&$C$5)) -> 0 | H14: =IF($B14="","",SUMIFS('Cash Ledger'!$E$7:$E$1006,'Cash Ledger'!$I$7:$I$1006,$A14,'Cash Ledger'!$D$7:$D$1006,"Advance",'Cash Ledger'!$B$7:$B$1006,">="&$C$5,'Cash Ledger'!$B$7:$B$1006,"<="&($C$5+6))) -> 0 | I14: =IF($B14="","",SUMIFS('Cash Ledger'!$E$7:$E$1006,'Cash Ledger'!$I$7:$I$1006,$A14,'Cash Ledger'!$D$7:$D$1006,"Correction",'Cash Ledger'!$B$7:$B$1006,">="&$C$5,'Cash Ledger'!$B$7:$B$1006,"<="&($C$5+6))) -> 0 | J14: =IF($B14="","",$G14+$F14-$H14-$I14) -> 1482125 | K14: =IF($B14="","",ROUND(MAX(0,IF($G14>=0,$J14,$F14-$H14-$I14-MIN(-$G14,DebtCap*$F14))),0)) -> 1482125 | L14: =IF($B14="","",SUMIFS('Cash Ledger'!$E$7:$E$1006,'Cash Ledger'!$I$7:$I$1006,$A14,'Cash Ledger'!$D$7:$D$1006,"Weekly pay",'Cash Ledger'!$B$7:$B$1006,">="&$C$5,'Cash Ledger'!$B$7:$B$1006,"<="&($C$5+6))) -> 0 | M14: =IF($B14="","",MAX(0,$K14-$L14)) -> 1482125 | N14: =IF($B14="","",$J14-$L14) -> 1482125 | O14: =IF($B14="","",IF(ROUND($N14,0)<0,"owes you "&TEXT(ROUND(-$N14,0),"#,##0"),IF(AND(ROUND($N14,0)>0,$M14>0),"not yet paid",IF(ROUND($N14,0)>0,"you owe "&TEXT(ROUND($N14,0),"#,##0"),"settled")))) -> not yet paid | Q14: =IF($U14="","",MEDIAN($C$5,$C$5+6,TODAY())) -> 46289 | R14: {=IF($U14="","",INDEX($B$12:$B$23,$U14))} -> Oybek | S14: =IF($U14="","","Weekly pay") -> Weekly pay | T14: {=IF($U14="","",INDEX($M$12:$M$23,$U14))} -> 1482125 | U14: {=IFERROR(_xlfn.AGGREGATE(15,6,(ROW($M$12:$M$23)-ROW($M$12)+1)/(ISNUMBER($M$12:$M$23)*($M$12:$M$23>0)),ROWS($U$12:U14)),"")} -> 3
A15: =Workers!$A$9 -> W04 | B15: =IF(Workers!$B$9="","",Workers!$B$9) -> Abdurashid | C15: =IF($B15="","",Workers!$C$9) -> Active | D15: =IF($B15="","",IFERROR(INDEX(Weeks!$L$7:$W$59,MATCH($C$5,Weeks!$A$7:$A$59,0),MATCH($A15,Weeks!$L$5:$W$5,0)),0)) -> 6 | E15: =IF(OR($B15="",N($H$8)=0),"",$D15/$H$8) -> 0.25 | F15: =IF($B15="","",IFERROR(INDEX(Weeks!$X$7:$AI$59,MATCH($C$5,Weeks!$A$7:$A$59,0),MATCH($A15,Weeks!$X$5:$AI$5,0)),0)) -> 1482125 | G15: =IF($B15="","",SUMPRODUCT((Weeks!$A$7:$A$59<$C$5)*(Weeks!$X$5:$AI$5=$A15)*Weeks!$X$7:$AI$59)-SUMIFS('Cash Ledger'!$E$7:$E$1006,'Cash Ledger'!$I$7:$I$1006,$A15,'Cash Ledger'!$B$7:$B$1006,"<"&$C$5)) -> 0 | H15: =IF($B15="","",SUMIFS('Cash Ledger'!$E$7:$E$1006,'Cash Ledger'!$I$7:$I$1006,$A15,'Cash Ledger'!$D$7:$D$1006,"Advance",'Cash Ledger'!$B$7:$B$1006,">="&$C$5,'Cash Ledger'!$B$7:$B$1006,"<="&($C$5+6))) -> 0 | I15: =IF($B15="","",SUMIFS('Cash Ledger'!$E$7:$E$1006,'Cash Ledger'!$I$7:$I$1006,$A15,'Cash Ledger'!$D$7:$D$1006,"Correction",'Cash Ledger'!$B$7:$B$1006,">="&$C$5,'Cash Ledger'!$B$7:$B$1006,"<="&($C$5+6))) -> 0 | J15: =IF($B15="","",$G15+$F15-$H15-$I15) -> 1482125 | K15: =IF($B15="","",ROUND(MAX(0,IF($G15>=0,$J15,$F15-$H15-$I15-MIN(-$G15,DebtCap*$F15))),0)) -> 1482125 | L15: =IF($B15="","",SUMIFS('Cash Ledger'!$E$7:$E$1006,'Cash Ledger'!$I$7:$I$1006,$A15,'Cash Ledger'!$D$7:$D$1006,"Weekly pay",'Cash Ledger'!$B$7:$B$1006,">="&$C$5,'Cash Ledger'!$B$7:$B$1006,"<="&($C$5+6))) -> 0 | M15: =IF($B15="","",MAX(0,$K15-$L15)) -> 1482125 | N15: =IF($B15="","",$J15-$L15) -> 1482125 | O15: =IF($B15="","",IF(ROUND($N15,0)<0,"owes you "&TEXT(ROUND(-$N15,0),"#,##0"),IF(AND(ROUND($N15,0)>0,$M15>0),"not yet paid",IF(ROUND($N15,0)>0,"you owe "&TEXT(ROUND($N15,0),"#,##0"),"settled")))) -> not yet paid | Q15: =IF($U15="","",MEDIAN($C$5,$C$5+6,TODAY())) -> 46289 | R15: {=IF($U15="","",INDEX($B$12:$B$23,$U15))} -> Abdurashid | S15: =IF($U15="","","Weekly pay") -> Weekly pay | T15: {=IF($U15="","",INDEX($M$12:$M$23,$U15))} -> 1482125 | U15: {=IFERROR(_xlfn.AGGREGATE(15,6,(ROW($M$12:$M$23)-ROW($M$12)+1)/(ISNUMBER($M$12:$M$23)*($M$12:$M$23>0)),ROWS($U$12:U15)),"")} -> 4
A16: =Workers!$A$10 -> W05 | B16: =IF(Workers!$B$10="","",Workers!$B$10) | C16: =IF($B16="","",Workers!$C$10) | D16: =IF($B16="","",IFERROR(INDEX(Weeks!$L$7:$W$59,MATCH($C$5,Weeks!$A$7:$A$59,0),MATCH($A16,Weeks!$L$5:$W$5,0)),0)) | E16: =IF(OR($B16="",N($H$8)=0),"",$D16/$H$8) | F16: =IF($B16="","",IFERROR(INDEX(Weeks!$X$7:$AI$59,MATCH($C$5,Weeks!$A$7:$A$59,0),MATCH($A16,Weeks!$X$5:$AI$5,0)),0)) | G16: =IF($B16="","",SUMPRODUCT((Weeks!$A$7:$A$59<$C$5)*(Weeks!$X$5:$AI$5=$A16)*Weeks!$X$7:$AI$59)-SUMIFS('Cash Ledger'!$E$7:$E$1006,'Cash Ledger'!$I$7:$I$1006,$A16,'Cash Ledger'!$B$7:$B$1006,"<"&$C$5)) | H16: =IF($B16="","",SUMIFS('Cash Ledger'!$E$7:$E$1006,'Cash Ledger'!$I$7:$I$1006,$A16,'Cash Ledger'!$D$7:$D$1006,"Advance",'Cash Ledger'!$B$7:$B$1006,">="&$C$5,'Cash Ledger'!$B$7:$B$1006,"<="&($C$5+6))) | I16: =IF($B16="","",SUMIFS('Cash Ledger'!$E$7:$E$1006,'Cash Ledger'!$I$7:$I$1006,$A16,'Cash Ledger'!$D$7:$D$1006,"Correction",'Cash Ledger'!$B$7:$B$1006,">="&$C$5,'Cash Ledger'!$B$7:$B$1006,"<="&($C$5+6))) | J16: =IF($B16="","",$G16+$F16-$H16-$I16) | K16: =IF($B16="","",ROUND(MAX(0,IF($G16>=0,$J16,$F16-$H16-$I16-MIN(-$G16,DebtCap*$F16))),0)) | L16: =IF($B16="","",SUMIFS('Cash Ledger'!$E$7:$E$1006,'Cash Ledger'!$I$7:$I$1006,$A16,'Cash Ledger'!$D$7:$D$1006,"Weekly pay",'Cash Ledger'!$B$7:$B$1006,">="&$C$5,'Cash Ledger'!$B$7:$B$1006,"<="&($C$5+6))) | M16: =IF($B16="","",MAX(0,$K16-$L16)) | N16: =IF($B16="","",$J16-$L16) | O16: =IF($B16="","",IF(ROUND($N16,0)<0,"owes you "&TEXT(ROUND(-$N16,0),"#,##0"),IF(AND(ROUND($N16,0)>0,$M16>0),"not yet paid",IF(ROUND($N16,0)>0,"you owe "&TEXT(ROUND($N16,0),"#,##0"),"settled")))) | Q16: =IF($U16="","",MEDIAN($C$5,$C$5+6,TODAY())) | R16: {=IF($U16="","",INDEX($B$12:$B$23,$U16))} | S16: =IF($U16="","","Weekly pay") | T16: {=IF($U16="","",INDEX($M$12:$M$23,$U16))} | U16: {=IFERROR(_xlfn.AGGREGATE(15,6,(ROW($M$12:$M$23)-ROW($M$12)+1)/(ISNUMBER($M$12:$M$23)*($M$12:$M$23>0)),ROWS($U$12:U16)),"")}
A17: =Workers!$A$11 -> W06 | B17: =IF(Workers!$B$11="","",Workers!$B$11) | C17: =IF($B17="","",Workers!$C$11) | D17: =IF($B17="","",IFERROR(INDEX(Weeks!$L$7:$W$59,MATCH($C$5,Weeks!$A$7:$A$59,0),MATCH($A17,Weeks!$L$5:$W$5,0)),0)) | E17: =IF(OR($B17="",N($H$8)=0),"",$D17/$H$8) | F17: =IF($B17="","",IFERROR(INDEX(Weeks!$X$7:$AI$59,MATCH($C$5,Weeks!$A$7:$A$59,0),MATCH($A17,Weeks!$X$5:$AI$5,0)),0)) | G17: =IF($B17="","",SUMPRODUCT((Weeks!$A$7:$A$59<$C$5)*(Weeks!$X$5:$AI$5=$A17)*Weeks!$X$7:$AI$59)-SUMIFS('Cash Ledger'!$E$7:$E$1006,'Cash Ledger'!$I$7:$I$1006,$A17,'Cash Ledger'!$B$7:$B$1006,"<"&$C$5)) | H17: =IF($B17="","",SUMIFS('Cash Ledger'!$E$7:$E$1006,'Cash Ledger'!$I$7:$I$1006,$A17,'Cash Ledger'!$D$7:$D$1006,"Advance",'Cash Ledger'!$B$7:$B$1006,">="&$C$5,'Cash Ledger'!$B$7:$B$1006,"<="&($C$5+6))) | I17: =IF($B17="","",SUMIFS('Cash Ledger'!$E$7:$E$1006,'Cash Ledger'!$I$7:$I$1006,$A17,'Cash Ledger'!$D$7:$D$1006,"Correction",'Cash Ledger'!$B$7:$B$1006,">="&$C$5,'Cash Ledger'!$B$7:$B$1006,"<="&($C$5+6))) | J17: =IF($B17="","",$G17+$F17-$H17-$I17) | K17: =IF($B17="","",ROUND(MAX(0,IF($G17>=0,$J17,$F17-$H17-$I17-MIN(-$G17,DebtCap*$F17))),0)) | L17: =IF($B17="","",SUMIFS('Cash Ledger'!$E$7:$E$1006,'Cash Ledger'!$I$7:$I$1006,$A17,'Cash Ledger'!$D$7:$D$1006,"Weekly pay",'Cash Ledger'!$B$7:$B$1006,">="&$C$5,'Cash Ledger'!$B$7:$B$1006,"<="&($C$5+6))) | M17: =IF($B17="","",MAX(0,$K17-$L17)) | N17: =IF($B17="","",$J17-$L17) | O17: =IF($B17="","",IF(ROUND($N17,0)<0,"owes you "&TEXT(ROUND(-$N17,0),"#,##0"),IF(AND(ROUND($N17,0)>0,$M17>0),"not yet paid",IF(ROUND($N17,0)>0,"you owe "&TEXT(ROUND($N17,0),"#,##0"),"settled")))) | Q17: =IF($U17="","",MEDIAN($C$5,$C$5+6,TODAY())) | R17: {=IF($U17="","",INDEX($B$12:$B$23,$U17))} | S17: =IF($U17="","","Weekly pay") | T17: {=IF($U17="","",INDEX($M$12:$M$23,$U17))} | U17: {=IFERROR(_xlfn.AGGREGATE(15,6,(ROW($M$12:$M$23)-ROW($M$12)+1)/(ISNUMBER($M$12:$M$23)*($M$12:$M$23>0)),ROWS($U$12:U17)),"")}
A18: =Workers!$A$12 -> W07 | B18: =IF(Workers!$B$12="","",Workers!$B$12) | C18: =IF($B18="","",Workers!$C$12) | D18: =IF($B18="","",IFERROR(INDEX(Weeks!$L$7:$W$59,MATCH($C$5,Weeks!$A$7:$A$59,0),MATCH($A18,Weeks!$L$5:$W$5,0)),0)) | E18: =IF(OR($B18="",N($H$8)=0),"",$D18/$H$8) | F18: =IF($B18="","",IFERROR(INDEX(Weeks!$X$7:$AI$59,MATCH($C$5,Weeks!$A$7:$A$59,0),MATCH($A18,Weeks!$X$5:$AI$5,0)),0)) | G18: =IF($B18="","",SUMPRODUCT((Weeks!$A$7:$A$59<$C$5)*(Weeks!$X$5:$AI$5=$A18)*Weeks!$X$7:$AI$59)-SUMIFS('Cash Ledger'!$E$7:$E$1006,'Cash Ledger'!$I$7:$I$1006,$A18,'Cash Ledger'!$B$7:$B$1006,"<"&$C$5)) | H18: =IF($B18="","",SUMIFS('Cash Ledger'!$E$7:$E$1006,'Cash Ledger'!$I$7:$I$1006,$A18,'Cash Ledger'!$D$7:$D$1006,"Advance",'Cash Ledger'!$B$7:$B$1006,">="&$C$5,'Cash Ledger'!$B$7:$B$1006,"<="&($C$5+6))) | I18: =IF($B18="","",SUMIFS('Cash Ledger'!$E$7:$E$1006,'Cash Ledger'!$I$7:$I$1006,$A18,'Cash Ledger'!$D$7:$D$1006,"Correction",'Cash Ledger'!$B$7:$B$1006,">="&$C$5,'Cash Ledger'!$B$7:$B$1006,"<="&($C$5+6))) | J18: =IF($B18="","",$G18+$F18-$H18-$I18) | K18: =IF($B18="","",ROUND(MAX(0,IF($G18>=0,$J18,$F18-$H18-$I18-MIN(-$G18,DebtCap*$F18))),0)) | L18: =IF($B18="","",SUMIFS('Cash Ledger'!$E$7:$E$1006,'Cash Ledger'!$I$7:$I$1006,$A18,'Cash Ledger'!$D$7:$D$1006,"Weekly pay",'Cash Ledger'!$B$7:$B$1006,">="&$C$5,'Cash Ledger'!$B$7:$B$1006,"<="&($C$5+6))) | M18: =IF($B18="","",MAX(0,$K18-$L18)) | N18: =IF($B18="","",$J18-$L18) | O18: =IF($B18="","",IF(ROUND($N18,0)<0,"owes you "&TEXT(ROUND(-$N18,0),"#,##0"),IF(AND(ROUND($N18,0)>0,$M18>0),"not yet paid",IF(ROUND($N18,0)>0,"you owe "&TEXT(ROUND($N18,0),"#,##0"),"settled")))) | Q18: =IF($U18="","",MEDIAN($C$5,$C$5+6,TODAY())) | R18: {=IF($U18="","",INDEX($B$12:$B$23,$U18))} | S18: =IF($U18="","","Weekly pay") | T18: {=IF($U18="","",INDEX($M$12:$M$23,$U18))} | U18: {=IFERROR(_xlfn.AGGREGATE(15,6,(ROW($M$12:$M$23)-ROW($M$12)+1)/(ISNUMBER($M$12:$M$23)*($M$12:$M$23>0)),ROWS($U$12:U18)),"")}
A19: =Workers!$A$13 -> W08 | B19: =IF(Workers!$B$13="","",Workers!$B$13) | C19: =IF($B19="","",Workers!$C$13) | D19: =IF($B19="","",IFERROR(INDEX(Weeks!$L$7:$W$59,MATCH($C$5,Weeks!$A$7:$A$59,0),MATCH($A19,Weeks!$L$5:$W$5,0)),0)) | E19: =IF(OR($B19="",N($H$8)=0),"",$D19/$H$8) | F19: =IF($B19="","",IFERROR(INDEX(Weeks!$X$7:$AI$59,MATCH($C$5,Weeks!$A$7:$A$59,0),MATCH($A19,Weeks!$X$5:$AI$5,0)),0)) | G19: =IF($B19="","",SUMPRODUCT((Weeks!$A$7:$A$59<$C$5)*(Weeks!$X$5:$AI$5=$A19)*Weeks!$X$7:$AI$59)-SUMIFS('Cash Ledger'!$E$7:$E$1006,'Cash Ledger'!$I$7:$I$1006,$A19,'Cash Ledger'!$B$7:$B$1006,"<"&$C$5)) | H19: =IF($B19="","",SUMIFS('Cash Ledger'!$E$7:$E$1006,'Cash Ledger'!$I$7:$I$1006,$A19,'Cash Ledger'!$D$7:$D$1006,"Advance",'Cash Ledger'!$B$7:$B$1006,">="&$C$5,'Cash Ledger'!$B$7:$B$1006,"<="&($C$5+6))) | I19: =IF($B19="","",SUMIFS('Cash Ledger'!$E$7:$E$1006,'Cash Ledger'!$I$7:$I$1006,$A19,'Cash Ledger'!$D$7:$D$1006,"Correction",'Cash Ledger'!$B$7:$B$1006,">="&$C$5,'Cash Ledger'!$B$7:$B$1006,"<="&($C$5+6))) | J19: =IF($B19="","",$G19+$F19-$H19-$I19) | K19: =IF($B19="","",ROUND(MAX(0,IF($G19>=0,$J19,$F19-$H19-$I19-MIN(-$G19,DebtCap*$F19))),0)) | L19: =IF($B19="","",SUMIFS('Cash Ledger'!$E$7:$E$1006,'Cash Ledger'!$I$7:$I$1006,$A19,'Cash Ledger'!$D$7:$D$1006,"Weekly pay",'Cash Ledger'!$B$7:$B$1006,">="&$C$5,'Cash Ledger'!$B$7:$B$1006,"<="&($C$5+6))) | M19: =IF($B19="","",MAX(0,$K19-$L19)) | N19: =IF($B19="","",$J19-$L19) | O19: =IF($B19="","",IF(ROUND($N19,0)<0,"owes you "&TEXT(ROUND(-$N19,0),"#,##0"),IF(AND(ROUND($N19,0)>0,$M19>0),"not yet paid",IF(ROUND($N19,0)>0,"you owe "&TEXT(ROUND($N19,0),"#,##0"),"settled")))) | Q19: =IF($U19="","",MEDIAN($C$5,$C$5+6,TODAY())) | R19: {=IF($U19="","",INDEX($B$12:$B$23,$U19))} | S19: =IF($U19="","","Weekly pay") | T19: {=IF($U19="","",INDEX($M$12:$M$23,$U19))} | U19: {=IFERROR(_xlfn.AGGREGATE(15,6,(ROW($M$12:$M$23)-ROW($M$12)+1)/(ISNUMBER($M$12:$M$23)*($M$12:$M$23>0)),ROWS($U$12:U19)),"")}
A20: =Workers!$A$14 -> W09 | B20: =IF(Workers!$B$14="","",Workers!$B$14) | C20: =IF($B20="","",Workers!$C$14) | D20: =IF($B20="","",IFERROR(INDEX(Weeks!$L$7:$W$59,MATCH($C$5,Weeks!$A$7:$A$59,0),MATCH($A20,Weeks!$L$5:$W$5,0)),0)) | E20: =IF(OR($B20="",N($H$8)=0),"",$D20/$H$8) | F20: =IF($B20="","",IFERROR(INDEX(Weeks!$X$7:$AI$59,MATCH($C$5,Weeks!$A$7:$A$59,0),MATCH($A20,Weeks!$X$5:$AI$5,0)),0)) | G20: =IF($B20="","",SUMPRODUCT((Weeks!$A$7:$A$59<$C$5)*(Weeks!$X$5:$AI$5=$A20)*Weeks!$X$7:$AI$59)-SUMIFS('Cash Ledger'!$E$7:$E$1006,'Cash Ledger'!$I$7:$I$1006,$A20,'Cash Ledger'!$B$7:$B$1006,"<"&$C$5)) | H20: =IF($B20="","",SUMIFS('Cash Ledger'!$E$7:$E$1006,'Cash Ledger'!$I$7:$I$1006,$A20,'Cash Ledger'!$D$7:$D$1006,"Advance",'Cash Ledger'!$B$7:$B$1006,">="&$C$5,'Cash Ledger'!$B$7:$B$1006,"<="&($C$5+6))) | I20: =IF($B20="","",SUMIFS('Cash Ledger'!$E$7:$E$1006,'Cash Ledger'!$I$7:$I$1006,$A20,'Cash Ledger'!$D$7:$D$1006,"Correction",'Cash Ledger'!$B$7:$B$1006,">="&$C$5,'Cash Ledger'!$B$7:$B$1006,"<="&($C$5+6))) | J20: =IF($B20="","",$G20+$F20-$H20-$I20) | K20: =IF($B20="","",ROUND(MAX(0,IF($G20>=0,$J20,$F20-$H20-$I20-MIN(-$G20,DebtCap*$F20))),0)) | L20: =IF($B20="","",SUMIFS('Cash Ledger'!$E$7:$E$1006,'Cash Ledger'!$I$7:$I$1006,$A20,'Cash Ledger'!$D$7:$D$1006,"Weekly pay",'Cash Ledger'!$B$7:$B$1006,">="&$C$5,'Cash Ledger'!$B$7:$B$1006,"<="&($C$5+6))) | M20: =IF($B20="","",MAX(0,$K20-$L20)) | N20: =IF($B20="","",$J20-$L20) | O20: =IF($B20="","",IF(ROUND($N20,0)<0,"owes you "&TEXT(ROUND(-$N20,0),"#,##0"),IF(AND(ROUND($N20,0)>0,$M20>0),"not yet paid",IF(ROUND($N20,0)>0,"you owe "&TEXT(ROUND($N20,0),"#,##0"),"settled")))) | Q20: =IF($U20="","",MEDIAN($C$5,$C$5+6,TODAY())) | R20: {=IF($U20="","",INDEX($B$12:$B$23,$U20))} | S20: =IF($U20="","","Weekly pay") | T20: {=IF($U20="","",INDEX($M$12:$M$23,$U20))} | U20: {=IFERROR(_xlfn.AGGREGATE(15,6,(ROW($M$12:$M$23)-ROW($M$12)+1)/(ISNUMBER($M$12:$M$23)*($M$12:$M$23>0)),ROWS($U$12:U20)),"")}
A21: =Workers!$A$15 -> W10 | B21: =IF(Workers!$B$15="","",Workers!$B$15) | C21: =IF($B21="","",Workers!$C$15) | D21: =IF($B21="","",IFERROR(INDEX(Weeks!$L$7:$W$59,MATCH($C$5,Weeks!$A$7:$A$59,0),MATCH($A21,Weeks!$L$5:$W$5,0)),0)) | E21: =IF(OR($B21="",N($H$8)=0),"",$D21/$H$8) | F21: =IF($B21="","",IFERROR(INDEX(Weeks!$X$7:$AI$59,MATCH($C$5,Weeks!$A$7:$A$59,0),MATCH($A21,Weeks!$X$5:$AI$5,0)),0)) | G21: =IF($B21="","",SUMPRODUCT((Weeks!$A$7:$A$59<$C$5)*(Weeks!$X$5:$AI$5=$A21)*Weeks!$X$7:$AI$59)-SUMIFS('Cash Ledger'!$E$7:$E$1006,'Cash Ledger'!$I$7:$I$1006,$A21,'Cash Ledger'!$B$7:$B$1006,"<"&$C$5)) | H21: =IF($B21="","",SUMIFS('Cash Ledger'!$E$7:$E$1006,'Cash Ledger'!$I$7:$I$1006,$A21,'Cash Ledger'!$D$7:$D$1006,"Advance",'Cash Ledger'!$B$7:$B$1006,">="&$C$5,'Cash Ledger'!$B$7:$B$1006,"<="&($C$5+6))) | I21: =IF($B21="","",SUMIFS('Cash Ledger'!$E$7:$E$1006,'Cash Ledger'!$I$7:$I$1006,$A21,'Cash Ledger'!$D$7:$D$1006,"Correction",'Cash Ledger'!$B$7:$B$1006,">="&$C$5,'Cash Ledger'!$B$7:$B$1006,"<="&($C$5+6))) | J21: =IF($B21="","",$G21+$F21-$H21-$I21) | K21: =IF($B21="","",ROUND(MAX(0,IF($G21>=0,$J21,$F21-$H21-$I21-MIN(-$G21,DebtCap*$F21))),0)) | L21: =IF($B21="","",SUMIFS('Cash Ledger'!$E$7:$E$1006,'Cash Ledger'!$I$7:$I$1006,$A21,'Cash Ledger'!$D$7:$D$1006,"Weekly pay",'Cash Ledger'!$B$7:$B$1006,">="&$C$5,'Cash Ledger'!$B$7:$B$1006,"<="&($C$5+6))) | M21: =IF($B21="","",MAX(0,$K21-$L21)) | N21: =IF($B21="","",$J21-$L21) | O21: =IF($B21="","",IF(ROUND($N21,0)<0,"owes you "&TEXT(ROUND(-$N21,0),"#,##0"),IF(AND(ROUND($N21,0)>0,$M21>0),"not yet paid",IF(ROUND($N21,0)>0,"you owe "&TEXT(ROUND($N21,0),"#,##0"),"settled")))) | Q21: =IF($U21="","",MEDIAN($C$5,$C$5+6,TODAY())) | R21: {=IF($U21="","",INDEX($B$12:$B$23,$U21))} | S21: =IF($U21="","","Weekly pay") | T21: {=IF($U21="","",INDEX($M$12:$M$23,$U21))} | U21: {=IFERROR(_xlfn.AGGREGATE(15,6,(ROW($M$12:$M$23)-ROW($M$12)+1)/(ISNUMBER($M$12:$M$23)*($M$12:$M$23>0)),ROWS($U$12:U21)),"")}
A22: =Workers!$A$16 -> W11 | B22: =IF(Workers!$B$16="","",Workers!$B$16) | C22: =IF($B22="","",Workers!$C$16) | D22: =IF($B22="","",IFERROR(INDEX(Weeks!$L$7:$W$59,MATCH($C$5,Weeks!$A$7:$A$59,0),MATCH($A22,Weeks!$L$5:$W$5,0)),0)) | E22: =IF(OR($B22="",N($H$8)=0),"",$D22/$H$8) | F22: =IF($B22="","",IFERROR(INDEX(Weeks!$X$7:$AI$59,MATCH($C$5,Weeks!$A$7:$A$59,0),MATCH($A22,Weeks!$X$5:$AI$5,0)),0)) | G22: =IF($B22="","",SUMPRODUCT((Weeks!$A$7:$A$59<$C$5)*(Weeks!$X$5:$AI$5=$A22)*Weeks!$X$7:$AI$59)-SUMIFS('Cash Ledger'!$E$7:$E$1006,'Cash Ledger'!$I$7:$I$1006,$A22,'Cash Ledger'!$B$7:$B$1006,"<"&$C$5)) | H22: =IF($B22="","",SUMIFS('Cash Ledger'!$E$7:$E$1006,'Cash Ledger'!$I$7:$I$1006,$A22,'Cash Ledger'!$D$7:$D$1006,"Advance",'Cash Ledger'!$B$7:$B$1006,">="&$C$5,'Cash Ledger'!$B$7:$B$1006,"<="&($C$5+6))) | I22: =IF($B22="","",SUMIFS('Cash Ledger'!$E$7:$E$1006,'Cash Ledger'!$I$7:$I$1006,$A22,'Cash Ledger'!$D$7:$D$1006,"Correction",'Cash Ledger'!$B$7:$B$1006,">="&$C$5,'Cash Ledger'!$B$7:$B$1006,"<="&($C$5+6))) | J22: =IF($B22="","",$G22+$F22-$H22-$I22) | K22: =IF($B22="","",ROUND(MAX(0,IF($G22>=0,$J22,$F22-$H22-$I22-MIN(-$G22,DebtCap*$F22))),0)) | L22: =IF($B22="","",SUMIFS('Cash Ledger'!$E$7:$E$1006,'Cash Ledger'!$I$7:$I$1006,$A22,'Cash Ledger'!$D$7:$D$1006,"Weekly pay",'Cash Ledger'!$B$7:$B$1006,">="&$C$5,'Cash Ledger'!$B$7:$B$1006,"<="&($C$5+6))) | M22: =IF($B22="","",MAX(0,$K22-$L22)) | N22: =IF($B22="","",$J22-$L22) | O22: =IF($B22="","",IF(ROUND($N22,0)<0,"owes you "&TEXT(ROUND(-$N22,0),"#,##0"),IF(AND(ROUND($N22,0)>0,$M22>0),"not yet paid",IF(ROUND($N22,0)>0,"you owe "&TEXT(ROUND($N22,0),"#,##0"),"settled")))) | Q22: =IF($U22="","",MEDIAN($C$5,$C$5+6,TODAY())) | R22: {=IF($U22="","",INDEX($B$12:$B$23,$U22))} | S22: =IF($U22="","","Weekly pay") | T22: {=IF($U22="","",INDEX($M$12:$M$23,$U22))} | U22: {=IFERROR(_xlfn.AGGREGATE(15,6,(ROW($M$12:$M$23)-ROW($M$12)+1)/(ISNUMBER($M$12:$M$23)*($M$12:$M$23>0)),ROWS($U$12:U22)),"")}
A23: =Workers!$A$17 -> W12 | B23: =IF(Workers!$B$17="","",Workers!$B$17) | C23: =IF($B23="","",Workers!$C$17) | D23: =IF($B23="","",IFERROR(INDEX(Weeks!$L$7:$W$59,MATCH($C$5,Weeks!$A$7:$A$59,0),MATCH($A23,Weeks!$L$5:$W$5,0)),0)) | E23: =IF(OR($B23="",N($H$8)=0),"",$D23/$H$8) | F23: =IF($B23="","",IFERROR(INDEX(Weeks!$X$7:$AI$59,MATCH($C$5,Weeks!$A$7:$A$59,0),MATCH($A23,Weeks!$X$5:$AI$5,0)),0)) | G23: =IF($B23="","",SUMPRODUCT((Weeks!$A$7:$A$59<$C$5)*(Weeks!$X$5:$AI$5=$A23)*Weeks!$X$7:$AI$59)-SUMIFS('Cash Ledger'!$E$7:$E$1006,'Cash Ledger'!$I$7:$I$1006,$A23,'Cash Ledger'!$B$7:$B$1006,"<"&$C$5)) | H23: =IF($B23="","",SUMIFS('Cash Ledger'!$E$7:$E$1006,'Cash Ledger'!$I$7:$I$1006,$A23,'Cash Ledger'!$D$7:$D$1006,"Advance",'Cash Ledger'!$B$7:$B$1006,">="&$C$5,'Cash Ledger'!$B$7:$B$1006,"<="&($C$5+6))) | I23: =IF($B23="","",SUMIFS('Cash Ledger'!$E$7:$E$1006,'Cash Ledger'!$I$7:$I$1006,$A23,'Cash Ledger'!$D$7:$D$1006,"Correction",'Cash Ledger'!$B$7:$B$1006,">="&$C$5,'Cash Ledger'!$B$7:$B$1006,"<="&($C$5+6))) | J23: =IF($B23="","",$G23+$F23-$H23-$I23) | K23: =IF($B23="","",ROUND(MAX(0,IF($G23>=0,$J23,$F23-$H23-$I23-MIN(-$G23,DebtCap*$F23))),0)) | L23: =IF($B23="","",SUMIFS('Cash Ledger'!$E$7:$E$1006,'Cash Ledger'!$I$7:$I$1006,$A23,'Cash Ledger'!$D$7:$D$1006,"Weekly pay",'Cash Ledger'!$B$7:$B$1006,">="&$C$5,'Cash Ledger'!$B$7:$B$1006,"<="&($C$5+6))) | M23: =IF($B23="","",MAX(0,$K23-$L23)) | N23: =IF($B23="","",$J23-$L23) | O23: =IF($B23="","",IF(ROUND($N23,0)<0,"owes you "&TEXT(ROUND(-$N23,0),"#,##0"),IF(AND(ROUND($N23,0)>0,$M23>0),"not yet paid",IF(ROUND($N23,0)>0,"you owe "&TEXT(ROUND($N23,0),"#,##0"),"settled")))) | Q23: =IF($U23="","",MEDIAN($C$5,$C$5+6,TODAY())) | R23: {=IF($U23="","",INDEX($B$12:$B$23,$U23))} | S23: =IF($U23="","","Weekly pay") | T23: {=IF($U23="","",INDEX($M$12:$M$23,$U23))} | U23: {=IFERROR(_xlfn.AGGREGATE(15,6,(ROW($M$12:$M$23)-ROW($M$12)+1)/(ISNUMBER($M$12:$M$23)*($M$12:$M$23>0)),ROWS($U$12:U23)),"")}
B24: Crew total | D24: =SUM(D12:D23) -> 24 | F24: =SUM(F12:F23) -> 5928500 | G24: =SUM(G12:G23) -> 0 | H24: =SUM(H12:H23) -> 650000 | I24: =SUM(I12:I23) -> 0 | J24: =SUM(J12:J23) -> 5278500 | K24: =SUM(K12:K23) -> 5278500 | L24: =SUM(L12:L23) -> 0 | M24: =SUM(M12:M23) -> 5278500 | N24: =SUM(N12:N23) -> 5278500 | Q24: ="Rows to copy: "&COUNT($U$12:$U$23) -> Rows to copy: 4
B26: Before you pay
B27: Shares add up to the pot | F27: =IF(ABS($F$24-$F$8)<=12,"OK","MISMATCH: "&TEXT(ROUND($F$24-$F$8,0),"#,##0")) -> OK
B28: Everyone's days match the crew total | F28: =IF(ABS($D$24-$H$8)<0.001,"OK","MISMATCH - check attendance") -> OK
B29: Pot is shared out | F29: =IF(AND($F$8>0,$H$8=0),"NO - mark attendance in the Daily Log","OK") -> OK
B30: Reject rate | F30: =IF($F$8=0,"-",IF(N($J$8)>RejectAlarm,"HIGH - look at curing and handling","OK")) -> OK
B31: Cash needed for payday | F31: =$M$24 -> 5278500
B33: Brought forward: positive = you still owe the worker from earlier weeks; negative = the worker owes you.
B34: TO PAY is never below zero. If advances were bigger than earnings, pay is 0 and the rest carries to next week.
B35: After paying, record each payment in the Cash Ledger as 'Weekly pay' with a date inside this week - 'Still to pay' then drops to 0.

Sheet Payslip
A1: ◆ Donabay | C1: Home | D1: Daily Log | E1: Cash Ledger | F1: Weekly Pay | I1: Payslip | K1: Workers | M1: Settings | O1: Guide | Q1: · | R1: History | T1: Weeks | V1: Checks
A2: Payslip
A3: Pick a week and a worker, print, and have the worker sign when paid.
B5: Week starting (Monday) | C5: 46286
B6: Worker | C6: Xusanboy | D6: =IFERROR(INDEX(WorkerIDs,MATCH($C$6,WorkerNames,0)),"unknown worker") -> W02
B8: DONABAY - PAYSLIP
B9: =$C$6 -> Xusanboy | C9: =$C$5 -> 46286 | D9: =$C$5+6 -> 46292
B11: Crew paid blocks this week | C11: =IFERROR(INDEX(Weeks!$F$7:$F$59,MATCH($C$5,Weeks!$A$7:$A$59,0)),0) -> 11857
B12: Crew pot | C12: =IFERROR(INDEX(Weeks!$G$7:$G$59,MATCH($C$5,Weeks!$A$7:$A$59,0)),0) -> 5928500
B13: Crew-days worked | C13: =IFERROR(INDEX(Weeks!$H$7:$H$59,MATCH($C$5,Weeks!$A$7:$A$59,0)),0) -> 24
B14: Your days | C14: =IFERROR(INDEX(Weeks!$L$7:$W$59,MATCH($C$5,Weeks!$A$7:$A$59,0),MATCH($D$6,Weeks!$L$5:$W$5,0)),0) -> 6
B15: Your share | C15: =IF(N($C$13)=0,0,$C$14/$C$13) -> 0.25
B17: Earned this week | C17: =IFERROR(INDEX(Weeks!$X$7:$AI$59,MATCH($C$5,Weeks!$A$7:$A$59,0),MATCH($D$6,Weeks!$X$5:$AI$5,0)),0) -> 1482125
B18: Brought forward from earlier weeks | C18: =SUMPRODUCT((Weeks!$A$7:$A$59<$C$5)*(Weeks!$X$5:$AI$5=$D$6)*Weeks!$X$7:$AI$59)-SUMIFS('Cash Ledger'!$E$7:$E$1006,'Cash Ledger'!$I$7:$I$1006,$D$6,'Cash Ledger'!$B$7:$B$1006,"<"&$C$5) -> 0
B19: Advances this week (listed below) | C19: =-SUMIFS('Cash Ledger'!$E$7:$E$1006,'Cash Ledger'!$I$7:$I$1006,$D$6,'Cash Ledger'!$D$7:$D$1006,"Advance",'Cash Ledger'!$B$7:$B$1006,">="&$C$5,'Cash Ledger'!$B$7:$B$1006,"<="&($C$5+6)) -> -500000
B20: Corrections this week | C20: =-SUMIFS('Cash Ledger'!$E$7:$E$1006,'Cash Ledger'!$I$7:$I$1006,$D$6,'Cash Ledger'!$D$7:$D$1006,"Correction",'Cash Ledger'!$B$7:$B$1006,">="&$C$5,'Cash Ledger'!$B$7:$B$1006,"<="&($C$5+6)) -> 0
B21: Due | C21: =$C$17+$C$18+$C$19+$C$20 -> 982125
B23: TO PAY NOW | C23: =ROUND(MAX(0,IF($C$18>=0,$C$21,$C$17+$C$19+$C$20-MIN(-$C$18,DebtCap*$C$17))),0) -> 982125
B24: Already paid this week (ledger) | C24: =SUMIFS('Cash Ledger'!$E$7:$E$1006,'Cash Ledger'!$I$7:$I$1006,$D$6,'Cash Ledger'!$D$7:$D$1006,"Weekly pay",'Cash Ledger'!$B$7:$B$1006,">="&$C$5,'Cash Ledger'!$B$7:$B$1006,"<="&($C$5+6)) -> 0
B25: Carried to next week | C25: =$C$21-$C$24 -> 982125 | D25: =IF(ROUND($C$25,0)<0,"you owe the workshop "&TEXT(ROUND(-$C$25,0),"#,##0")&" so'm",IF(ROUND($C$25,0)>0,"the workshop owes you "&TEXT(ROUND($C$25,0),"#,##0")&" so'm","settled")) -> the workshop owes you 982,125 so'm
B27: Advances taken this week
B28: Date | C28: Amount (so'm) | D28: Reason
B29: =IFERROR(INDEX('Cash Ledger'!$B$7:$B$1006,MATCH($D$6&"|"&$C$5&"|"&1,'Cash Ledger'!$K$7:$K$1006,0)),"") -> 46287 | C29: =IFERROR(INDEX('Cash Ledger'!$E$7:$E$1006,MATCH($D$6&"|"&$C$5&"|"&1,'Cash Ledger'!$K$7:$K$1006,0)),"") -> 500000 | D29: =IFERROR(INDEX('Cash Ledger'!$F$7:$F$1006,MATCH($D$6&"|"&$C$5&"|"&1,'Cash Ledger'!$K$7:$K$1006,0)),"") -> Karta+Naqd
B30: =IFERROR(INDEX('Cash Ledger'!$B$7:$B$1006,MATCH($D$6&"|"&$C$5&"|"&2,'Cash Ledger'!$K$7:$K$1006,0)),"") | C30: =IFERROR(INDEX('Cash Ledger'!$E$7:$E$1006,MATCH($D$6&"|"&$C$5&"|"&2,'Cash Ledger'!$K$7:$K$1006,0)),"") | D30: =IFERROR(INDEX('Cash Ledger'!$F$7:$F$1006,MATCH($D$6&"|"&$C$5&"|"&2,'Cash Ledger'!$K$7:$K$1006,0)),"")
B31: =IFERROR(INDEX('Cash Ledger'!$B$7:$B$1006,MATCH($D$6&"|"&$C$5&"|"&3,'Cash Ledger'!$K$7:$K$1006,0)),"") | C31: =IFERROR(INDEX('Cash Ledger'!$E$7:$E$1006,MATCH($D$6&"|"&$C$5&"|"&3,'Cash Ledger'!$K$7:$K$1006,0)),"") | D31: =IFERROR(INDEX('Cash Ledger'!$F$7:$F$1006,MATCH($D$6&"|"&$C$5&"|"&3,'Cash Ledger'!$K$7:$K$1006,0)),"")
B32: =IFERROR(INDEX('Cash Ledger'!$B$7:$B$1006,MATCH($D$6&"|"&$C$5&"|"&4,'Cash Ledger'!$K$7:$K$1006,0)),"") | C32: =IFERROR(INDEX('Cash Ledger'!$E$7:$E$1006,MATCH($D$6&"|"&$C$5&"|"&4,'Cash Ledger'!$K$7:$K$1006,0)),"") | D32: =IFERROR(INDEX('Cash Ledger'!$F$7:$F$1006,MATCH($D$6&"|"&$C$5&"|"&4,'Cash Ledger'!$K$7:$K$1006,0)),"")
B33: =IFERROR(INDEX('Cash Ledger'!$B$7:$B$1006,MATCH($D$6&"|"&$C$5&"|"&5,'Cash Ledger'!$K$7:$K$1006,0)),"") | C33: =IFERROR(INDEX('Cash Ledger'!$E$7:$E$1006,MATCH($D$6&"|"&$C$5&"|"&5,'Cash Ledger'!$K$7:$K$1006,0)),"") | D33: =IFERROR(INDEX('Cash Ledger'!$F$7:$F$1006,MATCH($D$6&"|"&$C$5&"|"&5,'Cash Ledger'!$K$7:$K$1006,0)),"")
B34: =IFERROR(INDEX('Cash Ledger'!$B$7:$B$1006,MATCH($D$6&"|"&$C$5&"|"&6,'Cash Ledger'!$K$7:$K$1006,0)),"") | C34: =IFERROR(INDEX('Cash Ledger'!$E$7:$E$1006,MATCH($D$6&"|"&$C$5&"|"&6,'Cash Ledger'!$K$7:$K$1006,0)),"") | D34: =IFERROR(INDEX('Cash Ledger'!$F$7:$F$1006,MATCH($D$6&"|"&$C$5&"|"&6,'Cash Ledger'!$K$7:$K$1006,0)),"")
B35: =IFERROR(INDEX('Cash Ledger'!$B$7:$B$1006,MATCH($D$6&"|"&$C$5&"|"&7,'Cash Ledger'!$K$7:$K$1006,0)),"") | C35: =IFERROR(INDEX('Cash Ledger'!$E$7:$E$1006,MATCH($D$6&"|"&$C$5&"|"&7,'Cash Ledger'!$K$7:$K$1006,0)),"") | D35: =IFERROR(INDEX('Cash Ledger'!$F$7:$F$1006,MATCH($D$6&"|"&$C$5&"|"&7,'Cash Ledger'!$K$7:$K$1006,0)),"")
B36: =IFERROR(INDEX('Cash Ledger'!$B$7:$B$1006,MATCH($D$6&"|"&$C$5&"|"&8,'Cash Ledger'!$K$7:$K$1006,0)),"") | C36: =IFERROR(INDEX('Cash Ledger'!$E$7:$E$1006,MATCH($D$6&"|"&$C$5&"|"&8,'Cash Ledger'!$K$7:$K$1006,0)),"") | D36: =IFERROR(INDEX('Cash Ledger'!$F$7:$F$1006,MATCH($D$6&"|"&$C$5&"|"&8,'Cash Ledger'!$K$7:$K$1006,0)),"")
B37: =IFERROR(INDEX('Cash Ledger'!$B$7:$B$1006,MATCH($D$6&"|"&$C$5&"|"&9,'Cash Ledger'!$K$7:$K$1006,0)),"") | C37: =IFERROR(INDEX('Cash Ledger'!$E$7:$E$1006,MATCH($D$6&"|"&$C$5&"|"&9,'Cash Ledger'!$K$7:$K$1006,0)),"") | D37: =IFERROR(INDEX('Cash Ledger'!$F$7:$F$1006,MATCH($D$6&"|"&$C$5&"|"&9,'Cash Ledger'!$K$7:$K$1006,0)),"")
B38: =IFERROR(INDEX('Cash Ledger'!$B$7:$B$1006,MATCH($D$6&"|"&$C$5&"|"&10,'Cash Ledger'!$K$7:$K$1006,0)),"") | C38: =IFERROR(INDEX('Cash Ledger'!$E$7:$E$1006,MATCH($D$6&"|"&$C$5&"|"&10,'Cash Ledger'!$K$7:$K$1006,0)),"") | D38: =IFERROR(INDEX('Cash Ledger'!$F$7:$F$1006,MATCH($D$6&"|"&$C$5&"|"&10,'Cash Ledger'!$K$7:$K$1006,0)),"")
B39: =IF(COUNTIFS('Cash Ledger'!$I$7:$I$1006,$D$6,'Cash Ledger'!$D$7:$D$1006,"Advance",'Cash Ledger'!$B$7:$B$1006,">="&$C$5,'Cash Ledger'!$B$7:$B$1006,"<="&($C$5+6))>10,"More advances than fit here - see the Cash Ledger","")
B41: Worker's signature
B43: Paid by
B45: Date paid

Sheet Worker History
A1: ◆ Donabay | C1: Home | D1: Daily Log | F1: Cash Ledger | H1: Weekly Pay | I1: Payslip | K1: Workers | M1: Settings | O1: Guide | Q1: · | R1: History | T1: Weeks | V1: Checks
A2: Worker History
A3: One worker's whole account, week by week: earned, taken, paid, and where the balance stands.
B5: Worker | C5: Xusanboy | D5: =IFERROR(INDEX(WorkerIDs,MATCH($C$5,WorkerNames,0)),"unknown worker") -> W02
G6: + you owe them / - they owe you
A7: Week of | B7: Days | C7: Earned | D7: Advances | E7: Corrections | F7: Weekly pay | G7: Balance after the week | H7: Meaning
A8: =Weeks!$A$7 -> 46286 | B8: =IF($A8>TODAY(),"",IFERROR(INDEX(Weeks!$L$7:$W$59,MATCH($A8,Weeks!$A$7:$A$59,0),MATCH($D$5,Weeks!$L$5:$W$5,0)),0)) -> 6 | C8: =IF($A8>TODAY(),"",IFERROR(INDEX(Weeks!$X$7:$AI$59,MATCH($A8,Weeks!$A$7:$A$59,0),MATCH($D$5,Weeks!$X$5:$AI$5,0)),0)) -> 1482125 | D8: =IF($A8>TODAY(),"",SUMIFS('Cash Ledger'!$E$7:$E$1006,'Cash Ledger'!$I$7:$I$1006,$D$5,'Cash Ledger'!$D$7:$D$1006,"Advance",'Cash Ledger'!$B$7:$B$1006,">="&$A8,'Cash Ledger'!$B$7:$B$1006,"<="&($A8+6))) -> 500000 | E8: =IF($A8>TODAY(),"",SUMIFS('Cash Ledger'!$E$7:$E$1006,'Cash Ledger'!$I$7:$I$1006,$D$5,'Cash Ledger'!$D$7:$D$1006,"Correction",'Cash Ledger'!$B$7:$B$1006,">="&$A8,'Cash Ledger'!$B$7:$B$1006,"<="&($A8+6))) -> 0 | F8: =IF($A8>TODAY(),"",SUMIFS('Cash Ledger'!$E$7:$E$1006,'Cash Ledger'!$I$7:$I$1006,$D$5,'Cash Ledger'!$D$7:$D$1006,"Weekly pay",'Cash Ledger'!$B$7:$B$1006,">="&$A8,'Cash Ledger'!$B$7:$B$1006,"<="&($A8+6))) -> 0 | G8: =IF($A8>TODAY(),"",SUMPRODUCT((Weeks!$A$7:$A$59<=$A8)*(Weeks!$X$5:$AI$5=$D$5)*Weeks!$X$7:$AI$59)-SUMIFS('Cash Ledger'!$E$7:$E$1006,'Cash Ledger'!$I$7:$I$1006,$D$5,'Cash Ledger'!$B$7:$B$1006,"<="&($A8+6))) -> 982125 | H8: =IF(OR($A8>TODAY(),$G8=""),"",IF(ROUND($G8,0)<0,"owes you",IF(ROUND($G8,0)>0,"you owe","settled"))) -> you owe
A9: =Weeks!$A$8 -> 46293 | B9: =IF($A9>TODAY(),"",IFERROR(INDEX(Weeks!$L$7:$W$59,MATCH($A9,Weeks!$A$7:$A$59,0),MATCH($D$5,Weeks!$L$5:$W$5,0)),0)) | C9: =IF($A9>TODAY(),"",IFERROR(INDEX(Weeks!$X$7:$AI$59,MATCH($A9,Weeks!$A$7:$A$59,0),MATCH($D$5,Weeks!$X$5:$AI$5,0)),0)) | D9: =IF($A9>TODAY(),"",SUMIFS('Cash Ledger'!$E$7:$E$1006,'Cash Ledger'!$I$7:$I$1006,$D$5,'Cash Ledger'!$D$7:$D$1006,"Advance",'Cash Ledger'!$B$7:$B$1006,">="&$A9,'Cash Ledger'!$B$7:$B$1006,"<="&($A9+6))) | E9: =IF($A9>TODAY(),"",SUMIFS('Cash Ledger'!$E$7:$E$1006,'Cash Ledger'!$I$7:$I$1006,$D$5,'Cash Ledger'!$D$7:$D$1006,"Correction",'Cash Ledger'!$B$7:$B$1006,">="&$A9,'Cash Ledger'!$B$7:$B$1006,"<="&($A9+6))) | F9: =IF($A9>TODAY(),"",SUMIFS('Cash Ledger'!$E$7:$E$1006,'Cash Ledger'!$I$7:$I$1006,$D$5,'Cash Ledger'!$D$7:$D$1006,"Weekly pay",'Cash Ledger'!$B$7:$B$1006,">="&$A9,'Cash Ledger'!$B$7:$B$1006,"<="&($A9+6))) | G9: =IF($A9>TODAY(),"",SUMPRODUCT((Weeks!$A$7:$A$59<=$A9)*(Weeks!$X$5:$AI$5=$D$5)*Weeks!$X$7:$AI$59)-SUMIFS('Cash Ledger'!$E$7:$E$1006,'Cash Ledger'!$I$7:$I$1006,$D$5,'Cash Ledger'!$B$7:$B$1006,"<="&($A9+6))) | H9: =IF(OR($A9>TODAY(),$G9=""),"",IF(ROUND($G9,0)<0,"owes you",IF(ROUND($G9,0)>0,"you owe","settled")))
A10: =Weeks!$A$9 -> 46300 | B10: =IF($A10>TODAY(),"",IFERROR(INDEX(Weeks!$L$7:$W$59,MATCH($A10,Weeks!$A$7:$A$59,0),MATCH($D$5,Weeks!$L$5:$W$5,0)),0)) | C10: =IF($A10>TODAY(),"",IFERROR(INDEX(Weeks!$X$7:$AI$59,MATCH($A10,Weeks!$A$7:$A$59,0),MATCH($D$5,Weeks!$X$5:$AI$5,0)),0)) | D10: =IF($A10>TODAY(),"",SUMIFS('Cash Ledger'!$E$7:$E$1006,'Cash Ledger'!$I$7:$I$1006,$D$5,'Cash Ledger'!$D$7:$D$1006,"Advance",'Cash Ledger'!$B$7:$B$1006,">="&$A10,'Cash Ledger'!$B$7:$B$1006,"<="&($A10+6))) | E10: =IF($A10>TODAY(),"",SUMIFS('Cash Ledger'!$E$7:$E$1006,'Cash Ledger'!$I$7:$I$1006,$D$5,'Cash Ledger'!$D$7:$D$1006,"Correction",'Cash Ledger'!$B$7:$B$1006,">="&$A10,'Cash Ledger'!$B$7:$B$1006,"<="&($A10+6))) | F10: =IF($A10>TODAY(),"",SUMIFS('Cash Ledger'!$E$7:$E$1006,'Cash Ledger'!$I$7:$I$1006,$D$5,'Cash Ledger'!$D$7:$D$1006,"Weekly pay",'Cash Ledger'!$B$7:$B$1006,">="&$A10,'Cash Ledger'!$B$7:$B$1006,"<="&($A10+6))) | G10: =IF($A10>TODAY(),"",SUMPRODUCT((Weeks!$A$7:$A$59<=$A10)*(Weeks!$X$5:$AI$5=$D$5)*Weeks!$X$7:$AI$59)-SUMIFS('Cash Ledger'!$E$7:$E$1006,'Cash Ledger'!$I$7:$I$1006,$D$5,'Cash Ledger'!$B$7:$B$1006,"<="&($A10+6))) | H10: =IF(OR($A10>TODAY(),$G10=""),"",IF(ROUND($G10,0)<0,"owes you",IF(ROUND($G10,0)>0,"you owe","settled")))
A11: =Weeks!$A$10 -> 46307 | B11: =IF($A11>TODAY(),"",IFERROR(INDEX(Weeks!$L$7:$W$59,MATCH($A11,Weeks!$A$7:$A$59,0),MATCH($D$5,Weeks!$L$5:$W$5,0)),0)) | C11: =IF($A11>TODAY(),"",IFERROR(INDEX(Weeks!$X$7:$AI$59,MATCH($A11,Weeks!$A$7:$A$59,0),MATCH($D$5,Weeks!$X$5:$AI$5,0)),0)) | D11: =IF($A11>TODAY(),"",SUMIFS('Cash Ledger'!$E$7:$E$1006,'Cash Ledger'!$I$7:$I$1006,$D$5,'Cash Ledger'!$D$7:$D$1006,"Advance",'Cash Ledger'!$B$7:$B$1006,">="&$A11,'Cash Ledger'!$B$7:$B$1006,"<="&($A11+6))) | E11: =IF($A11>TODAY(),"",SUMIFS('Cash Ledger'!$E$7:$E$1006,'Cash Ledger'!$I$7:$I$1006,$D$5,'Cash Ledger'!$D$7:$D$1006,"Correction",'Cash Ledger'!$B$7:$B$1006,">="&$A11,'Cash Ledger'!$B$7:$B$1006,"<="&($A11+6))) | F11: =IF($A11>TODAY(),"",SUMIFS('Cash Ledger'!$E$7:$E$1006,'Cash Ledger'!$I$7:$I$1006,$D$5,'Cash Ledger'!$D$7:$D$1006,"Weekly pay",'Cash Ledger'!$B$7:$B$1006,">="&$A11,'Cash Ledger'!$B$7:$B$1006,"<="&($A11+6))) | G11: =IF($A11>TODAY(),"",SUMPRODUCT((Weeks!$A$7:$A$59<=$A11)*(Weeks!$X$5:$AI$5=$D$5)*Weeks!$X$7:$AI$59)-SUMIFS('Cash Ledger'!$E$7:$E$1006,'Cash Ledger'!$I$7:$I$1006,$D$5,'Cash Ledger'!$B$7:$B$1006,"<="&($A11+6))) | H11: =IF(OR($A11>TODAY(),$G11=""),"",IF(ROUND($G11,0)<0,"owes you",IF(ROUND($G11,0)>0,"you owe","settled")))
A12: =Weeks!$A$11 -> 46314 | B12: =IF($A12>TODAY(),"",IFERROR(INDEX(Weeks!$L$7:$W$59,MATCH($A12,Weeks!$A$7:$A$59,0),MATCH($D$5,Weeks!$L$5:$W$5,0)),0)) | C12: =IF($A12>TODAY(),"",IFERROR(INDEX(Weeks!$X$7:$AI$59,MATCH($A12,Weeks!$A$7:$A$59,0),MATCH($D$5,Weeks!$X$5:$AI$5,0)),0)) | D12: =IF($A12>TODAY(),"",SUMIFS('Cash Ledger'!$E$7:$E$1006,'Cash Ledger'!$I$7:$I$1006,$D$5,'Cash Ledger'!$D$7:$D$1006,"Advance",'Cash Ledger'!$B$7:$B$1006,">="&$A12,'Cash Ledger'!$B$7:$B$1006,"<="&($A12+6))) | E12: =IF($A12>TODAY(),"",SUMIFS('Cash Ledger'!$E$7:$E$1006,'Cash Ledger'!$I$7:$I$1006,$D$5,'Cash Ledger'!$D$7:$D$1006,"Correction",'Cash Ledger'!$B$7:$B$1006,">="&$A12,'Cash Ledger'!$B$7:$B$1006,"<="&($A12+6))) | F12: =IF($A12>TODAY(),"",SUMIFS('Cash Ledger'!$E$7:$E$1006,'Cash Ledger'!$I$7:$I$1006,$D$5,'Cash Ledger'!$D$7:$D$1006,"Weekly pay",'Cash Ledger'!$B$7:$B$1006,">="&$A12,'Cash Ledger'!$B$7:$B$1006,"<="&($A12+6))) | G12: =IF($A12>TODAY(),"",SUMPRODUCT((Weeks!$A$7:$A$59<=$A12)*(Weeks!$X$5:$AI$5=$D$5)*Weeks!$X$7:$AI$59)-SUMIFS('Cash Ledger'!$E$7:$E$1006,'Cash Ledger'!$I$7:$I$1006,$D$5,'Cash Ledger'!$B$7:$B$1006,"<="&($A12+6))) | H12: =IF(OR($A12>TODAY(),$G12=""),"",IF(ROUND($G12,0)<0,"owes you",IF(ROUND($G12,0)>0,"you owe","settled")))
A13: =Weeks!$A$12 -> 46321 | B13: =IF($A13>TODAY(),"",IFERROR(INDEX(Weeks!$L$7:$W$59,MATCH($A13,Weeks!$A$7:$A$59,0),MATCH($D$5,Weeks!$L$5:$W$5,0)),0)) | C13: =IF($A13>TODAY(),"",IFERROR(INDEX(Weeks!$X$7:$AI$59,MATCH($A13,Weeks!$A$7:$A$59,0),MATCH($D$5,Weeks!$X$5:$AI$5,0)),0)) | D13: =IF($A13>TODAY(),"",SUMIFS('Cash Ledger'!$E$7:$E$1006,'Cash Ledger'!$I$7:$I$1006,$D$5,'Cash Ledger'!$D$7:$D$1006,"Advance",'Cash Ledger'!$B$7:$B$1006,">="&$A13,'Cash Ledger'!$B$7:$B$1006,"<="&($A13+6))) | E13: =IF($A13>TODAY(),"",SUMIFS('Cash Ledger'!$E$7:$E$1006,'Cash Ledger'!$I$7:$I$1006,$D$5,'Cash Ledger'!$D$7:$D$1006,"Correction",'Cash Ledger'!$B$7:$B$1006,">="&$A13,'Cash Ledger'!$B$7:$B$1006,"<="&($A13+6))) | F13: =IF($A13>TODAY(),"",SUMIFS('Cash Ledger'!$E$7:$E$1006,'Cash Ledger'!$I$7:$I$1006,$D$5,'Cash Ledger'!$D$7:$D$1006,"Weekly pay",'Cash Ledger'!$B$7:$B$1006,">="&$A13,'Cash Ledger'!$B$7:$B$1006,"<="&($A13+6))) | G13: =IF($A13>TODAY(),"",SUMPRODUCT((Weeks!$A$7:$A$59<=$A13)*(Weeks!$X$5:$AI$5=$D$5)*Weeks!$X$7:$AI$59)-SUMIFS('Cash Ledger'!$E$7:$E$1006,'Cash Ledger'!$I$7:$I$1006,$D$5,'Cash Ledger'!$B$7:$B$1006,"<="&($A13+6))) | H13: =IF(OR($A13>TODAY(),$G13=""),"",IF(ROUND($G13,0)<0,"owes you",IF(ROUND($G13,0)>0,"you owe","settled")))
A14: =Weeks!$A$13 -> 46328 | B14: =IF($A14>TODAY(),"",IFERROR(INDEX(Weeks!$L$7:$W$59,MATCH($A14,Weeks!$A$7:$A$59,0),MATCH($D$5,Weeks!$L$5:$W$5,0)),0)) | C14: =IF($A14>TODAY(),"",IFERROR(INDEX(Weeks!$X$7:$AI$59,MATCH($A14,Weeks!$A$7:$A$59,0),MATCH($D$5,Weeks!$X$5:$AI$5,0)),0)) | D14: =IF($A14>TODAY(),"",SUMIFS('Cash Ledger'!$E$7:$E$1006,'Cash Ledger'!$I$7:$I$1006,$D$5,'Cash Ledger'!$D$7:$D$1006,"Advance",'Cash Ledger'!$B$7:$B$1006,">="&$A14,'Cash Ledger'!$B$7:$B$1006,"<="&($A14+6))) | E14: =IF($A14>TODAY(),"",SUMIFS('Cash Ledger'!$E$7:$E$1006,'Cash Ledger'!$I$7:$I$1006,$D$5,'Cash Ledger'!$D$7:$D$1006,"Correction",'Cash Ledger'!$B$7:$B$1006,">="&$A14,'Cash Ledger'!$B$7:$B$1006,"<="&($A14+6))) | F14: =IF($A14>TODAY(),"",SUMIFS('Cash Ledger'!$E$7:$E$1006,'Cash Ledger'!$I$7:$I$1006,$D$5,'Cash Ledger'!$D$7:$D$1006,"Weekly pay",'Cash Ledger'!$B$7:$B$1006,">="&$A14,'Cash Ledger'!$B$7:$B$1006,"<="&($A14+6))) | G14: =IF($A14>TODAY(),"",SUMPRODUCT((Weeks!$A$7:$A$59<=$A14)*(Weeks!$X$5:$AI$5=$D$5)*Weeks!$X$7:$AI$59)-SUMIFS('Cash Ledger'!$E$7:$E$1006,'Cash Ledger'!$I$7:$I$1006,$D$5,'Cash Ledger'!$B$7:$B$1006,"<="&($A14+6))) | H14: =IF(OR($A14>TODAY(),$G14=""),"",IF(ROUND($G14,0)<0,"owes you",IF(ROUND($G14,0)>0,"you owe","settled")))
A15: =Weeks!$A$14 -> 46335 | B15: =IF($A15>TODAY(),"",IFERROR(INDEX(Weeks!$L$7:$W$59,MATCH($A15,Weeks!$A$7:$A$59,0),MATCH($D$5,Weeks!$L$5:$W$5,0)),0)) | C15: =IF($A15>TODAY(),"",IFERROR(INDEX(Weeks!$X$7:$AI$59,MATCH($A15,Weeks!$A$7:$A$59,0),MATCH($D$5,Weeks!$X$5:$AI$5,0)),0)) | D15: =IF($A15>TODAY(),"",SUMIFS('Cash Ledger'!$E$7:$E$1006,'Cash Ledger'!$I$7:$I$1006,$D$5,'Cash Ledger'!$D$7:$D$1006,"Advance",'Cash Ledger'!$B$7:$B$1006,">="&$A15,'Cash Ledger'!$B$7:$B$1006,"<="&($A15+6))) | E15: =IF($A15>TODAY(),"",SUMIFS('Cash Ledger'!$E$7:$E$1006,'Cash Ledger'!$I$7:$I$1006,$D$5,'Cash Ledger'!$D$7:$D$1006,"Correction",'Cash Ledger'!$B$7:$B$1006,">="&$A15,'Cash Ledger'!$B$7:$B$1006,"<="&($A15+6))) | F15: =IF($A15>TODAY(),"",SUMIFS('Cash Ledger'!$E$7:$E$1006,'Cash Ledger'!$I$7:$I$1006,$D$5,'Cash Ledger'!$D$7:$D$1006,"Weekly pay",'Cash Ledger'!$B$7:$B$1006,">="&$A15,'Cash Ledger'!$B$7:$B$1006,"<="&($A15+6))) | G15: =IF($A15>TODAY(),"",SUMPRODUCT((Weeks!$A$7:$A$59<=$A15)*(Weeks!$X$5:$AI$5=$D$5)*Weeks!$X$7:$AI$59)-SUMIFS('Cash Ledger'!$E$7:$E$1006,'Cash Ledger'!$I$7:$I$1006,$D$5,'Cash Ledger'!$B$7:$B$1006,"<="&($A15+6))) | H15: =IF(OR($A15>TODAY(),$G15=""),"",IF(ROUND($G15,0)<0,"owes you",IF(ROUND($G15,0)>0,"you owe","settled")))
A16: =Weeks!$A$15 -> 46342 | B16: =IF($A16>TODAY(),"",IFERROR(INDEX(Weeks!$L$7:$W$59,MATCH($A16,Weeks!$A$7:$A$59,0),MATCH($D$5,Weeks!$L$5:$W$5,0)),0)) | C16: =IF($A16>TODAY(),"",IFERROR(INDEX(Weeks!$X$7:$AI$59,MATCH($A16,Weeks!$A$7:$A$59,0),MATCH($D$5,Weeks!$X$5:$AI$5,0)),0)) | D16: =IF($A16>TODAY(),"",SUMIFS('Cash Ledger'!$E$7:$E$1006,'Cash Ledger'!$I$7:$I$1006,$D$5,'Cash Ledger'!$D$7:$D$1006,"Advance",'Cash Ledger'!$B$7:$B$1006,">="&$A16,'Cash Ledger'!$B$7:$B$1006,"<="&($A16+6))) | E16: =IF($A16>TODAY(),"",SUMIFS('Cash Ledger'!$E$7:$E$1006,'Cash Ledger'!$I$7:$I$1006,$D$5,'Cash Ledger'!$D$7:$D$1006,"Correction",'Cash Ledger'!$B$7:$B$1006,">="&$A16,'Cash Ledger'!$B$7:$B$1006,"<="&($A16+6))) | F16: =IF($A16>TODAY(),"",SUMIFS('Cash Ledger'!$E$7:$E$1006,'Cash Ledger'!$I$7:$I$1006,$D$5,'Cash Ledger'!$D$7:$D$1006,"Weekly pay",'Cash Ledger'!$B$7:$B$1006,">="&$A16,'Cash Ledger'!$B$7:$B$1006,"<="&($A16+6))) | G16: =IF($A16>TODAY(),"",SUMPRODUCT((Weeks!$A$7:$A$59<=$A16)*(Weeks!$X$5:$AI$5=$D$5)*Weeks!$X$7:$AI$59)-SUMIFS('Cash Ledger'!$E$7:$E$1006,'Cash Ledger'!$I$7:$I$1006,$D$5,'Cash Ledger'!$B$7:$B$1006,"<="&($A16+6))) | H16: =IF(OR($A16>TODAY(),$G16=""),"",IF(ROUND($G16,0)<0,"owes you",IF(ROUND($G16,0)>0,"you owe","settled")))
A17: =Weeks!$A$16 -> 46349 | B17: =IF($A17>TODAY(),"",IFERROR(INDEX(Weeks!$L$7:$W$59,MATCH($A17,Weeks!$A$7:$A$59,0),MATCH($D$5,Weeks!$L$5:$W$5,0)),0)) | C17: =IF($A17>TODAY(),"",IFERROR(INDEX(Weeks!$X$7:$AI$59,MATCH($A17,Weeks!$A$7:$A$59,0),MATCH($D$5,Weeks!$X$5:$AI$5,0)),0)) | D17: =IF($A17>TODAY(),"",SUMIFS('Cash Ledger'!$E$7:$E$1006,'Cash Ledger'!$I$7:$I$1006,$D$5,'Cash Ledger'!$D$7:$D$1006,"Advance",'Cash Ledger'!$B$7:$B$1006,">="&$A17,'Cash Ledger'!$B$7:$B$1006,"<="&($A17+6))) | E17: =IF($A17>TODAY(),"",SUMIFS('Cash Ledger'!$E$7:$E$1006,'Cash Ledger'!$I$7:$I$1006,$D$5,'Cash Ledger'!$D$7:$D$1006,"Correction",'Cash Ledger'!$B$7:$B$1006,">="&$A17,'Cash Ledger'!$B$7:$B$1006,"<="&($A17+6))) | F17: =IF($A17>TODAY(),"",SUMIFS('Cash Ledger'!$E$7:$E$1006,'Cash Ledger'!$I$7:$I$1006,$D$5,'Cash Ledger'!$D$7:$D$1006,"Weekly pay",'Cash Ledger'!$B$7:$B$1006,">="&$A17,'Cash Ledger'!$B$7:$B$1006,"<="&($A17+6))) | G17: =IF($A17>TODAY(),"",SUMPRODUCT((Weeks!$A$7:$A$59<=$A17)*(Weeks!$X$5:$AI$5=$D$5)*Weeks!$X$7:$AI$59)-SUMIFS('Cash Ledger'!$E$7:$E$1006,'Cash Ledger'!$I$7:$I$1006,$D$5,'Cash Ledger'!$B$7:$B$1006,"<="&($A17+6))) | H17: =IF(OR($A17>TODAY(),$G17=""),"",IF(ROUND($G17,0)<0,"owes you",IF(ROUND($G17,0)>0,"you owe","settled")))
A18: =Weeks!$A$17 -> 46356 | B18: =IF($A18>TODAY(),"",IFERROR(INDEX(Weeks!$L$7:$W$59,MATCH($A18,Weeks!$A$7:$A$59,0),MATCH($D$5,Weeks!$L$5:$W$5,0)),0)) | C18: =IF($A18>TODAY(),"",IFERROR(INDEX(Weeks!$X$7:$AI$59,MATCH($A18,Weeks!$A$7:$A$59,0),MATCH($D$5,Weeks!$X$5:$AI$5,0)),0)) | D18: =IF($A18>TODAY(),"",SUMIFS('Cash Ledger'!$E$7:$E$1006,'Cash Ledger'!$I$7:$I$1006,$D$5,'Cash Ledger'!$D$7:$D$1006,"Advance",'Cash Ledger'!$B$7:$B$1006,">="&$A18,'Cash Ledger'!$B$7:$B$1006,"<="&($A18+6))) | E18: =IF($A18>TODAY(),"",SUMIFS('Cash Ledger'!$E$7:$E$1006,'Cash Ledger'!$I$7:$I$1006,$D$5,'Cash Ledger'!$D$7:$D$1006,"Correction",'Cash Ledger'!$B$7:$B$1006,">="&$A18,'Cash Ledger'!$B$7:$B$1006,"<="&($A18+6))) | F18: =IF($A18>TODAY(),"",SUMIFS('Cash Ledger'!$E$7:$E$1006,'Cash Ledger'!$I$7:$I$1006,$D$5,'Cash Ledger'!$D$7:$D$1006,"Weekly pay",'Cash Ledger'!$B$7:$B$1006,">="&$A18,'Cash Ledger'!$B$7:$B$1006,"<="&($A18+6))) | G18: =IF($A18>TODAY(),"",SUMPRODUCT((Weeks!$A$7:$A$59<=$A18)*(Weeks!$X$5:$AI$5=$D$5)*Weeks!$X$7:$AI$59)-SUMIFS('Cash Ledger'!$E$7:$E$1006,'Cash Ledger'!$I$7:$I$1006,$D$5,'Cash Ledger'!$B$7:$B$1006,"<="&($A18+6))) | H18: =IF(OR($A18>TODAY(),$G18=""),"",IF(ROUND($G18,0)<0,"owes you",IF(ROUND($G18,0)>0,"you owe","settled")))
A19: =Weeks!$A$18 -> 46363 | B19: =IF($A19>TODAY(),"",IFERROR(INDEX(Weeks!$L$7:$W$59,MATCH($A19,Weeks!$A$7:$A$59,0),MATCH($D$5,Weeks!$L$5:$W$5,0)),0)) | C19: =IF($A19>TODAY(),"",IFERROR(INDEX(Weeks!$X$7:$AI$59,MATCH($A19,Weeks!$A$7:$A$59,0),MATCH($D$5,Weeks!$X$5:$AI$5,0)),0)) | D19: =IF($A19>TODAY(),"",SUMIFS('Cash Ledger'!$E$7:$E$1006,'Cash Ledger'!$I$7:$I$1006,$D$5,'Cash Ledger'!$D$7:$D$1006,"Advance",'Cash Ledger'!$B$7:$B$1006,">="&$A19,'Cash Ledger'!$B$7:$B$1006,"<="&($A19+6))) | E19: =IF($A19>TODAY(),"",SUMIFS('Cash Ledger'!$E$7:$E$1006,'Cash Ledger'!$I$7:$I$1006,$D$5,'Cash Ledger'!$D$7:$D$1006,"Correction",'Cash Ledger'!$B$7:$B$1006,">="&$A19,'Cash Ledger'!$B$7:$B$1006,"<="&($A19+6))) | F19: =IF($A19>TODAY(),"",SUMIFS('Cash Ledger'!$E$7:$E$1006,'Cash Ledger'!$I$7:$I$1006,$D$5,'Cash Ledger'!$D$7:$D$1006,"Weekly pay",'Cash Ledger'!$B$7:$B$1006,">="&$A19,'Cash Ledger'!$B$7:$B$1006,"<="&($A19+6))) | G19: =IF($A19>TODAY(),"",SUMPRODUCT((Weeks!$A$7:$A$59<=$A19)*(Weeks!$X$5:$AI$5=$D$5)*Weeks!$X$7:$AI$59)-SUMIFS('Cash Ledger'!$E$7:$E$1006,'Cash Ledger'!$I$7:$I$1006,$D$5,'Cash Ledger'!$B$7:$B$1006,"<="&($A19+6))) | H19: =IF(OR($A19>TODAY(),$G19=""),"",IF(ROUND($G19,0)<0,"owes you",IF(ROUND($G19,0)>0,"you owe","settled")))
A20: =Weeks!$A$19 -> 46370 | B20: =IF($A20>TODAY(),"",IFERROR(INDEX(Weeks!$L$7:$W$59,MATCH($A20,Weeks!$A$7:$A$59,0),MATCH($D$5,Weeks!$L$5:$W$5,0)),0)) | C20: =IF($A20>TODAY(),"",IFERROR(INDEX(Weeks!$X$7:$AI$59,MATCH($A20,Weeks!$A$7:$A$59,0),MATCH($D$5,Weeks!$X$5:$AI$5,0)),0)) | D20: =IF($A20>TODAY(),"",SUMIFS('Cash Ledger'!$E$7:$E$1006,'Cash Ledger'!$I$7:$I$1006,$D$5,'Cash Ledger'!$D$7:$D$1006,"Advance",'Cash Ledger'!$B$7:$B$1006,">="&$A20,'Cash Ledger'!$B$7:$B$1006,"<="&($A20+6))) | E20: =IF($A20>TODAY(),"",SUMIFS('Cash Ledger'!$E$7:$E$1006,'Cash Ledger'!$I$7:$I$1006,$D$5,'Cash Ledger'!$D$7:$D$1006,"Correction",'Cash Ledger'!$B$7:$B$1006,">="&$A20,'Cash Ledger'!$B$7:$B$1006,"<="&($A20+6))) | F20: =IF($A20>TODAY(),"",SUMIFS('Cash Ledger'!$E$7:$E$1006,'Cash Ledger'!$I$7:$I$1006,$D$5,'Cash Ledger'!$D$7:$D$1006,"Weekly pay",'Cash Ledger'!$B$7:$B$1006,">="&$A20,'Cash Ledger'!$B$7:$B$1006,"<="&($A20+6))) | G20: =IF($A20>TODAY(),"",SUMPRODUCT((Weeks!$A$7:$A$59<=$A20)*(Weeks!$X$5:$AI$5=$D$5)*Weeks!$X$7:$AI$59)-SUMIFS('Cash Ledger'!$E$7:$E$1006,'Cash Ledger'!$I$7:$I$1006,$D$5,'Cash Ledger'!$B$7:$B$1006,"<="&($A20+6))) | H20: =IF(OR($A20>TODAY(),$G20=""),"",IF(ROUND($G20,0)<0,"owes you",IF(ROUND($G20,0)>0,"you owe","settled")))
A21: =Weeks!$A$20 -> 46377 | B21: =IF($A21>TODAY(),"",IFERROR(INDEX(Weeks!$L$7:$W$59,MATCH($A21,Weeks!$A$7:$A$59,0),MATCH($D$5,Weeks!$L$5:$W$5,0)),0)) | C21: =IF($A21>TODAY(),"",IFERROR(INDEX(Weeks!$X$7:$AI$59,MATCH($A21,Weeks!$A$7:$A$59,0),MATCH($D$5,Weeks!$X$5:$AI$5,0)),0)) | D21: =IF($A21>TODAY(),"",SUMIFS('Cash Ledger'!$E$7:$E$1006,'Cash Ledger'!$I$7:$I$1006,$D$5,'Cash Ledger'!$D$7:$D$1006,"Advance",'Cash Ledger'!$B$7:$B$1006,">="&$A21,'Cash Ledger'!$B$7:$B$1006,"<="&($A21+6))) | E21: =IF($A21>TODAY(),"",SUMIFS('Cash Ledger'!$E$7:$E$1006,'Cash Ledger'!$I$7:$I$1006,$D$5,'Cash Ledger'!$D$7:$D$1006,"Correction",'Cash Ledger'!$B$7:$B$1006,">="&$A21,'Cash Ledger'!$B$7:$B$1006,"<="&($A21+6))) | F21: =IF($A21>TODAY(),"",SUMIFS('Cash Ledger'!$E$7:$E$1006,'Cash Ledger'!$I$7:$I$1006,$D$5,'Cash Ledger'!$D$7:$D$1006,"Weekly pay",'Cash Ledger'!$B$7:$B$1006,">="&$A21,'Cash Ledger'!$B$7:$B$1006,"<="&($A21+6))) | G21: =IF($A21>TODAY(),"",SUMPRODUCT((Weeks!$A$7:$A$59<=$A21)*(Weeks!$X$5:$AI$5=$D$5)*Weeks!$X$7:$AI$59)-SUMIFS('Cash Ledger'!$E$7:$E$1006,'Cash Ledger'!$I$7:$I$1006,$D$5,'Cash Ledger'!$B$7:$B$1006,"<="&($A21+6))) | H21: =IF(OR($A21>TODAY(),$G21=""),"",IF(ROUND($G21,0)<0,"owes you",IF(ROUND($G21,0)>0,"you owe","settled")))
A22: =Weeks!$A$21 -> 46384 | B22: =IF($A22>TODAY(),"",IFERROR(INDEX(Weeks!$L$7:$W$59,MATCH($A22,Weeks!$A$7:$A$59,0),MATCH($D$5,Weeks!$L$5:$W$5,0)),0)) | C22: =IF($A22>TODAY(),"",IFERROR(INDEX(Weeks!$X$7:$AI$59,MATCH($A22,Weeks!$A$7:$A$59,0),MATCH($D$5,Weeks!$X$5:$AI$5,0)),0)) | D22: =IF($A22>TODAY(),"",SUMIFS('Cash Ledger'!$E$7:$E$1006,'Cash Ledger'!$I$7:$I$1006,$D$5,'Cash Ledger'!$D$7:$D$1006,"Advance",'Cash Ledger'!$B$7:$B$1006,">="&$A22,'Cash Ledger'!$B$7:$B$1006,"<="&($A22+6))) | E22: =IF($A22>TODAY(),"",SUMIFS('Cash Ledger'!$E$7:$E$1006,'Cash Ledger'!$I$7:$I$1006,$D$5,'Cash Ledger'!$D$7:$D$1006,"Correction",'Cash Ledger'!$B$7:$B$1006,">="&$A22,'Cash Ledger'!$B$7:$B$1006,"<="&($A22+6))) | F22: =IF($A22>TODAY(),"",SUMIFS('Cash Ledger'!$E$7:$E$1006,'Cash Ledger'!$I$7:$I$1006,$D$5,'Cash Ledger'!$D$7:$D$1006,"Weekly pay",'Cash Ledger'!$B$7:$B$1006,">="&$A22,'Cash Ledger'!$B$7:$B$1006,"<="&($A22+6))) | G22: =IF($A22>TODAY(),"",SUMPRODUCT((Weeks!$A$7:$A$59<=$A22)*(Weeks!$X$5:$AI$5=$D$5)*Weeks!$X$7:$AI$59)-SUMIFS('Cash Ledger'!$E$7:$E$1006,'Cash Ledger'!$I$7:$I$1006,$D$5,'Cash Ledger'!$B$7:$B$1006,"<="&($A22+6))) | H22: =IF(OR($A22>TODAY(),$G22=""),"",IF(ROUND($G22,0)<0,"owes you",IF(ROUND($G22,0)>0,"you owe","settled")))
A23: =Weeks!$A$22 -> 46391 | B23: =IF($A23>TODAY(),"",IFERROR(INDEX(Weeks!$L$7:$W$59,MATCH($A23,Weeks!$A$7:$A$59,0),MATCH($D$5,Weeks!$L$5:$W$5,0)),0)) | C23: =IF($A23>TODAY(),"",IFERROR(INDEX(Weeks!$X$7:$AI$59,MATCH($A23,Weeks!$A$7:$A$59,0),MATCH($D$5,Weeks!$X$5:$AI$5,0)),0)) | D23: =IF($A23>TODAY(),"",SUMIFS('Cash Ledger'!$E$7:$E$1006,'Cash Ledger'!$I$7:$I$1006,$D$5,'Cash Ledger'!$D$7:$D$1006,"Advance",'Cash Ledger'!$B$7:$B$1006,">="&$A23,'Cash Ledger'!$B$7:$B$1006,"<="&($A23+6))) | E23: =IF($A23>TODAY(),"",SUMIFS('Cash Ledger'!$E$7:$E$1006,'Cash Ledger'!$I$7:$I$1006,$D$5,'Cash Ledger'!$D$7:$D$1006,"Correction",'Cash Ledger'!$B$7:$B$1006,">="&$A23,'Cash Ledger'!$B$7:$B$1006,"<="&($A23+6))) | F23: =IF($A23>TODAY(),"",SUMIFS('Cash Ledger'!$E$7:$E$1006,'Cash Ledger'!$I$7:$I$1006,$D$5,'Cash Ledger'!$D$7:$D$1006,"Weekly pay",'Cash Ledger'!$B$7:$B$1006,">="&$A23,'Cash Ledger'!$B$7:$B$1006,"<="&($A23+6))) | G23: =IF($A23>TODAY(),"",SUMPRODUCT((Weeks!$A$7:$A$59<=$A23)*(Weeks!$X$5:$AI$5=$D$5)*Weeks!$X$7:$AI$59)-SUMIFS('Cash Ledger'!$E$7:$E$1006,'Cash Ledger'!$I$7:$I$1006,$D$5,'Cash Ledger'!$B$7:$B$1006,"<="&($A23+6))) | H23: =IF(OR($A23>TODAY(),$G23=""),"",IF(ROUND($G23,0)<0,"owes you",IF(ROUND($G23,0)>0,"you owe","settled")))
A24: =Weeks!$A$23 -> 46398 | B24: =IF($A24>TODAY(),"",IFERROR(INDEX(Weeks!$L$7:$W$59,MATCH($A24,Weeks!$A$7:$A$59,0),MATCH($D$5,Weeks!$L$5:$W$5,0)),0)) | C24: =IF($A24>TODAY(),"",IFERROR(INDEX(Weeks!$X$7:$AI$59,MATCH($A24,Weeks!$A$7:$A$59,0),MATCH($D$5,Weeks!$X$5:$AI$5,0)),0)) | D24: =IF($A24>TODAY(),"",SUMIFS('Cash Ledger'!$E$7:$E$1006,'Cash Ledger'!$I$7:$I$1006,$D$5,'Cash Ledger'!$D$7:$D$1006,"Advance",'Cash Ledger'!$B$7:$B$1006,">="&$A24,'Cash Ledger'!$B$7:$B$1006,"<="&($A24+6))) | E24: =IF($A24>TODAY(),"",SUMIFS('Cash Ledger'!$E$7:$E$1006,'Cash Ledger'!$I$7:$I$1006,$D$5,'Cash Ledger'!$D$7:$D$1006,"Correction",'Cash Ledger'!$B$7:$B$1006,">="&$A24,'Cash Ledger'!$B$7:$B$1006,"<="&($A24+6))) | F24: =IF($A24>TODAY(),"",SUMIFS('Cash Ledger'!$E$7:$E$1006,'Cash Ledger'!$I$7:$I$1006,$D$5,'Cash Ledger'!$D$7:$D$1006,"Weekly pay",'Cash Ledger'!$B$7:$B$1006,">="&$A24,'Cash Ledger'!$B$7:$B$1006,"<="&($A24+6))) | G24: =IF($A24>TODAY(),"",SUMPRODUCT((Weeks!$A$7:$A$59<=$A24)*(Weeks!$X$5:$AI$5=$D$5)*Weeks!$X$7:$AI$59)-SUMIFS('Cash Ledger'!$E$7:$E$1006,'Cash Ledger'!$I$7:$I$1006,$D$5,'Cash Ledger'!$B$7:$B$1006,"<="&($A24+6))) | H24: =IF(OR($A24>TODAY(),$G24=""),"",IF(ROUND($G24,0)<0,"owes you",IF(ROUND($G24,0)>0,"you owe","settled")))
A25: =Weeks!$A$24 -> 46405 | B25: =IF($A25>TODAY(),"",IFERROR(INDEX(Weeks!$L$7:$W$59,MATCH($A25,Weeks!$A$7:$A$59,0),MATCH($D$5,Weeks!$L$5:$W$5,0)),0)) | C25: =IF($A25>TODAY(),"",IFERROR(INDEX(Weeks!$X$7:$AI$59,MATCH($A25,Weeks!$A$7:$A$59,0),MATCH($D$5,Weeks!$X$5:$AI$5,0)),0)) | D25: =IF($A25>TODAY(),"",SUMIFS('Cash Ledger'!$E$7:$E$1006,'Cash Ledger'!$I$7:$I$1006,$D$5,'Cash Ledger'!$D$7:$D$1006,"Advance",'Cash Ledger'!$B$7:$B$1006,">="&$A25,'Cash Ledger'!$B$7:$B$1006,"<="&($A25+6))) | E25: =IF($A25>TODAY(),"",SUMIFS('Cash Ledger'!$E$7:$E$1006,'Cash Ledger'!$I$7:$I$1006,$D$5,'Cash Ledger'!$D$7:$D$1006,"Correction",'Cash Ledger'!$B$7:$B$1006,">="&$A25,'Cash Ledger'!$B$7:$B$1006,"<="&($A25+6))) | F25: =IF($A25>TODAY(),"",SUMIFS('Cash Ledger'!$E$7:$E$1006,'Cash Ledger'!$I$7:$I$1006,$D$5,'Cash Ledger'!$D$7:$D$1006,"Weekly pay",'Cash Ledger'!$B$7:$B$1006,">="&$A25,'Cash Ledger'!$B$7:$B$1006,"<="&($A25+6))) | G25: =IF($A25>TODAY(),"",SUMPRODUCT((Weeks!$A$7:$A$59<=$A25)*(Weeks!$X$5:$AI$5=$D$5)*Weeks!$X$7:$AI$59)-SUMIFS('Cash Ledger'!$E$7:$E$1006,'Cash Ledger'!$I$7:$I$1006,$D$5,'Cash Ledger'!$B$7:$B$1006,"<="&($A25+6))) | H25: =IF(OR($A25>TODAY(),$G25=""),"",IF(ROUND($G25,0)<0,"owes you",IF(ROUND($G25,0)>0,"you owe","settled")))
A26: =Weeks!$A$25 -> 46412 | B26: =IF($A26>TODAY(),"",IFERROR(INDEX(Weeks!$L$7:$W$59,MATCH($A26,Weeks!$A$7:$A$59,0),MATCH($D$5,Weeks!$L$5:$W$5,0)),0)) | C26: =IF($A26>TODAY(),"",IFERROR(INDEX(Weeks!$X$7:$AI$59,MATCH($A26,Weeks!$A$7:$A$59,0),MATCH($D$5,Weeks!$X$5:$AI$5,0)),0)) | D26: =IF($A26>TODAY(),"",SUMIFS('Cash Ledger'!$E$7:$E$1006,'Cash Ledger'!$I$7:$I$1006,$D$5,'Cash Ledger'!$D$7:$D$1006,"Advance",'Cash Ledger'!$B$7:$B$1006,">="&$A26,'Cash Ledger'!$B$7:$B$1006,"<="&($A26+6))) | E26: =IF($A26>TODAY(),"",SUMIFS('Cash Ledger'!$E$7:$E$1006,'Cash Ledger'!$I$7:$I$1006,$D$5,'Cash Ledger'!$D$7:$D$1006,"Correction",'Cash Ledger'!$B$7:$B$1006,">="&$A26,'Cash Ledger'!$B$7:$B$1006,"<="&($A26+6))) | F26: =IF($A26>TODAY(),"",SUMIFS('Cash Ledger'!$E$7:$E$1006,'Cash Ledger'!$I$7:$I$1006,$D$5,'Cash Ledger'!$D$7:$D$1006,"Weekly pay",'Cash Ledger'!$B$7:$B$1006,">="&$A26,'Cash Ledger'!$B$7:$B$1006,"<="&($A26+6))) | G26: =IF($A26>TODAY(),"",SUMPRODUCT((Weeks!$A$7:$A$59<=$A26)*(Weeks!$X$5:$AI$5=$D$5)*Weeks!$X$7:$AI$59)-SUMIFS('Cash Ledger'!$E$7:$E$1006,'Cash Ledger'!$I$7:$I$1006,$D$5,'Cash Ledger'!$B$7:$B$1006,"<="&($A26+6))) | H26: =IF(OR($A26>TODAY(),$G26=""),"",IF(ROUND($G26,0)<0,"owes you",IF(ROUND($G26,0)>0,"you owe","settled")))
A27: =Weeks!$A$26 -> 46419 | B27: =IF($A27>TODAY(),"",IFERROR(INDEX(Weeks!$L$7:$W$59,MATCH($A27,Weeks!$A$7:$A$59,0),MATCH($D$5,Weeks!$L$5:$W$5,0)),0)) | C27: =IF($A27>TODAY(),"",IFERROR(INDEX(Weeks!$X$7:$AI$59,MATCH($A27,Weeks!$A$7:$A$59,0),MATCH($D$5,Weeks!$X$5:$AI$5,0)),0)) | D27: =IF($A27>TODAY(),"",SUMIFS('Cash Ledger'!$E$7:$E$1006,'Cash Ledger'!$I$7:$I$1006,$D$5,'Cash Ledger'!$D$7:$D$1006,"Advance",'Cash Ledger'!$B$7:$B$1006,">="&$A27,'Cash Ledger'!$B$7:$B$1006,"<="&($A27+6))) | E27: =IF($A27>TODAY(),"",SUMIFS('Cash Ledger'!$E$7:$E$1006,'Cash Ledger'!$I$7:$I$1006,$D$5,'Cash Ledger'!$D$7:$D$1006,"Correction",'Cash Ledger'!$B$7:$B$1006,">="&$A27,'Cash Ledger'!$B$7:$B$1006,"<="&($A27+6))) | F27: =IF($A27>TODAY(),"",SUMIFS('Cash Ledger'!$E$7:$E$1006,'Cash Ledger'!$I$7:$I$1006,$D$5,'Cash Ledger'!$D$7:$D$1006,"Weekly pay",'Cash Ledger'!$B$7:$B$1006,">="&$A27,'Cash Ledger'!$B$7:$B$1006,"<="&($A27+6))) | G27: =IF($A27>TODAY(),"",SUMPRODUCT((Weeks!$A$7:$A$59<=$A27)*(Weeks!$X$5:$AI$5=$D$5)*Weeks!$X$7:$AI$59)-SUMIFS('Cash Ledger'!$E$7:$E$1006,'Cash Ledger'!$I$7:$I$1006,$D$5,'Cash Ledger'!$B$7:$B$1006,"<="&($A27+6))) | H27: =IF(OR($A27>TODAY(),$G27=""),"",IF(ROUND($G27,0)<0,"owes you",IF(ROUND($G27,0)>0,"you owe","settled")))
A28: =Weeks!$A$27 -> 46426 | B28: =IF($A28>TODAY(),"",IFERROR(INDEX(Weeks!$L$7:$W$59,MATCH($A28,Weeks!$A$7:$A$59,0),MATCH($D$5,Weeks!$L$5:$W$5,0)),0)) | C28: =IF($A28>TODAY(),"",IFERROR(INDEX(Weeks!$X$7:$AI$59,MATCH($A28,Weeks!$A$7:$A$59,0),MATCH($D$5,Weeks!$X$5:$AI$5,0)),0)) | D28: =IF($A28>TODAY(),"",SUMIFS('Cash Ledger'!$E$7:$E$1006,'Cash Ledger'!$I$7:$I$1006,$D$5,'Cash Ledger'!$D$7:$D$1006,"Advance",'Cash Ledger'!$B$7:$B$1006,">="&$A28,'Cash Ledger'!$B$7:$B$1006,"<="&($A28+6))) | E28: =IF($A28>TODAY(),"",SUMIFS('Cash Ledger'!$E$7:$E$1006,'Cash Ledger'!$I$7:$I$1006,$D$5,'Cash Ledger'!$D$7:$D$1006,"Correction",'Cash Ledger'!$B$7:$B$1006,">="&$A28,'Cash Ledger'!$B$7:$B$1006,"<="&($A28+6))) | F28: =IF($A28>TODAY(),"",SUMIFS('Cash Ledger'!$E$7:$E$1006,'Cash Ledger'!$I$7:$I$1006,$D$5,'Cash Ledger'!$D$7:$D$1006,"Weekly pay",'Cash Ledger'!$B$7:$B$1006,">="&$A28,'Cash Ledger'!$B$7:$B$1006,"<="&($A28+6))) | G28: =IF($A28>TODAY(),"",SUMPRODUCT((Weeks!$A$7:$A$59<=$A28)*(Weeks!$X$5:$AI$5=$D$5)*Weeks!$X$7:$AI$59)-SUMIFS('Cash Ledger'!$E$7:$E$1006,'Cash Ledger'!$I$7:$I$1006,$D$5,'Cash Ledger'!$B$7:$B$1006,"<="&($A28+6))) | H28: =IF(OR($A28>TODAY(),$G28=""),"",IF(ROUND($G28,0)<0,"owes you",IF(ROUND($G28,0)>0,"you owe","settled")))
A29: =Weeks!$A$28 -> 46433 | B29: =IF($A29>TODAY(),"",IFERROR(INDEX(Weeks!$L$7:$W$59,MATCH($A29,Weeks!$A$7:$A$59,0),MATCH($D$5,Weeks!$L$5:$W$5,0)),0)) | C29: =IF($A29>TODAY(),"",IFERROR(INDEX(Weeks!$X$7:$AI$59,MATCH($A29,Weeks!$A$7:$A$59,0),MATCH($D$5,Weeks!$X$5:$AI$5,0)),0)) | D29: =IF($A29>TODAY(),"",SUMIFS('Cash Ledger'!$E$7:$E$1006,'Cash Ledger'!$I$7:$I$1006,$D$5,'Cash Ledger'!$D$7:$D$1006,"Advance",'Cash Ledger'!$B$7:$B$1006,">="&$A29,'Cash Ledger'!$B$7:$B$1006,"<="&($A29+6))) | E29: =IF($A29>TODAY(),"",SUMIFS('Cash Ledger'!$E$7:$E$1006,'Cash Ledger'!$I$7:$I$1006,$D$5,'Cash Ledger'!$D$7:$D$1006,"Correction",'Cash Ledger'!$B$7:$B$1006,">="&$A29,'Cash Ledger'!$B$7:$B$1006,"<="&($A29+6))) | F29: =IF($A29>TODAY(),"",SUMIFS('Cash Ledger'!$E$7:$E$1006,'Cash Ledger'!$I$7:$I$1006,$D$5,'Cash Ledger'!$D$7:$D$1006,"Weekly pay",'Cash Ledger'!$B$7:$B$1006,">="&$A29,'Cash Ledger'!$B$7:$B$1006,"<="&($A29+6))) | G29: =IF($A29>TODAY(),"",SUMPRODUCT((Weeks!$A$7:$A$59<=$A29)*(Weeks!$X$5:$AI$5=$D$5)*Weeks!$X$7:$AI$59)-SUMIFS('Cash Ledger'!$E$7:$E$1006,'Cash Ledger'!$I$7:$I$1006,$D$5,'Cash Ledger'!$B$7:$B$1006,"<="&($A29+6))) | H29: =IF(OR($A29>TODAY(),$G29=""),"",IF(ROUND($G29,0)<0,"owes you",IF(ROUND($G29,0)>0,"you owe","settled")))
A30: =Weeks!$A$29 -> 46440 | B30: =IF($A30>TODAY(),"",IFERROR(INDEX(Weeks!$L$7:$W$59,MATCH($A30,Weeks!$A$7:$A$59,0),MATCH($D$5,Weeks!$L$5:$W$5,0)),0)) | C30: =IF($A30>TODAY(),"",IFERROR(INDEX(Weeks!$X$7:$AI$59,MATCH($A30,Weeks!$A$7:$A$59,0),MATCH($D$5,Weeks!$X$5:$AI$5,0)),0)) | D30: =IF($A30>TODAY(),"",SUMIFS('Cash Ledger'!$E$7:$E$1006,'Cash Ledger'!$I$7:$I$1006,$D$5,'Cash Ledger'!$D$7:$D$1006,"Advance",'Cash Ledger'!$B$7:$B$1006,">="&$A30,'Cash Ledger'!$B$7:$B$1006,"<="&($A30+6))) | E30: =IF($A30>TODAY(),"",SUMIFS('Cash Ledger'!$E$7:$E$1006,'Cash Ledger'!$I$7:$I$1006,$D$5,'Cash Ledger'!$D$7:$D$1006,"Correction",'Cash Ledger'!$B$7:$B$1006,">="&$A30,'Cash Ledger'!$B$7:$B$1006,"<="&($A30+6))) | F30: =IF($A30>TODAY(),"",SUMIFS('Cash Ledger'!$E$7:$E$1006,'Cash Ledger'!$I$7:$I$1006,$D$5,'Cash Ledger'!$D$7:$D$1006,"Weekly pay",'Cash Ledger'!$B$7:$B$1006,">="&$A30,'Cash Ledger'!$B$7:$B$1006,"<="&($A30+6))) | G30: =IF($A30>TODAY(),"",SUMPRODUCT((Weeks!$A$7:$A$59<=$A30)*(Weeks!$X$5:$AI$5=$D$5)*Weeks!$X$7:$AI$59)-SUMIFS('Cash Ledger'!$E$7:$E$1006,'Cash Ledger'!$I$7:$I$1006,$D$5,'Cash Ledger'!$B$7:$B$1006,"<="&($A30+6))) | H30: =IF(OR($A30>TODAY(),$G30=""),"",IF(ROUND($G30,0)<0,"owes you",IF(ROUND($G30,0)>0,"you owe","settled")))
A31: =Weeks!$A$30 -> 46447 | B31: =IF($A31>TODAY(),"",IFERROR(INDEX(Weeks!$L$7:$W$59,MATCH($A31,Weeks!$A$7:$A$59,0),MATCH($D$5,Weeks!$L$5:$W$5,0)),0)) | C31: =IF($A31>TODAY(),"",IFERROR(INDEX(Weeks!$X$7:$AI$59,MATCH($A31,Weeks!$A$7:$A$59,0),MATCH($D$5,Weeks!$X$5:$AI$5,0)),0)) | D31: =IF($A31>TODAY(),"",SUMIFS('Cash Ledger'!$E$7:$E$1006,'Cash Ledger'!$I$7:$I$1006,$D$5,'Cash Ledger'!$D$7:$D$1006,"Advance",'Cash Ledger'!$B$7:$B$1006,">="&$A31,'Cash Ledger'!$B$7:$B$1006,"<="&($A31+6))) | E31: =IF($A31>TODAY(),"",SUMIFS('Cash Ledger'!$E$7:$E$1006,'Cash Ledger'!$I$7:$I$1006,$D$5,'Cash Ledger'!$D$7:$D$1006,"Correction",'Cash Ledger'!$B$7:$B$1006,">="&$A31,'Cash Ledger'!$B$7:$B$1006,"<="&($A31+6))) | F31: =IF($A31>TODAY(),"",SUMIFS('Cash Ledger'!$E$7:$E$1006,'Cash Ledger'!$I$7:$I$1006,$D$5,'Cash Ledger'!$D$7:$D$1006,"Weekly pay",'Cash Ledger'!$B$7:$B$1006,">="&$A31,'Cash Ledger'!$B$7:$B$1006,"<="&($A31+6))) | G31: =IF($A31>TODAY(),"",SUMPRODUCT((Weeks!$A$7:$A$59<=$A31)*(Weeks!$X$5:$AI$5=$D$5)*Weeks!$X$7:$AI$59)-SUMIFS('Cash Ledger'!$E$7:$E$1006,'Cash Ledger'!$I$7:$I$1006,$D$5,'Cash Ledger'!$B$7:$B$1006,"<="&($A31+6))) | H31: =IF(OR($A31>TODAY(),$G31=""),"",IF(ROUND($G31,0)<0,"owes you",IF(ROUND($G31,0)>0,"you owe","settled")))
A32: =Weeks!$A$31 -> 46454 | B32: =IF($A32>TODAY(),"",IFERROR(INDEX(Weeks!$L$7:$W$59,MATCH($A32,Weeks!$A$7:$A$59,0),MATCH($D$5,Weeks!$L$5:$W$5,0)),0)) | C32: =IF($A32>TODAY(),"",IFERROR(INDEX(Weeks!$X$7:$AI$59,MATCH($A32,Weeks!$A$7:$A$59,0),MATCH($D$5,Weeks!$X$5:$AI$5,0)),0)) | D32: =IF($A32>TODAY(),"",SUMIFS('Cash Ledger'!$E$7:$E$1006,'Cash Ledger'!$I$7:$I$1006,$D$5,'Cash Ledger'!$D$7:$D$1006,"Advance",'Cash Ledger'!$B$7:$B$1006,">="&$A32,'Cash Ledger'!$B$7:$B$1006,"<="&($A32+6))) | E32: =IF($A32>TODAY(),"",SUMIFS('Cash Ledger'!$E$7:$E$1006,'Cash Ledger'!$I$7:$I$1006,$D$5,'Cash Ledger'!$D$7:$D$1006,"Correction",'Cash Ledger'!$B$7:$B$1006,">="&$A32,'Cash Ledger'!$B$7:$B$1006,"<="&($A32+6))) | F32: =IF($A32>TODAY(),"",SUMIFS('Cash Ledger'!$E$7:$E$1006,'Cash Ledger'!$I$7:$I$1006,$D$5,'Cash Ledger'!$D$7:$D$1006,"Weekly pay",'Cash Ledger'!$B$7:$B$1006,">="&$A32,'Cash Ledger'!$B$7:$B$1006,"<="&($A32+6))) | G32: =IF($A32>TODAY(),"",SUMPRODUCT((Weeks!$A$7:$A$59<=$A32)*(Weeks!$X$5:$AI$5=$D$5)*Weeks!$X$7:$AI$59)-SUMIFS('Cash Ledger'!$E$7:$E$1006,'Cash Ledger'!$I$7:$I$1006,$D$5,'Cash Ledger'!$B$7:$B$1006,"<="&($A32+6))) | H32: =IF(OR($A32>TODAY(),$G32=""),"",IF(ROUND($G32,0)<0,"owes you",IF(ROUND($G32,0)>0,"you owe","settled")))
A33: =Weeks!$A$32 -> 46461 | B33: =IF($A33>TODAY(),"",IFERROR(INDEX(Weeks!$L$7:$W$59,MATCH($A33,Weeks!$A$7:$A$59,0),MATCH($D$5,Weeks!$L$5:$W$5,0)),0)) | C33: =IF($A33>TODAY(),"",IFERROR(INDEX(Weeks!$X$7:$AI$59,MATCH($A33,Weeks!$A$7:$A$59,0),MATCH($D$5,Weeks!$X$5:$AI$5,0)),0)) | D33: =IF($A33>TODAY(),"",SUMIFS('Cash Ledger'!$E$7:$E$1006,'Cash Ledger'!$I$7:$I$1006,$D$5,'Cash Ledger'!$D$7:$D$1006,"Advance",'Cash Ledger'!$B$7:$B$1006,">="&$A33,'Cash Ledger'!$B$7:$B$1006,"<="&($A33+6))) | E33: =IF($A33>TODAY(),"",SUMIFS('Cash Ledger'!$E$7:$E$1006,'Cash Ledger'!$I$7:$I$1006,$D$5,'Cash Ledger'!$D$7:$D$1006,"Correction",'Cash Ledger'!$B$7:$B$1006,">="&$A33,'Cash Ledger'!$B$7:$B$1006,"<="&($A33+6))) | F33: =IF($A33>TODAY(),"",SUMIFS('Cash Ledger'!$E$7:$E$1006,'Cash Ledger'!$I$7:$I$1006,$D$5,'Cash Ledger'!$D$7:$D$1006,"Weekly pay",'Cash Ledger'!$B$7:$B$1006,">="&$A33,'Cash Ledger'!$B$7:$B$1006,"<="&($A33+6))) | G33: =IF($A33>TODAY(),"",SUMPRODUCT((Weeks!$A$7:$A$59<=$A33)*(Weeks!$X$5:$AI$5=$D$5)*Weeks!$X$7:$AI$59)-SUMIFS('Cash Ledger'!$E$7:$E$1006,'Cash Ledger'!$I$7:$I$1006,$D$5,'Cash Ledger'!$B$7:$B$1006,"<="&($A33+6))) | H33: =IF(OR($A33>TODAY(),$G33=""),"",IF(ROUND($G33,0)<0,"owes you",IF(ROUND($G33,0)>0,"you owe","settled")))
A34: =Weeks!$A$33 -> 46468 | B34: =IF($A34>TODAY(),"",IFERROR(INDEX(Weeks!$L$7:$W$59,MATCH($A34,Weeks!$A$7:$A$59,0),MATCH($D$5,Weeks!$L$5:$W$5,0)),0)) | C34: =IF($A34>TODAY(),"",IFERROR(INDEX(Weeks!$X$7:$AI$59,MATCH($A34,Weeks!$A$7:$A$59,0),MATCH($D$5,Weeks!$X$5:$AI$5,0)),0)) | D34: =IF($A34>TODAY(),"",SUMIFS('Cash Ledger'!$E$7:$E$1006,'Cash Ledger'!$I$7:$I$1006,$D$5,'Cash Ledger'!$D$7:$D$1006,"Advance",'Cash Ledger'!$B$7:$B$1006,">="&$A34,'Cash Ledger'!$B$7:$B$1006,"<="&($A34+6))) | E34: =IF($A34>TODAY(),"",SUMIFS('Cash Ledger'!$E$7:$E$1006,'Cash Ledger'!$I$7:$I$1006,$D$5,'Cash Ledger'!$D$7:$D$1006,"Correction",'Cash Ledger'!$B$7:$B$1006,">="&$A34,'Cash Ledger'!$B$7:$B$1006,"<="&($A34+6))) | F34: =IF($A34>TODAY(),"",SUMIFS('Cash Ledger'!$E$7:$E$1006,'Cash Ledger'!$I$7:$I$1006,$D$5,'Cash Ledger'!$D$7:$D$1006,"Weekly pay",'Cash Ledger'!$B$7:$B$1006,">="&$A34,'Cash Ledger'!$B$7:$B$1006,"<="&($A34+6))) | G34: =IF($A34>TODAY(),"",SUMPRODUCT((Weeks!$A$7:$A$59<=$A34)*(Weeks!$X$5:$AI$5=$D$5)*Weeks!$X$7:$AI$59)-SUMIFS('Cash Ledger'!$E$7:$E$1006,'Cash Ledger'!$I$7:$I$1006,$D$5,'Cash Ledger'!$B$7:$B$1006,"<="&($A34+6))) | H34: =IF(OR($A34>TODAY(),$G34=""),"",IF(ROUND($G34,0)<0,"owes you",IF(ROUND($G34,0)>0,"you owe","settled")))
A35: =Weeks!$A$34 -> 46475 | B35: =IF($A35>TODAY(),"",IFERROR(INDEX(Weeks!$L$7:$W$59,MATCH($A35,Weeks!$A$7:$A$59,0),MATCH($D$5,Weeks!$L$5:$W$5,0)),0)) | C35: =IF($A35>TODAY(),"",IFERROR(INDEX(Weeks!$X$7:$AI$59,MATCH($A35,Weeks!$A$7:$A$59,0),MATCH($D$5,Weeks!$X$5:$AI$5,0)),0)) | D35: =IF($A35>TODAY(),"",SUMIFS('Cash Ledger'!$E$7:$E$1006,'Cash Ledger'!$I$7:$I$1006,$D$5,'Cash Ledger'!$D$7:$D$1006,"Advance",'Cash Ledger'!$B$7:$B$1006,">="&$A35,'Cash Ledger'!$B$7:$B$1006,"<="&($A35+6))) | E35: =IF($A35>TODAY(),"",SUMIFS('Cash Ledger'!$E$7:$E$1006,'Cash Ledger'!$I$7:$I$1006,$D$5,'Cash Ledger'!$D$7:$D$1006,"Correction",'Cash Ledger'!$B$7:$B$1006,">="&$A35,'Cash Ledger'!$B$7:$B$1006,"<="&($A35+6))) | F35: =IF($A35>TODAY(),"",SUMIFS('Cash Ledger'!$E$7:$E$1006,'Cash Ledger'!$I$7:$I$1006,$D$5,'Cash Ledger'!$D$7:$D$1006,"Weekly pay",'Cash Ledger'!$B$7:$B$1006,">="&$A35,'Cash Ledger'!$B$7:$B$1006,"<="&($A35+6))) | G35: =IF($A35>TODAY(),"",SUMPRODUCT((Weeks!$A$7:$A$59<=$A35)*(Weeks!$X$5:$AI$5=$D$5)*Weeks!$X$7:$AI$59)-SUMIFS('Cash Ledger'!$E$7:$E$1006,'Cash Ledger'!$I$7:$I$1006,$D$5,'Cash Ledger'!$B$7:$B$1006,"<="&($A35+6))) | H35: =IF(OR($A35>TODAY(),$G35=""),"",IF(ROUND($G35,0)<0,"owes you",IF(ROUND($G35,0)>0,"you owe","settled")))
A36: =Weeks!$A$35 -> 46482 | B36: =IF($A36>TODAY(),"",IFERROR(INDEX(Weeks!$L$7:$W$59,MATCH($A36,Weeks!$A$7:$A$59,0),MATCH($D$5,Weeks!$L$5:$W$5,0)),0)) | C36: =IF($A36>TODAY(),"",IFERROR(INDEX(Weeks!$X$7:$AI$59,MATCH($A36,Weeks!$A$7:$A$59,0),MATCH($D$5,Weeks!$X$5:$AI$5,0)),0)) | D36: =IF($A36>TODAY(),"",SUMIFS('Cash Ledger'!$E$7:$E$1006,'Cash Ledger'!$I$7:$I$1006,$D$5,'Cash Ledger'!$D$7:$D$1006,"Advance",'Cash Ledger'!$B$7:$B$1006,">="&$A36,'Cash Ledger'!$B$7:$B$1006,"<="&($A36+6))) | E36: =IF($A36>TODAY(),"",SUMIFS('Cash Ledger'!$E$7:$E$1006,'Cash Ledger'!$I$7:$I$1006,$D$5,'Cash Ledger'!$D$7:$D$1006,"Correction",'Cash Ledger'!$B$7:$B$1006,">="&$A36,'Cash Ledger'!$B$7:$B$1006,"<="&($A36+6))) | F36: =IF($A36>TODAY(),"",SUMIFS('Cash Ledger'!$E$7:$E$1006,'Cash Ledger'!$I$7:$I$1006,$D$5,'Cash Ledger'!$D$7:$D$1006,"Weekly pay",'Cash Ledger'!$B$7:$B$1006,">="&$A36,'Cash Ledger'!$B$7:$B$1006,"<="&($A36+6))) | G36: =IF($A36>TODAY(),"",SUMPRODUCT((Weeks!$A$7:$A$59<=$A36)*(Weeks!$X$5:$AI$5=$D$5)*Weeks!$X$7:$AI$59)-SUMIFS('Cash Ledger'!$E$7:$E$1006,'Cash Ledger'!$I$7:$I$1006,$D$5,'Cash Ledger'!$B$7:$B$1006,"<="&($A36+6))) | H36: =IF(OR($A36>TODAY(),$G36=""),"",IF(ROUND($G36,0)<0,"owes you",IF(ROUND($G36,0)>0,"you owe","settled")))
A37: =Weeks!$A$36 -> 46489 | B37: =IF($A37>TODAY(),"",IFERROR(INDEX(Weeks!$L$7:$W$59,MATCH($A37,Weeks!$A$7:$A$59,0),MATCH($D$5,Weeks!$L$5:$W$5,0)),0)) | C37: =IF($A37>TODAY(),"",IFERROR(INDEX(Weeks!$X$7:$AI$59,MATCH($A37,Weeks!$A$7:$A$59,0),MATCH($D$5,Weeks!$X$5:$AI$5,0)),0)) | D37: =IF($A37>TODAY(),"",SUMIFS('Cash Ledger'!$E$7:$E$1006,'Cash Ledger'!$I$7:$I$1006,$D$5,'Cash Ledger'!$D$7:$D$1006,"Advance",'Cash Ledger'!$B$7:$B$1006,">="&$A37,'Cash Ledger'!$B$7:$B$1006,"<="&($A37+6))) | E37: =IF($A37>TODAY(),"",SUMIFS('Cash Ledger'!$E$7:$E$1006,'Cash Ledger'!$I$7:$I$1006,$D$5,'Cash Ledger'!$D$7:$D$1006,"Correction",'Cash Ledger'!$B$7:$B$1006,">="&$A37,'Cash Ledger'!$B$7:$B$1006,"<="&($A37+6))) | F37: =IF($A37>TODAY(),"",SUMIFS('Cash Ledger'!$E$7:$E$1006,'Cash Ledger'!$I$7:$I$1006,$D$5,'Cash Ledger'!$D$7:$D$1006,"Weekly pay",'Cash Ledger'!$B$7:$B$1006,">="&$A37,'Cash Ledger'!$B$7:$B$1006,"<="&($A37+6))) | G37: =IF($A37>TODAY(),"",SUMPRODUCT((Weeks!$A$7:$A$59<=$A37)*(Weeks!$X$5:$AI$5=$D$5)*Weeks!$X$7:$AI$59)-SUMIFS('Cash Ledger'!$E$7:$E$1006,'Cash Ledger'!$I$7:$I$1006,$D$5,'Cash Ledger'!$B$7:$B$1006,"<="&($A37+6))) | H37: =IF(OR($A37>TODAY(),$G37=""),"",IF(ROUND($G37,0)<0,"owes you",IF(ROUND($G37,0)>0,"you owe","settled")))
A38: =Weeks!$A$37 -> 46496 | B38: =IF($A38>TODAY(),"",IFERROR(INDEX(Weeks!$L$7:$W$59,MATCH($A38,Weeks!$A$7:$A$59,0),MATCH($D$5,Weeks!$L$5:$W$5,0)),0)) | C38: =IF($A38>TODAY(),"",IFERROR(INDEX(Weeks!$X$7:$AI$59,MATCH($A38,Weeks!$A$7:$A$59,0),MATCH($D$5,Weeks!$X$5:$AI$5,0)),0)) | D38: =IF($A38>TODAY(),"",SUMIFS('Cash Ledger'!$E$7:$E$1006,'Cash Ledger'!$I$7:$I$1006,$D$5,'Cash Ledger'!$D$7:$D$1006,"Advance",'Cash Ledger'!$B$7:$B$1006,">="&$A38,'Cash Ledger'!$B$7:$B$1006,"<="&($A38+6))) | E38: =IF($A38>TODAY(),"",SUMIFS('Cash Ledger'!$E$7:$E$1006,'Cash Ledger'!$I$7:$I$1006,$D$5,'Cash Ledger'!$D$7:$D$1006,"Correction",'Cash Ledger'!$B$7:$B$1006,">="&$A38,'Cash Ledger'!$B$7:$B$1006,"<="&($A38+6))) | F38: =IF($A38>TODAY(),"",SUMIFS('Cash Ledger'!$E$7:$E$1006,'Cash Ledger'!$I$7:$I$1006,$D$5,'Cash Ledger'!$D$7:$D$1006,"Weekly pay",'Cash Ledger'!$B$7:$B$1006,">="&$A38,'Cash Ledger'!$B$7:$B$1006,"<="&($A38+6))) | G38: =IF($A38>TODAY(),"",SUMPRODUCT((Weeks!$A$7:$A$59<=$A38)*(Weeks!$X$5:$AI$5=$D$5)*Weeks!$X$7:$AI$59)-SUMIFS('Cash Ledger'!$E$7:$E$1006,'Cash Ledger'!$I$7:$I$1006,$D$5,'Cash Ledger'!$B$7:$B$1006,"<="&($A38+6))) | H38: =IF(OR($A38>TODAY(),$G38=""),"",IF(ROUND($G38,0)<0,"owes you",IF(ROUND($G38,0)>0,"you owe","settled")))
A39: =Weeks!$A$38 -> 46503 | B39: =IF($A39>TODAY(),"",IFERROR(INDEX(Weeks!$L$7:$W$59,MATCH($A39,Weeks!$A$7:$A$59,0),MATCH($D$5,Weeks!$L$5:$W$5,0)),0)) | C39: =IF($A39>TODAY(),"",IFERROR(INDEX(Weeks!$X$7:$AI$59,MATCH($A39,Weeks!$A$7:$A$59,0),MATCH($D$5,Weeks!$X$5:$AI$5,0)),0)) | D39: =IF($A39>TODAY(),"",SUMIFS('Cash Ledger'!$E$7:$E$1006,'Cash Ledger'!$I$7:$I$1006,$D$5,'Cash Ledger'!$D$7:$D$1006,"Advance",'Cash Ledger'!$B$7:$B$1006,">="&$A39,'Cash Ledger'!$B$7:$B$1006,"<="&($A39+6))) | E39: =IF($A39>TODAY(),"",SUMIFS('Cash Ledger'!$E$7:$E$1006,'Cash Ledger'!$I$7:$I$1006,$D$5,'Cash Ledger'!$D$7:$D$1006,"Correction",'Cash Ledger'!$B$7:$B$1006,">="&$A39,'Cash Ledger'!$B$7:$B$1006,"<="&($A39+6))) | F39: =IF($A39>TODAY(),"",SUMIFS('Cash Ledger'!$E$7:$E$1006,'Cash Ledger'!$I$7:$I$1006,$D$5,'Cash Ledger'!$D$7:$D$1006,"Weekly pay",'Cash Ledger'!$B$7:$B$1006,">="&$A39,'Cash Ledger'!$B$7:$B$1006,"<="&($A39+6))) | G39: =IF($A39>TODAY(),"",SUMPRODUCT((Weeks!$A$7:$A$59<=$A39)*(Weeks!$X$5:$AI$5=$D$5)*Weeks!$X$7:$AI$59)-SUMIFS('Cash Ledger'!$E$7:$E$1006,'Cash Ledger'!$I$7:$I$1006,$D$5,'Cash Ledger'!$B$7:$B$1006,"<="&($A39+6))) | H39: =IF(OR($A39>TODAY(),$G39=""),"",IF(ROUND($G39,0)<0,"owes you",IF(ROUND($G39,0)>0,"you owe","settled")))
A40: =Weeks!$A$39 -> 46510 | B40: =IF($A40>TODAY(),"",IFERROR(INDEX(Weeks!$L$7:$W$59,MATCH($A40,Weeks!$A$7:$A$59,0),MATCH($D$5,Weeks!$L$5:$W$5,0)),0)) | C40: =IF($A40>TODAY(),"",IFERROR(INDEX(Weeks!$X$7:$AI$59,MATCH($A40,Weeks!$A$7:$A$59,0),MATCH($D$5,Weeks!$X$5:$AI$5,0)),0)) | D40: =IF($A40>TODAY(),"",SUMIFS('Cash Ledger'!$E$7:$E$1006,'Cash Ledger'!$I$7:$I$1006,$D$5,'Cash Ledger'!$D$7:$D$1006,"Advance",'Cash Ledger'!$B$7:$B$1006,">="&$A40,'Cash Ledger'!$B$7:$B$1006,"<="&($A40+6))) | E40: =IF($A40>TODAY(),"",SUMIFS('Cash Ledger'!$E$7:$E$1006,'Cash Ledger'!$I$7:$I$1006,$D$5,'Cash Ledger'!$D$7:$D$1006,"Correction",'Cash Ledger'!$B$7:$B$1006,">="&$A40,'Cash Ledger'!$B$7:$B$1006,"<="&($A40+6))) | F40: =IF($A40>TODAY(),"",SUMIFS('Cash Ledger'!$E$7:$E$1006,'Cash Ledger'!$I$7:$I$1006,$D$5,'Cash Ledger'!$D$7:$D$1006,"Weekly pay",'Cash Ledger'!$B$7:$B$1006,">="&$A40,'Cash Ledger'!$B$7:$B$1006,"<="&($A40+6))) | G40: =IF($A40>TODAY(),"",SUMPRODUCT((Weeks!$A$7:$A$59<=$A40)*(Weeks!$X$5:$AI$5=$D$5)*Weeks!$X$7:$AI$59)-SUMIFS('Cash Ledger'!$E$7:$E$1006,'Cash Ledger'!$I$7:$I$1006,$D$5,'Cash Ledger'!$B$7:$B$1006,"<="&($A40+6))) | H40: =IF(OR($A40>TODAY(),$G40=""),"",IF(ROUND($G40,0)<0,"owes you",IF(ROUND($G40,0)>0,"you owe","settled")))
A41: =Weeks!$A$40 -> 46517 | B41: =IF($A41>TODAY(),"",IFERROR(INDEX(Weeks!$L$7:$W$59,MATCH($A41,Weeks!$A$7:$A$59,0),MATCH($D$5,Weeks!$L$5:$W$5,0)),0)) | C41: =IF($A41>TODAY(),"",IFERROR(INDEX(Weeks!$X$7:$AI$59,MATCH($A41,Weeks!$A$7:$A$59,0),MATCH($D$5,Weeks!$X$5:$AI$5,0)),0)) | D41: =IF($A41>TODAY(),"",SUMIFS('Cash Ledger'!$E$7:$E$1006,'Cash Ledger'!$I$7:$I$1006,$D$5,'Cash Ledger'!$D$7:$D$1006,"Advance",'Cash Ledger'!$B$7:$B$1006,">="&$A41,'Cash Ledger'!$B$7:$B$1006,"<="&($A41+6))) | E41: =IF($A41>TODAY(),"",SUMIFS('Cash Ledger'!$E$7:$E$1006,'Cash Ledger'!$I$7:$I$1006,$D$5,'Cash Ledger'!$D$7:$D$1006,"Correction",'Cash Ledger'!$B$7:$B$1006,">="&$A41,'Cash Ledger'!$B$7:$B$1006,"<="&($A41+6))) | F41: =IF($A41>TODAY(),"",SUMIFS('Cash Ledger'!$E$7:$E$1006,'Cash Ledger'!$I$7:$I$1006,$D$5,'Cash Ledger'!$D$7:$D$1006,"Weekly pay",'Cash Ledger'!$B$7:$B$1006,">="&$A41,'Cash Ledger'!$B$7:$B$1006,"<="&($A41+6))) | G41: =IF($A41>TODAY(),"",SUMPRODUCT((Weeks!$A$7:$A$59<=$A41)*(Weeks!$X$5:$AI$5=$D$5)*Weeks!$X$7:$AI$59)-SUMIFS('Cash Ledger'!$E$7:$E$1006,'Cash Ledger'!$I$7:$I$1006,$D$5,'Cash Ledger'!$B$7:$B$1006,"<="&($A41+6))) | H41: =IF(OR($A41>TODAY(),$G41=""),"",IF(ROUND($G41,0)<0,"owes you",IF(ROUND($G41,0)>0,"you owe","settled")))
A42: =Weeks!$A$41 -> 46524 | B42: =IF($A42>TODAY(),"",IFERROR(INDEX(Weeks!$L$7:$W$59,MATCH($A42,Weeks!$A$7:$A$59,0),MATCH($D$5,Weeks!$L$5:$W$5,0)),0)) | C42: =IF($A42>TODAY(),"",IFERROR(INDEX(Weeks!$X$7:$AI$59,MATCH($A42,Weeks!$A$7:$A$59,0),MATCH($D$5,Weeks!$X$5:$AI$5,0)),0)) | D42: =IF($A42>TODAY(),"",SUMIFS('Cash Ledger'!$E$7:$E$1006,'Cash Ledger'!$I$7:$I$1006,$D$5,'Cash Ledger'!$D$7:$D$1006,"Advance",'Cash Ledger'!$B$7:$B$1006,">="&$A42,'Cash Ledger'!$B$7:$B$1006,"<="&($A42+6))) | E42: =IF($A42>TODAY(),"",SUMIFS('Cash Ledger'!$E$7:$E$1006,'Cash Ledger'!$I$7:$I$1006,$D$5,'Cash Ledger'!$D$7:$D$1006,"Correction",'Cash Ledger'!$B$7:$B$1006,">="&$A42,'Cash Ledger'!$B$7:$B$1006,"<="&($A42+6))) | F42: =IF($A42>TODAY(),"",SUMIFS('Cash Ledger'!$E$7:$E$1006,'Cash Ledger'!$I$7:$I$1006,$D$5,'Cash Ledger'!$D$7:$D$1006,"Weekly pay",'Cash Ledger'!$B$7:$B$1006,">="&$A42,'Cash Ledger'!$B$7:$B$1006,"<="&($A42+6))) | G42: =IF($A42>TODAY(),"",SUMPRODUCT((Weeks!$A$7:$A$59<=$A42)*(Weeks!$X$5:$AI$5=$D$5)*Weeks!$X$7:$AI$59)-SUMIFS('Cash Ledger'!$E$7:$E$1006,'Cash Ledger'!$I$7:$I$1006,$D$5,'Cash Ledger'!$B$7:$B$1006,"<="&($A42+6))) | H42: =IF(OR($A42>TODAY(),$G42=""),"",IF(ROUND($G42,0)<0,"owes you",IF(ROUND($G42,0)>0,"you owe","settled")))
A43: =Weeks!$A$42 -> 46531 | B43: =IF($A43>TODAY(),"",IFERROR(INDEX(Weeks!$L$7:$W$59,MATCH($A43,Weeks!$A$7:$A$59,0),MATCH($D$5,Weeks!$L$5:$W$5,0)),0)) | C43: =IF($A43>TODAY(),"",IFERROR(INDEX(Weeks!$X$7:$AI$59,MATCH($A43,Weeks!$A$7:$A$59,0),MATCH($D$5,Weeks!$X$5:$AI$5,0)),0)) | D43: =IF($A43>TODAY(),"",SUMIFS('Cash Ledger'!$E$7:$E$1006,'Cash Ledger'!$I$7:$I$1006,$D$5,'Cash Ledger'!$D$7:$D$1006,"Advance",'Cash Ledger'!$B$7:$B$1006,">="&$A43,'Cash Ledger'!$B$7:$B$1006,"<="&($A43+6))) | E43: =IF($A43>TODAY(),"",SUMIFS('Cash Ledger'!$E$7:$E$1006,'Cash Ledger'!$I$7:$I$1006,$D$5,'Cash Ledger'!$D$7:$D$1006,"Correction",'Cash Ledger'!$B$7:$B$1006,">="&$A43,'Cash Ledger'!$B$7:$B$1006,"<="&($A43+6))) | F43: =IF($A43>TODAY(),"",SUMIFS('Cash Ledger'!$E$7:$E$1006,'Cash Ledger'!$I$7:$I$1006,$D$5,'Cash Ledger'!$D$7:$D$1006,"Weekly pay",'Cash Ledger'!$B$7:$B$1006,">="&$A43,'Cash Ledger'!$B$7:$B$1006,"<="&($A43+6))) | G43: =IF($A43>TODAY(),"",SUMPRODUCT((Weeks!$A$7:$A$59<=$A43)*(Weeks!$X$5:$AI$5=$D$5)*Weeks!$X$7:$AI$59)-SUMIFS('Cash Ledger'!$E$7:$E$1006,'Cash Ledger'!$I$7:$I$1006,$D$5,'Cash Ledger'!$B$7:$B$1006,"<="&($A43+6))) | H43: =IF(OR($A43>TODAY(),$G43=""),"",IF(ROUND($G43,0)<0,"owes you",IF(ROUND($G43,0)>0,"you owe","settled")))
A44: =Weeks!$A$43 -> 46538 | B44: =IF($A44>TODAY(),"",IFERROR(INDEX(Weeks!$L$7:$W$59,MATCH($A44,Weeks!$A$7:$A$59,0),MATCH($D$5,Weeks!$L$5:$W$5,0)),0)) | C44: =IF($A44>TODAY(),"",IFERROR(INDEX(Weeks!$X$7:$AI$59,MATCH($A44,Weeks!$A$7:$A$59,0),MATCH($D$5,Weeks!$X$5:$AI$5,0)),0)) | D44: =IF($A44>TODAY(),"",SUMIFS('Cash Ledger'!$E$7:$E$1006,'Cash Ledger'!$I$7:$I$1006,$D$5,'Cash Ledger'!$D$7:$D$1006,"Advance",'Cash Ledger'!$B$7:$B$1006,">="&$A44,'Cash Ledger'!$B$7:$B$1006,"<="&($A44+6))) | E44: =IF($A44>TODAY(),"",SUMIFS('Cash Ledger'!$E$7:$E$1006,'Cash Ledger'!$I$7:$I$1006,$D$5,'Cash Ledger'!$D$7:$D$1006,"Correction",'Cash Ledger'!$B$7:$B$1006,">="&$A44,'Cash Ledger'!$B$7:$B$1006,"<="&($A44+6))) | F44: =IF($A44>TODAY(),"",SUMIFS('Cash Ledger'!$E$7:$E$1006,'Cash Ledger'!$I$7:$I$1006,$D$5,'Cash Ledger'!$D$7:$D$1006,"Weekly pay",'Cash Ledger'!$B$7:$B$1006,">="&$A44,'Cash Ledger'!$B$7:$B$1006,"<="&($A44+6))) | G44: =IF($A44>TODAY(),"",SUMPRODUCT((Weeks!$A$7:$A$59<=$A44)*(Weeks!$X$5:$AI$5=$D$5)*Weeks!$X$7:$AI$59)-SUMIFS('Cash Ledger'!$E$7:$E$1006,'Cash Ledger'!$I$7:$I$1006,$D$5,'Cash Ledger'!$B$7:$B$1006,"<="&($A44+6))) | H44: =IF(OR($A44>TODAY(),$G44=""),"",IF(ROUND($G44,0)<0,"owes you",IF(ROUND($G44,0)>0,"you owe","settled")))
A45: =Weeks!$A$44 -> 46545 | B45: =IF($A45>TODAY(),"",IFERROR(INDEX(Weeks!$L$7:$W$59,MATCH($A45,Weeks!$A$7:$A$59,0),MATCH($D$5,Weeks!$L$5:$W$5,0)),0)) | C45: =IF($A45>TODAY(),"",IFERROR(INDEX(Weeks!$X$7:$AI$59,MATCH($A45,Weeks!$A$7:$A$59,0),MATCH($D$5,Weeks!$X$5:$AI$5,0)),0)) | D45: =IF($A45>TODAY(),"",SUMIFS('Cash Ledger'!$E$7:$E$1006,'Cash Ledger'!$I$7:$I$1006,$D$5,'Cash Ledger'!$D$7:$D$1006,"Advance",'Cash Ledger'!$B$7:$B$1006,">="&$A45,'Cash Ledger'!$B$7:$B$1006,"<="&($A45+6))) | E45: =IF($A45>TODAY(),"",SUMIFS('Cash Ledger'!$E$7:$E$1006,'Cash Ledger'!$I$7:$I$1006,$D$5,'Cash Ledger'!$D$7:$D$1006,"Correction",'Cash Ledger'!$B$7:$B$1006,">="&$A45,'Cash Ledger'!$B$7:$B$1006,"<="&($A45+6))) | F45: =IF($A45>TODAY(),"",SUMIFS('Cash Ledger'!$E$7:$E$1006,'Cash Ledger'!$I$7:$I$1006,$D$5,'Cash Ledger'!$D$7:$D$1006,"Weekly pay",'Cash Ledger'!$B$7:$B$1006,">="&$A45,'Cash Ledger'!$B$7:$B$1006,"<="&($A45+6))) | G45: =IF($A45>TODAY(),"",SUMPRODUCT((Weeks!$A$7:$A$59<=$A45)*(Weeks!$X$5:$AI$5=$D$5)*Weeks!$X$7:$AI$59)-SUMIFS('Cash Ledger'!$E$7:$E$1006,'Cash Ledger'!$I$7:$I$1006,$D$5,'Cash Ledger'!$B$7:$B$1006,"<="&($A45+6))) | H45: =IF(OR($A45>TODAY(),$G45=""),"",IF(ROUND($G45,0)<0,"owes you",IF(ROUND($G45,0)>0,"you owe","settled")))
A46: =Weeks!$A$45 -> 46552 | B46: =IF($A46>TODAY(),"",IFERROR(INDEX(Weeks!$L$7:$W$59,MATCH($A46,Weeks!$A$7:$A$59,0),MATCH($D$5,Weeks!$L$5:$W$5,0)),0)) | C46: =IF($A46>TODAY(),"",IFERROR(INDEX(Weeks!$X$7:$AI$59,MATCH($A46,Weeks!$A$7:$A$59,0),MATCH($D$5,Weeks!$X$5:$AI$5,0)),0)) | D46: =IF($A46>TODAY(),"",SUMIFS('Cash Ledger'!$E$7:$E$1006,'Cash Ledger'!$I$7:$I$1006,$D$5,'Cash Ledger'!$D$7:$D$1006,"Advance",'Cash Ledger'!$B$7:$B$1006,">="&$A46,'Cash Ledger'!$B$7:$B$1006,"<="&($A46+6))) | E46: =IF($A46>TODAY(),"",SUMIFS('Cash Ledger'!$E$7:$E$1006,'Cash Ledger'!$I$7:$I$1006,$D$5,'Cash Ledger'!$D$7:$D$1006,"Correction",'Cash Ledger'!$B$7:$B$1006,">="&$A46,'Cash Ledger'!$B$7:$B$1006,"<="&($A46+6))) | F46: =IF($A46>TODAY(),"",SUMIFS('Cash Ledger'!$E$7:$E$1006,'Cash Ledger'!$I$7:$I$1006,$D$5,'Cash Ledger'!$D$7:$D$1006,"Weekly pay",'Cash Ledger'!$B$7:$B$1006,">="&$A46,'Cash Ledger'!$B$7:$B$1006,"<="&($A46+6))) | G46: =IF($A46>TODAY(),"",SUMPRODUCT((Weeks!$A$7:$A$59<=$A46)*(Weeks!$X$5:$AI$5=$D$5)*Weeks!$X$7:$AI$59)-SUMIFS('Cash Ledger'!$E$7:$E$1006,'Cash Ledger'!$I$7:$I$1006,$D$5,'Cash Ledger'!$B$7:$B$1006,"<="&($A46+6))) | H46: =IF(OR($A46>TODAY(),$G46=""),"",IF(ROUND($G46,0)<0,"owes you",IF(ROUND($G46,0)>0,"you owe","settled")))
A47: =Weeks!$A$46 -> 46559 | B47: =IF($A47>TODAY(),"",IFERROR(INDEX(Weeks!$L$7:$W$59,MATCH($A47,Weeks!$A$7:$A$59,0),MATCH($D$5,Weeks!$L$5:$W$5,0)),0)) | C47: =IF($A47>TODAY(),"",IFERROR(INDEX(Weeks!$X$7:$AI$59,MATCH($A47,Weeks!$A$7:$A$59,0),MATCH($D$5,Weeks!$X$5:$AI$5,0)),0)) | D47: =IF($A47>TODAY(),"",SUMIFS('Cash Ledger'!$E$7:$E$1006,'Cash Ledger'!$I$7:$I$1006,$D$5,'Cash Ledger'!$D$7:$D$1006,"Advance",'Cash Ledger'!$B$7:$B$1006,">="&$A47,'Cash Ledger'!$B$7:$B$1006,"<="&($A47+6))) | E47: =IF($A47>TODAY(),"",SUMIFS('Cash Ledger'!$E$7:$E$1006,'Cash Ledger'!$I$7:$I$1006,$D$5,'Cash Ledger'!$D$7:$D$1006,"Correction",'Cash Ledger'!$B$7:$B$1006,">="&$A47,'Cash Ledger'!$B$7:$B$1006,"<="&($A47+6))) | F47: =IF($A47>TODAY(),"",SUMIFS('Cash Ledger'!$E$7:$E$1006,'Cash Ledger'!$I$7:$I$1006,$D$5,'Cash Ledger'!$D$7:$D$1006,"Weekly pay",'Cash Ledger'!$B$7:$B$1006,">="&$A47,'Cash Ledger'!$B$7:$B$1006,"<="&($A47+6))) | G47: =IF($A47>TODAY(),"",SUMPRODUCT((Weeks!$A$7:$A$59<=$A47)*(Weeks!$X$5:$AI$5=$D$5)*Weeks!$X$7:$AI$59)-SUMIFS('Cash Ledger'!$E$7:$E$1006,'Cash Ledger'!$I$7:$I$1006,$D$5,'Cash Ledger'!$B$7:$B$1006,"<="&($A47+6))) | H47: =IF(OR($A47>TODAY(),$G47=""),"",IF(ROUND($G47,0)<0,"owes you",IF(ROUND($G47,0)>0,"you owe","settled")))
A48: =Weeks!$A$47 -> 46566 | B48: =IF($A48>TODAY(),"",IFERROR(INDEX(Weeks!$L$7:$W$59,MATCH($A48,Weeks!$A$7:$A$59,0),MATCH($D$5,Weeks!$L$5:$W$5,0)),0)) | C48: =IF($A48>TODAY(),"",IFERROR(INDEX(Weeks!$X$7:$AI$59,MATCH($A48,Weeks!$A$7:$A$59,0),MATCH($D$5,Weeks!$X$5:$AI$5,0)),0)) | D48: =IF($A48>TODAY(),"",SUMIFS('Cash Ledger'!$E$7:$E$1006,'Cash Ledger'!$I$7:$I$1006,$D$5,'Cash Ledger'!$D$7:$D$1006,"Advance",'Cash Ledger'!$B$7:$B$1006,">="&$A48,'Cash Ledger'!$B$7:$B$1006,"<="&($A48+6))) | E48: =IF($A48>TODAY(),"",SUMIFS('Cash Ledger'!$E$7:$E$1006,'Cash Ledger'!$I$7:$I$1006,$D$5,'Cash Ledger'!$D$7:$D$1006,"Correction",'Cash Ledger'!$B$7:$B$1006,">="&$A48,'Cash Ledger'!$B$7:$B$1006,"<="&($A48+6))) | F48: =IF($A48>TODAY(),"",SUMIFS('Cash Ledger'!$E$7:$E$1006,'Cash Ledger'!$I$7:$I$1006,$D$5,'Cash Ledger'!$D$7:$D$1006,"Weekly pay",'Cash Ledger'!$B$7:$B$1006,">="&$A48,'Cash Ledger'!$B$7:$B$1006,"<="&($A48+6))) | G48: =IF($A48>TODAY(),"",SUMPRODUCT((Weeks!$A$7:$A$59<=$A48)*(Weeks!$X$5:$AI$5=$D$5)*Weeks!$X$7:$AI$59)-SUMIFS('Cash Ledger'!$E$7:$E$1006,'Cash Ledger'!$I$7:$I$1006,$D$5,'Cash Ledger'!$B$7:$B$1006,"<="&($A48+6))) | H48: =IF(OR($A48>TODAY(),$G48=""),"",IF(ROUND($G48,0)<0,"owes you",IF(ROUND($G48,0)>0,"you owe","settled")))
A49: =Weeks!$A$48 -> 46573 | B49: =IF($A49>TODAY(),"",IFERROR(INDEX(Weeks!$L$7:$W$59,MATCH($A49,Weeks!$A$7:$A$59,0),MATCH($D$5,Weeks!$L$5:$W$5,0)),0)) | C49: =IF($A49>TODAY(),"",IFERROR(INDEX(Weeks!$X$7:$AI$59,MATCH($A49,Weeks!$A$7:$A$59,0),MATCH($D$5,Weeks!$X$5:$AI$5,0)),0)) | D49: =IF($A49>TODAY(),"",SUMIFS('Cash Ledger'!$E$7:$E$1006,'Cash Ledger'!$I$7:$I$1006,$D$5,'Cash Ledger'!$D$7:$D$1006,"Advance",'Cash Ledger'!$B$7:$B$1006,">="&$A49,'Cash Ledger'!$B$7:$B$1006,"<="&($A49+6))) | E49: =IF($A49>TODAY(),"",SUMIFS('Cash Ledger'!$E$7:$E$1006,'Cash Ledger'!$I$7:$I$1006,$D$5,'Cash Ledger'!$D$7:$D$1006,"Correction",'Cash Ledger'!$B$7:$B$1006,">="&$A49,'Cash Ledger'!$B$7:$B$1006,"<="&($A49+6))) | F49: =IF($A49>TODAY(),"",SUMIFS('Cash Ledger'!$E$7:$E$1006,'Cash Ledger'!$I$7:$I$1006,$D$5,'Cash Ledger'!$D$7:$D$1006,"Weekly pay",'Cash Ledger'!$B$7:$B$1006,">="&$A49,'Cash Ledger'!$B$7:$B$1006,"<="&($A49+6))) | G49: =IF($A49>TODAY(),"",SUMPRODUCT((Weeks!$A$7:$A$59<=$A49)*(Weeks!$X$5:$AI$5=$D$5)*Weeks!$X$7:$AI$59)-SUMIFS('Cash Ledger'!$E$7:$E$1006,'Cash Ledger'!$I$7:$I$1006,$D$5,'Cash Ledger'!$B$7:$B$1006,"<="&($A49+6))) | H49: =IF(OR($A49>TODAY(),$G49=""),"",IF(ROUND($G49,0)<0,"owes you",IF(ROUND($G49,0)>0,"you owe","settled")))
A50: =Weeks!$A$49 -> 46580 | B50: =IF($A50>TODAY(),"",IFERROR(INDEX(Weeks!$L$7:$W$59,MATCH($A50,Weeks!$A$7:$A$59,0),MATCH($D$5,Weeks!$L$5:$W$5,0)),0)) | C50: =IF($A50>TODAY(),"",IFERROR(INDEX(Weeks!$X$7:$AI$59,MATCH($A50,Weeks!$A$7:$A$59,0),MATCH($D$5,Weeks!$X$5:$AI$5,0)),0)) | D50: =IF($A50>TODAY(),"",SUMIFS('Cash Ledger'!$E$7:$E$1006,'Cash Ledger'!$I$7:$I$1006,$D$5,'Cash Ledger'!$D$7:$D$1006,"Advance",'Cash Ledger'!$B$7:$B$1006,">="&$A50,'Cash Ledger'!$B$7:$B$1006,"<="&($A50+6))) | E50: =IF($A50>TODAY(),"",SUMIFS('Cash Ledger'!$E$7:$E$1006,'Cash Ledger'!$I$7:$I$1006,$D$5,'Cash Ledger'!$D$7:$D$1006,"Correction",'Cash Ledger'!$B$7:$B$1006,">="&$A50,'Cash Ledger'!$B$7:$B$1006,"<="&($A50+6))) | F50: =IF($A50>TODAY(),"",SUMIFS('Cash Ledger'!$E$7:$E$1006,'Cash Ledger'!$I$7:$I$1006,$D$5,'Cash Ledger'!$D$7:$D$1006,"Weekly pay",'Cash Ledger'!$B$7:$B$1006,">="&$A50,'Cash Ledger'!$B$7:$B$1006,"<="&($A50+6))) | G50: =IF($A50>TODAY(),"",SUMPRODUCT((Weeks!$A$7:$A$59<=$A50)*(Weeks!$X$5:$AI$5=$D$5)*Weeks!$X$7:$AI$59)-SUMIFS('Cash Ledger'!$E$7:$E$1006,'Cash Ledger'!$I$7:$I$1006,$D$5,'Cash Ledger'!$B$7:$B$1006,"<="&($A50+6))) | H50: =IF(OR($A50>TODAY(),$G50=""),"",IF(ROUND($G50,0)<0,"owes you",IF(ROUND($G50,0)>0,"you owe","settled")))
A51: =Weeks!$A$50 -> 46587 | B51: =IF($A51>TODAY(),"",IFERROR(INDEX(Weeks!$L$7:$W$59,MATCH($A51,Weeks!$A$7:$A$59,0),MATCH($D$5,Weeks!$L$5:$W$5,0)),0)) | C51: =IF($A51>TODAY(),"",IFERROR(INDEX(Weeks!$X$7:$AI$59,MATCH($A51,Weeks!$A$7:$A$59,0),MATCH($D$5,Weeks!$X$5:$AI$5,0)),0)) | D51: =IF($A51>TODAY(),"",SUMIFS('Cash Ledger'!$E$7:$E$1006,'Cash Ledger'!$I$7:$I$1006,$D$5,'Cash Ledger'!$D$7:$D$1006,"Advance",'Cash Ledger'!$B$7:$B$1006,">="&$A51,'Cash Ledger'!$B$7:$B$1006,"<="&($A51+6))) | E51: =IF($A51>TODAY(),"",SUMIFS('Cash Ledger'!$E$7:$E$1006,'Cash Ledger'!$I$7:$I$1006,$D$5,'Cash Ledger'!$D$7:$D$1006,"Correction",'Cash Ledger'!$B$7:$B$1006,">="&$A51,'Cash Ledger'!$B$7:$B$1006,"<="&($A51+6))) | F51: =IF($A51>TODAY(),"",SUMIFS('Cash Ledger'!$E$7:$E$1006,'Cash Ledger'!$I$7:$I$1006,$D$5,'Cash Ledger'!$D$7:$D$1006,"Weekly pay",'Cash Ledger'!$B$7:$B$1006,">="&$A51,'Cash Ledger'!$B$7:$B$1006,"<="&($A51+6))) | G51: =IF($A51>TODAY(),"",SUMPRODUCT((Weeks!$A$7:$A$59<=$A51)*(Weeks!$X$5:$AI$5=$D$5)*Weeks!$X$7:$AI$59)-SUMIFS('Cash Ledger'!$E$7:$E$1006,'Cash Ledger'!$I$7:$I$1006,$D$5,'Cash Ledger'!$B$7:$B$1006,"<="&($A51+6))) | H51: =IF(OR($A51>TODAY(),$G51=""),"",IF(ROUND($G51,0)<0,"owes you",IF(ROUND($G51,0)>0,"you owe","settled")))
A52: =Weeks!$A$51 -> 46594 | B52: =IF($A52>TODAY(),"",IFERROR(INDEX(Weeks!$L$7:$W$59,MATCH($A52,Weeks!$A$7:$A$59,0),MATCH($D$5,Weeks!$L$5:$W$5,0)),0)) | C52: =IF($A52>TODAY(),"",IFERROR(INDEX(Weeks!$X$7:$AI$59,MATCH($A52,Weeks!$A$7:$A$59,0),MATCH($D$5,Weeks!$X$5:$AI$5,0)),0)) | D52: =IF($A52>TODAY(),"",SUMIFS('Cash Ledger'!$E$7:$E$1006,'Cash Ledger'!$I$7:$I$1006,$D$5,'Cash Ledger'!$D$7:$D$1006,"Advance",'Cash Ledger'!$B$7:$B$1006,">="&$A52,'Cash Ledger'!$B$7:$B$1006,"<="&($A52+6))) | E52: =IF($A52>TODAY(),"",SUMIFS('Cash Ledger'!$E$7:$E$1006,'Cash Ledger'!$I$7:$I$1006,$D$5,'Cash Ledger'!$D$7:$D$1006,"Correction",'Cash Ledger'!$B$7:$B$1006,">="&$A52,'Cash Ledger'!$B$7:$B$1006,"<="&($A52+6))) | F52: =IF($A52>TODAY(),"",SUMIFS('Cash Ledger'!$E$7:$E$1006,'Cash Ledger'!$I$7:$I$1006,$D$5,'Cash Ledger'!$D$7:$D$1006,"Weekly pay",'Cash Ledger'!$B$7:$B$1006,">="&$A52,'Cash Ledger'!$B$7:$B$1006,"<="&($A52+6))) | G52: =IF($A52>TODAY(),"",SUMPRODUCT((Weeks!$A$7:$A$59<=$A52)*(Weeks!$X$5:$AI$5=$D$5)*Weeks!$X$7:$AI$59)-SUMIFS('Cash Ledger'!$E$7:$E$1006,'Cash Ledger'!$I$7:$I$1006,$D$5,'Cash Ledger'!$B$7:$B$1006,"<="&($A52+6))) | H52: =IF(OR($A52>TODAY(),$G52=""),"",IF(ROUND($G52,0)<0,"owes you",IF(ROUND($G52,0)>0,"you owe","settled")))
A53: =Weeks!$A$52 -> 46601 | B53: =IF($A53>TODAY(),"",IFERROR(INDEX(Weeks!$L$7:$W$59,MATCH($A53,Weeks!$A$7:$A$59,0),MATCH($D$5,Weeks!$L$5:$W$5,0)),0)) | C53: =IF($A53>TODAY(),"",IFERROR(INDEX(Weeks!$X$7:$AI$59,MATCH($A53,Weeks!$A$7:$A$59,0),MATCH($D$5,Weeks!$X$5:$AI$5,0)),0)) | D53: =IF($A53>TODAY(),"",SUMIFS('Cash Ledger'!$E$7:$E$1006,'Cash Ledger'!$I$7:$I$1006,$D$5,'Cash Ledger'!$D$7:$D$1006,"Advance",'Cash Ledger'!$B$7:$B$1006,">="&$A53,'Cash Ledger'!$B$7:$B$1006,"<="&($A53+6))) | E53: =IF($A53>TODAY(),"",SUMIFS('Cash Ledger'!$E$7:$E$1006,'Cash Ledger'!$I$7:$I$1006,$D$5,'Cash Ledger'!$D$7:$D$1006,"Correction",'Cash Ledger'!$B$7:$B$1006,">="&$A53,'Cash Ledger'!$B$7:$B$1006,"<="&($A53+6))) | F53: =IF($A53>TODAY(),"",SUMIFS('Cash Ledger'!$E$7:$E$1006,'Cash Ledger'!$I$7:$I$1006,$D$5,'Cash Ledger'!$D$7:$D$1006,"Weekly pay",'Cash Ledger'!$B$7:$B$1006,">="&$A53,'Cash Ledger'!$B$7:$B$1006,"<="&($A53+6))) | G53: =IF($A53>TODAY(),"",SUMPRODUCT((Weeks!$A$7:$A$59<=$A53)*(Weeks!$X$5:$AI$5=$D$5)*Weeks!$X$7:$AI$59)-SUMIFS('Cash Ledger'!$E$7:$E$1006,'Cash Ledger'!$I$7:$I$1006,$D$5,'Cash Ledger'!$B$7:$B$1006,"<="&($A53+6))) | H53: =IF(OR($A53>TODAY(),$G53=""),"",IF(ROUND($G53,0)<0,"owes you",IF(ROUND($G53,0)>0,"you owe","settled")))
A54: =Weeks!$A$53 -> 46608 | B54: =IF($A54>TODAY(),"",IFERROR(INDEX(Weeks!$L$7:$W$59,MATCH($A54,Weeks!$A$7:$A$59,0),MATCH($D$5,Weeks!$L$5:$W$5,0)),0)) | C54: =IF($A54>TODAY(),"",IFERROR(INDEX(Weeks!$X$7:$AI$59,MATCH($A54,Weeks!$A$7:$A$59,0),MATCH($D$5,Weeks!$X$5:$AI$5,0)),0)) | D54: =IF($A54>TODAY(),"",SUMIFS('Cash Ledger'!$E$7:$E$1006,'Cash Ledger'!$I$7:$I$1006,$D$5,'Cash Ledger'!$D$7:$D$1006,"Advance",'Cash Ledger'!$B$7:$B$1006,">="&$A54,'Cash Ledger'!$B$7:$B$1006,"<="&($A54+6))) | E54: =IF($A54>TODAY(),"",SUMIFS('Cash Ledger'!$E$7:$E$1006,'Cash Ledger'!$I$7:$I$1006,$D$5,'Cash Ledger'!$D$7:$D$1006,"Correction",'Cash Ledger'!$B$7:$B$1006,">="&$A54,'Cash Ledger'!$B$7:$B$1006,"<="&($A54+6))) | F54: =IF($A54>TODAY(),"",SUMIFS('Cash Ledger'!$E$7:$E$1006,'Cash Ledger'!$I$7:$I$1006,$D$5,'Cash Ledger'!$D$7:$D$1006,"Weekly pay",'Cash Ledger'!$B$7:$B$1006,">="&$A54,'Cash Ledger'!$B$7:$B$1006,"<="&($A54+6))) | G54: =IF($A54>TODAY(),"",SUMPRODUCT((Weeks!$A$7:$A$59<=$A54)*(Weeks!$X$5:$AI$5=$D$5)*Weeks!$X$7:$AI$59)-SUMIFS('Cash Ledger'!$E$7:$E$1006,'Cash Ledger'!$I$7:$I$1006,$D$5,'Cash Ledger'!$B$7:$B$1006,"<="&($A54+6))) | H54: =IF(OR($A54>TODAY(),$G54=""),"",IF(ROUND($G54,0)<0,"owes you",IF(ROUND($G54,0)>0,"you owe","settled")))
A55: =Weeks!$A$54 -> 46615 | B55: =IF($A55>TODAY(),"",IFERROR(INDEX(Weeks!$L$7:$W$59,MATCH($A55,Weeks!$A$7:$A$59,0),MATCH($D$5,Weeks!$L$5:$W$5,0)),0)) | C55: =IF($A55>TODAY(),"",IFERROR(INDEX(Weeks!$X$7:$AI$59,MATCH($A55,Weeks!$A$7:$A$59,0),MATCH($D$5,Weeks!$X$5:$AI$5,0)),0)) | D55: =IF($A55>TODAY(),"",SUMIFS('Cash Ledger'!$E$7:$E$1006,'Cash Ledger'!$I$7:$I$1006,$D$5,'Cash Ledger'!$D$7:$D$1006,"Advance",'Cash Ledger'!$B$7:$B$1006,">="&$A55,'Cash Ledger'!$B$7:$B$1006,"<="&($A55+6))) | E55: =IF($A55>TODAY(),"",SUMIFS('Cash Ledger'!$E$7:$E$1006,'Cash Ledger'!$I$7:$I$1006,$D$5,'Cash Ledger'!$D$7:$D$1006,"Correction",'Cash Ledger'!$B$7:$B$1006,">="&$A55,'Cash Ledger'!$B$7:$B$1006,"<="&($A55+6))) | F55: =IF($A55>TODAY(),"",SUMIFS('Cash Ledger'!$E$7:$E$1006,'Cash Ledger'!$I$7:$I$1006,$D$5,'Cash Ledger'!$D$7:$D$1006,"Weekly pay",'Cash Ledger'!$B$7:$B$1006,">="&$A55,'Cash Ledger'!$B$7:$B$1006,"<="&($A55+6))) | G55: =IF($A55>TODAY(),"",SUMPRODUCT((Weeks!$A$7:$A$59<=$A55)*(Weeks!$X$5:$AI$5=$D$5)*Weeks!$X$7:$AI$59)-SUMIFS('Cash Ledger'!$E$7:$E$1006,'Cash Ledger'!$I$7:$I$1006,$D$5,'Cash Ledger'!$B$7:$B$1006,"<="&($A55+6))) | H55: =IF(OR($A55>TODAY(),$G55=""),"",IF(ROUND($G55,0)<0,"owes you",IF(ROUND($G55,0)>0,"you owe","settled")))
A56: =Weeks!$A$55 -> 46622 | B56: =IF($A56>TODAY(),"",IFERROR(INDEX(Weeks!$L$7:$W$59,MATCH($A56,Weeks!$A$7:$A$59,0),MATCH($D$5,Weeks!$L$5:$W$5,0)),0)) | C56: =IF($A56>TODAY(),"",IFERROR(INDEX(Weeks!$X$7:$AI$59,MATCH($A56,Weeks!$A$7:$A$59,0),MATCH($D$5,Weeks!$X$5:$AI$5,0)),0)) | D56: =IF($A56>TODAY(),"",SUMIFS('Cash Ledger'!$E$7:$E$1006,'Cash Ledger'!$I$7:$I$1006,$D$5,'Cash Ledger'!$D$7:$D$1006,"Advance",'Cash Ledger'!$B$7:$B$1006,">="&$A56,'Cash Ledger'!$B$7:$B$1006,"<="&($A56+6))) | E56: =IF($A56>TODAY(),"",SUMIFS('Cash Ledger'!$E$7:$E$1006,'Cash Ledger'!$I$7:$I$1006,$D$5,'Cash Ledger'!$D$7:$D$1006,"Correction",'Cash Ledger'!$B$7:$B$1006,">="&$A56,'Cash Ledger'!$B$7:$B$1006,"<="&($A56+6))) | F56: =IF($A56>TODAY(),"",SUMIFS('Cash Ledger'!$E$7:$E$1006,'Cash Ledger'!$I$7:$I$1006,$D$5,'Cash Ledger'!$D$7:$D$1006,"Weekly pay",'Cash Ledger'!$B$7:$B$1006,">="&$A56,'Cash Ledger'!$B$7:$B$1006,"<="&($A56+6))) | G56: =IF($A56>TODAY(),"",SUMPRODUCT((Weeks!$A$7:$A$59<=$A56)*(Weeks!$X$5:$AI$5=$D$5)*Weeks!$X$7:$AI$59)-SUMIFS('Cash Ledger'!$E$7:$E$1006,'Cash Ledger'!$I$7:$I$1006,$D$5,'Cash Ledger'!$B$7:$B$1006,"<="&($A56+6))) | H56: =IF(OR($A56>TODAY(),$G56=""),"",IF(ROUND($G56,0)<0,"owes you",IF(ROUND($G56,0)>0,"you owe","settled")))
A57: =Weeks!$A$56 -> 46629 | B57: =IF($A57>TODAY(),"",IFERROR(INDEX(Weeks!$L$7:$W$59,MATCH($A57,Weeks!$A$7:$A$59,0),MATCH($D$5,Weeks!$L$5:$W$5,0)),0)) | C57: =IF($A57>TODAY(),"",IFERROR(INDEX(Weeks!$X$7:$AI$59,MATCH($A57,Weeks!$A$7:$A$59,0),MATCH($D$5,Weeks!$X$5:$AI$5,0)),0)) | D57: =IF($A57>TODAY(),"",SUMIFS('Cash Ledger'!$E$7:$E$1006,'Cash Ledger'!$I$7:$I$1006,$D$5,'Cash Ledger'!$D$7:$D$1006,"Advance",'Cash Ledger'!$B$7:$B$1006,">="&$A57,'Cash Ledger'!$B$7:$B$1006,"<="&($A57+6))) | E57: =IF($A57>TODAY(),"",SUMIFS('Cash Ledger'!$E$7:$E$1006,'Cash Ledger'!$I$7:$I$1006,$D$5,'Cash Ledger'!$D$7:$D$1006,"Correction",'Cash Ledger'!$B$7:$B$1006,">="&$A57,'Cash Ledger'!$B$7:$B$1006,"<="&($A57+6))) | F57: =IF($A57>TODAY(),"",SUMIFS('Cash Ledger'!$E$7:$E$1006,'Cash Ledger'!$I$7:$I$1006,$D$5,'Cash Ledger'!$D$7:$D$1006,"Weekly pay",'Cash Ledger'!$B$7:$B$1006,">="&$A57,'Cash Ledger'!$B$7:$B$1006,"<="&($A57+6))) | G57: =IF($A57>TODAY(),"",SUMPRODUCT((Weeks!$A$7:$A$59<=$A57)*(Weeks!$X$5:$AI$5=$D$5)*Weeks!$X$7:$AI$59)-SUMIFS('Cash Ledger'!$E$7:$E$1006,'Cash Ledger'!$I$7:$I$1006,$D$5,'Cash Ledger'!$B$7:$B$1006,"<="&($A57+6))) | H57: =IF(OR($A57>TODAY(),$G57=""),"",IF(ROUND($G57,0)<0,"owes you",IF(ROUND($G57,0)>0,"you owe","settled")))
A58: =Weeks!$A$57 -> 46636 | B58: =IF($A58>TODAY(),"",IFERROR(INDEX(Weeks!$L$7:$W$59,MATCH($A58,Weeks!$A$7:$A$59,0),MATCH($D$5,Weeks!$L$5:$W$5,0)),0)) | C58: =IF($A58>TODAY(),"",IFERROR(INDEX(Weeks!$X$7:$AI$59,MATCH($A58,Weeks!$A$7:$A$59,0),MATCH($D$5,Weeks!$X$5:$AI$5,0)),0)) | D58: =IF($A58>TODAY(),"",SUMIFS('Cash Ledger'!$E$7:$E$1006,'Cash Ledger'!$I$7:$I$1006,$D$5,'Cash Ledger'!$D$7:$D$1006,"Advance",'Cash Ledger'!$B$7:$B$1006,">="&$A58,'Cash Ledger'!$B$7:$B$1006,"<="&($A58+6))) | E58: =IF($A58>TODAY(),"",SUMIFS('Cash Ledger'!$E$7:$E$1006,'Cash Ledger'!$I$7:$I$1006,$D$5,'Cash Ledger'!$D$7:$D$1006,"Correction",'Cash Ledger'!$B$7:$B$1006,">="&$A58,'Cash Ledger'!$B$7:$B$1006,"<="&($A58+6))) | F58: =IF($A58>TODAY(),"",SUMIFS('Cash Ledger'!$E$7:$E$1006,'Cash Ledger'!$I$7:$I$1006,$D$5,'Cash Ledger'!$D$7:$D$1006,"Weekly pay",'Cash Ledger'!$B$7:$B$1006,">="&$A58,'Cash Ledger'!$B$7:$B$1006,"<="&($A58+6))) | G58: =IF($A58>TODAY(),"",SUMPRODUCT((Weeks!$A$7:$A$59<=$A58)*(Weeks!$X$5:$AI$5=$D$5)*Weeks!$X$7:$AI$59)-SUMIFS('Cash Ledger'!$E$7:$E$1006,'Cash Ledger'!$I$7:$I$1006,$D$5,'Cash Ledger'!$B$7:$B$1006,"<="&($A58+6))) | H58: =IF(OR($A58>TODAY(),$G58=""),"",IF(ROUND($G58,0)<0,"owes you",IF(ROUND($G58,0)>0,"you owe","settled")))
A59: =Weeks!$A$58 -> 46643 | B59: =IF($A59>TODAY(),"",IFERROR(INDEX(Weeks!$L$7:$W$59,MATCH($A59,Weeks!$A$7:$A$59,0),MATCH($D$5,Weeks!$L$5:$W$5,0)),0)) | C59: =IF($A59>TODAY(),"",IFERROR(INDEX(Weeks!$X$7:$AI$59,MATCH($A59,Weeks!$A$7:$A$59,0),MATCH($D$5,Weeks!$X$5:$AI$5,0)),0)) | D59: =IF($A59>TODAY(),"",SUMIFS('Cash Ledger'!$E$7:$E$1006,'Cash Ledger'!$I$7:$I$1006,$D$5,'Cash Ledger'!$D$7:$D$1006,"Advance",'Cash Ledger'!$B$7:$B$1006,">="&$A59,'Cash Ledger'!$B$7:$B$1006,"<="&($A59+6))) | E59: =IF($A59>TODAY(),"",SUMIFS('Cash Ledger'!$E$7:$E$1006,'Cash Ledger'!$I$7:$I$1006,$D$5,'Cash Ledger'!$D$7:$D$1006,"Correction",'Cash Ledger'!$B$7:$B$1006,">="&$A59,'Cash Ledger'!$B$7:$B$1006,"<="&($A59+6))) | F59: =IF($A59>TODAY(),"",SUMIFS('Cash Ledger'!$E$7:$E$1006,'Cash Ledger'!$I$7:$I$1006,$D$5,'Cash Ledger'!$D$7:$D$1006,"Weekly pay",'Cash Ledger'!$B$7:$B$1006,">="&$A59,'Cash Ledger'!$B$7:$B$1006,"<="&($A59+6))) | G59: =IF($A59>TODAY(),"",SUMPRODUCT((Weeks!$A$7:$A$59<=$A59)*(Weeks!$X$5:$AI$5=$D$5)*Weeks!$X$7:$AI$59)-SUMIFS('Cash Ledger'!$E$7:$E$1006,'Cash Ledger'!$I$7:$I$1006,$D$5,'Cash Ledger'!$B$7:$B$1006,"<="&($A59+6))) | H59: =IF(OR($A59>TODAY(),$G59=""),"",IF(ROUND($G59,0)<0,"owes you",IF(ROUND($G59,0)>0,"you owe","settled")))
A60: =Weeks!$A$59 -> 46650 | B60: =IF($A60>TODAY(),"",IFERROR(INDEX(Weeks!$L$7:$W$59,MATCH($A60,Weeks!$A$7:$A$59,0),MATCH($D$5,Weeks!$L$5:$W$5,0)),0)) | C60: =IF($A60>TODAY(),"",IFERROR(INDEX(Weeks!$X$7:$AI$59,MATCH($A60,Weeks!$A$7:$A$59,0),MATCH($D$5,Weeks!$X$5:$AI$5,0)),0)) | D60: =IF($A60>TODAY(),"",SUMIFS('Cash Ledger'!$E$7:$E$1006,'Cash Ledger'!$I$7:$I$1006,$D$5,'Cash Ledger'!$D$7:$D$1006,"Advance",'Cash Ledger'!$B$7:$B$1006,">="&$A60,'Cash Ledger'!$B$7:$B$1006,"<="&($A60+6))) | E60: =IF($A60>TODAY(),"",SUMIFS('Cash Ledger'!$E$7:$E$1006,'Cash Ledger'!$I$7:$I$1006,$D$5,'Cash Ledger'!$D$7:$D$1006,"Correction",'Cash Ledger'!$B$7:$B$1006,">="&$A60,'Cash Ledger'!$B$7:$B$1006,"<="&($A60+6))) | F60: =IF($A60>TODAY(),"",SUMIFS('Cash Ledger'!$E$7:$E$1006,'Cash Ledger'!$I$7:$I$1006,$D$5,'Cash Ledger'!$D$7:$D$1006,"Weekly pay",'Cash Ledger'!$B$7:$B$1006,">="&$A60,'Cash Ledger'!$B$7:$B$1006,"<="&($A60+6))) | G60: =IF($A60>TODAY(),"",SUMPRODUCT((Weeks!$A$7:$A$59<=$A60)*(Weeks!$X$5:$AI$5=$D$5)*Weeks!$X$7:$AI$59)-SUMIFS('Cash Ledger'!$E$7:$E$1006,'Cash Ledger'!$I$7:$I$1006,$D$5,'Cash Ledger'!$B$7:$B$1006,"<="&($A60+6))) | H60: =IF(OR($A60>TODAY(),$G60=""),"",IF(ROUND($G60,0)<0,"owes you",IF(ROUND($G60,0)>0,"you owe","settled")))

Sheet Workers
A1: ◆ Donabay | C1: Home | D1: Daily Log | F1: Cash Ledger | H1: Weekly Pay | I1: Payslip | K1: Workers | M1: Settings | O1: Guide | Q1: · | R1: History | T1: Weeks | V1: Checks
A2: Workers
A3: Add a worker: fill the next empty slot and set Active. Remove one: set Left. Never delete or reuse a slot - that keeps each person's history intact.
A5: ID | B5: Name | C5: Status | D5: Joined | E5: Left on | F5: Phone | G5: Notes | H5: Check
A6: W01 | B6: Davlatbek | C6: Active | D6: 46286 | H6: =IF($B6="",IF($C6<>"","status set but no name",""),IF(COUNTIF($B$6:$B$17,$B6)>1,"same name twice - make it unique",IF($C6="","choose Active or Left","")))
A7: W02 | B7: Xusanboy | C7: Active | D7: 46286 | H7: =IF($B7="",IF($C7<>"","status set but no name",""),IF(COUNTIF($B$6:$B$17,$B7)>1,"same name twice - make it unique",IF($C7="","choose Active or Left","")))
A8: W03 | B8: Oybek | C8: Active | D8: 46286 | H8: =IF($B8="",IF($C8<>"","status set but no name",""),IF(COUNTIF($B$6:$B$17,$B8)>1,"same name twice - make it unique",IF($C8="","choose Active or Left","")))
A9: W04 | B9: Abdurashid | C9: Active | D9: 46286 | H9: =IF($B9="",IF($C9<>"","status set but no name",""),IF(COUNTIF($B$6:$B$17,$B9)>1,"same name twice - make it unique",IF($C9="","choose Active or Left","")))
A10: W05 | H10: =IF($B10="",IF($C10<>"","status set but no name",""),IF(COUNTIF($B$6:$B$17,$B10)>1,"same name twice - make it unique",IF($C10="","choose Active or Left","")))
A11: W06 | H11: =IF($B11="",IF($C11<>"","status set but no name",""),IF(COUNTIF($B$6:$B$17,$B11)>1,"same name twice - make it unique",IF($C11="","choose Active or Left","")))
A12: W07 | H12: =IF($B12="",IF($C12<>"","status set but no name",""),IF(COUNTIF($B$6:$B$17,$B12)>1,"same name twice - make it unique",IF($C12="","choose Active or Left","")))
A13: W08 | H13: =IF($B13="",IF($C13<>"","status set but no name",""),IF(COUNTIF($B$6:$B$17,$B13)>1,"same name twice - make it unique",IF($C13="","choose Active or Left","")))
A14: W09 | H14: =IF($B14="",IF($C14<>"","status set but no name",""),IF(COUNTIF($B$6:$B$17,$B14)>1,"same name twice - make it unique",IF($C14="","choose Active or Left","")))
A15: W10 | H15: =IF($B15="",IF($C15<>"","status set but no name",""),IF(COUNTIF($B$6:$B$17,$B15)>1,"same name twice - make it unique",IF($C15="","choose Active or Left","")))
A16: W11 | H16: =IF($B16="",IF($C16<>"","status set but no name",""),IF(COUNTIF($B$6:$B$17,$B16)>1,"same name twice - make it unique",IF($C16="","choose Active or Left","")))
A17: W12 | H17: =IF($B17="",IF($C17<>"","status set but no name",""),IF(COUNTIF($B$6:$B$17,$B17)>1,"same name twice - make it unique",IF($C17="","choose Active or Left","")))

Sheet Settings
A1: ◆ Donabay | C1: Home | D1: Daily Log | E1: Cash Ledger | H1: Weekly Pay | K1: Payslip | M1: Workers | O1: Settings | Q1: Guide | S1: · | T1: History | V1: Weeks | X1: Checks
A2: Settings
A3: Change these rarely. Tinted (light blue) cells are yours to edit.
B5: Rules | F5: Lists (used by dropdowns)
B6: Breakage allowance | C6: 0 | D6: Broken blocks up to this share of what was moulded are still paid. 0% = pay only good blocks (your rule). Block plants commonly break 2-5%; set e.g. 3% if you want to absorb normal breakage yourself. | F6: Advance | G6: Active | H6: Yes
B7: Old debt taken back per week, max | C7: 1 | D7: When a worker owes you from earlier weeks, at most this share of a week's earnings goes to paying it back. 100% = take back everything you can (your rule). For formally employed workers Uzbek labour law caps wage deductions at 50% - check the Labour Code on lex.uz before relying on this. | F7: Weekly pay | G7: Left | H7: No
B8: Reject rate that raises a warning | C8: 0.08 | D8: Normal breakage in block plants is 2-5%; above about 8% usually means a curing or handling problem worth looking at. | F8: Correction
B11: Pay rate per paid block
B12: Starts from (date) | C12: Rate (so'm per block)
B13: 46286 | C13: 500 | D13: <- type your rate here. Add a row below when it changes; old weeks keep the old rate.

Sheet Guide
A1: ◆ Donabay | C1: Home | D1: Daily Log | F1: Cash Ledger | I1: Weekly Pay | L1: Payslip | N1: Workers | P1: Settings | R1: Guide | T1: · | U1: History | W1: Weeks | Y1: Checks
A2: Donabay
A3: Filler-block production and weekly crew pay. No macros, no add-ins - just type.
B5: Workbook status | C5: =Checks!$C$5 -> ALL CHECKS OK
B8: FIRST TIME
B9: 1. Settings | C9: Type your pay rate per block next to the start date.
B10: 2. Workers | C10: Replace 'Worker 1..4' with real names. Leave them Active.
B12: EVERY DAY (1 minute)
B13: Daily Log | C13: On today's row: blocks moulded, blocks broken, and 1 under each worker who came (0.5 for half a day, leave empty if absent). Broken blocks can be filled in later, once you know them.
B15: WHEN SOMEONE ASKS FOR MONEY
B16: Cash Ledger | C16: New row: date, worker, type 'Advance', amount, reason. That's it - it is subtracted on payday automatically.
B18: PAYDAY
B19: 1. Weekly Pay | C19: Pick the week. Check 'Before you pay' says OK. Pay each worker the green TO PAY amount.
B20: 2. Cash Ledger | C20: Copy the green 'Ready for the Cash Ledger' list on Weekly Pay and Paste Values into the next empty row.
B21: 3. Payslip | C21: Print one per worker and have them sign. It lists every advance they took that week.
B23: PEOPLE CHANGE
B24: Someone joins | C24: Workers: type the name in the next empty slot, status Active, joined date.
B25: Someone leaves | C25: Workers: set status Left. Do not delete the row - their history stays.
B26: Rate changes | C26: Settings: add a NEW row with the date the new rate starts. Old weeks keep the old rate.
B28: MISTAKES
B29: Wrong ledger entry | C29: Do not delete it. Add a 'Correction' row with the opposite amount (e.g. -100000) and say why.
B31: RULES THIS FILE FOLLOWS
B32: Pay base | C32: Only good blocks are paid (moulded minus broken). Settings can add a breakage allowance.
B33: Split | C33: The week's pot is shared by days worked: pot x your days / everyone's days.
B34: Debts | C34: Advances bigger than earnings never make pay negative - pay is 0 and the rest carries forward, visible on every payslip until it is paid back.
B35: Colours | C35: Light blue = you type here. White = calculated, leave alone. Red = needs a look.

Sheet Weeks
A1: ◆ Donabay | C1: Home | D1: Daily Log | F1: Cash Ledger | H1: Weekly Pay | J1: Payslip | K1: Workers | L1: Settings | N1: Guide | P1: · | Y1: History | AA1: Weeks | AK1: Checks
A2: Weeks
A3: Calculation engine - nothing to type here. Every other sheet reads from it.
L4: Days worked | X4: Earned (so'm)
L5: W01 | M5: W02 | N5: W03 | O5: W04 | P5: W05 | Q5: W06 | R5: W07 | S5: W08 | T5: W09 | U5: W10 | V5: W11 | W5: W12 | X5: W01 | Y5: W02 | Z5: W03 | AA5: W04 | AB5: W05 | AC5: W06 | AD5: W07 | AE5: W08 | AF5: W09 | AG5: W10 | AH5: W11 | AI5: W12
A6: Week of | B6: to | C6: Moulded | D6: Broken | E6: Good | F6: Paid blocks | G6: Pot (so'm) | H6: Crew-days | I6: Reject % | J6: Good per crew-day | K6: Check | L6: =IF(Workers!$B$6="",Workers!$A$6,Workers!$B$6) -> Davlatbek | M6: =IF(Workers!$B$7="",Workers!$A$7,Workers!$B$7) -> Xusanboy | N6: =IF(Workers!$B$8="",Workers!$A$8,Workers!$B$8) -> Oybek | O6: =IF(Workers!$B$9="",Workers!$A$9,Workers!$B$9) -> Abdurashid | P6: =IF(Workers!$B$10="",Workers!$A$10,Workers!$B$10) -> W05 | Q6: =IF(Workers!$B$11="",Workers!$A$11,Workers!$B$11) -> W06 | R6: =IF(Workers!$B$12="",Workers!$A$12,Workers!$B$12) -> W07 | S6: =IF(Workers!$B$13="",Workers!$A$13,Workers!$B$13) -> W08 | T6: =IF(Workers!$B$14="",Workers!$A$14,Workers!$B$14) -> W09 | U6: =IF(Workers!$B$15="",Workers!$A$15,Workers!$B$15) -> W10 | V6: =IF(Workers!$B$16="",Workers!$A$16,Workers!$B$16) -> W11 | W6: =IF(Workers!$B$17="",Workers!$A$17,Workers!$B$17) -> W12 | X6: =IF(Workers!$B$6="",Workers!$A$6,Workers!$B$6) -> Davlatbek | Y6: =IF(Workers!$B$7="",Workers!$A$7,Workers!$B$7) -> Xusanboy | Z6: =IF(Workers!$B$8="",Workers!$A$8,Workers!$B$8) -> Oybek | AA6: =IF(Workers!$B$9="",Workers!$A$9,Workers!$B$9) -> Abdurashid | AB6: =IF(Workers!$B$10="",Workers!$A$10,Workers!$B$10) -> W05 | AC6: =IF(Workers!$B$11="",Workers!$A$11,Workers!$B$11) -> W06 | AD6: =IF(Workers!$B$12="",Workers!$A$12,Workers!$B$12) -> W07 | AE6: =IF(Workers!$B$13="",Workers!$A$13,Workers!$B$13) -> W08 | AF6: =IF(Workers!$B$14="",Workers!$A$14,Workers!$B$14) -> W09 | AG6: =IF(Workers!$B$15="",Workers!$A$15,Workers!$B$15) -> W10 | AH6: =IF(Workers!$B$16="",Workers!$A$16,Workers!$B$16) -> W11 | AI6: =IF(Workers!$B$17="",Workers!$A$17,Workers!$B$17) -> W12 | AJ6: Shares total | AK6: Shares - pot
A7: 46286 | B7: =$A7+6 -> 46292 | C7: =SUMIFS('Daily Log'!$C$7:$C$377,'Daily Log'!$V$7:$V$377,$A7) -> 11978 | D7: =SUMIFS('Daily Log'!$D$7:$D$377,'Daily Log'!$V$7:$V$377,$A7) -> 121 | E7: =SUMIFS('Daily Log'!$E$7:$E$377,'Daily Log'!$V$7:$V$377,$A7) -> 11857 | F7: =SUMIFS('Daily Log'!$F$7:$F$377,'Daily Log'!$V$7:$V$377,$A7) -> 11857 | G7: =SUMIFS('Daily Log'!$U$7:$U$377,'Daily Log'!$V$7:$V$377,$A7) -> 5928500 | H7: =SUMIFS('Daily Log'!$S$7:$S$377,'Daily Log'!$V$7:$V$377,$A7) -> 24 | I7: =IF($C7=0,"",$D7/$C7) -> 0.010101853 | J7: =IF($H7=0,"",$E7/$H7) -> 494.04167 | K7: =IF(AND($G7>0,$H7=0),"pot not shared - no attendance marked",IF(AND($I7<>"",N($I7)>RejectAlarm),"reject rate high","")) | L7: =SUMIFS('Daily Log'!$G$7:$G$377,'Daily Log'!$V$7:$V$377,$A7) -> 6 | M7: =SUMIFS('Daily Log'!$H$7:$H$377,'Daily Log'!$V$7:$V$377,$A7) -> 6 | N7: =SUMIFS('Daily Log'!$I$7:$I$377,'Daily Log'!$V$7:$V$377,$A7) -> 6 | O7: =SUMIFS('Daily Log'!$J$7:$J$377,'Daily Log'!$V$7:$V$377,$A7) -> 6 | P7: =SUMIFS('Daily Log'!$K$7:$K$377,'Daily Log'!$V$7:$V$377,$A7) -> 0 | Q7: =SUMIFS('Daily Log'!$L$7:$L$377,'Daily Log'!$V$7:$V$377,$A7) -> 0 | R7: =SUMIFS('Daily Log'!$M$7:$M$377,'Daily Log'!$V$7:$V$377,$A7) -> 0 | S7: =SUMIFS('Daily Log'!$N$7:$N$377,'Daily Log'!$V$7:$V$377,$A7) -> 0 | T7: =SUMIFS('Daily Log'!$O$7:$O$377,'Daily Log'!$V$7:$V$377,$A7) -> 0 | U7: =SUMIFS('Daily Log'!$P$7:$P$377,'Daily Log'!$V$7:$V$377,$A7) -> 0 | V7: =SUMIFS('Daily Log'!$Q$7:$Q$377,'Daily Log'!$V$7:$V$377,$A7) -> 0 | W7: =SUMIFS('Daily Log'!$R$7:$R$377,'Daily Log'!$V$7:$V$377,$A7) -> 0 | X7: =IF($H7=0,0,ROUND($G7*L7/$H7,0)) -> 1482125 | Y7: =IF($H7=0,0,ROUND($G7*M7/$H7,0)) -> 1482125 | Z7: =IF($H7=0,0,ROUND($G7*N7/$H7,0)) -> 1482125 | AA7: =IF($H7=0,0,ROUND($G7*O7/$H7,0)) -> 1482125 | AB7: =IF($H7=0,0,ROUND($G7*P7/$H7,0)) -> 0 | AC7: =IF($H7=0,0,ROUND($G7*Q7/$H7,0)) -> 0 | AD7: =IF($H7=0,0,ROUND($G7*R7/$H7,0)) -> 0 | AE7: =IF($H7=0,0,ROUND($G7*S7/$H7,0)) -> 0 | ... AI7: =IF($H7=0,0,ROUND($G7*W7/$H7,0)) -> 0 | AJ7: =SUM(X7:AI7) -> 5928500 | AK7: =$AJ7-$G7 -> 0
A8: 46293 | B8: =$A8+6 -> 46299 | C8: =SUMIFS('Daily Log'!$C$7:$C$377,'Daily Log'!$V$7:$V$377,$A8) -> 0 | D8: =SUMIFS('Daily Log'!$D$7:$D$377,'Daily Log'!$V$7:$V$377,$A8) -> 0 | E8: =SUMIFS('Daily Log'!$E$7:$E$377,'Daily Log'!$V$7:$V$377,$A8) -> 0 | F8: =SUMIFS('Daily Log'!$F$7:$F$377,'Daily Log'!$V$7:$V$377,$A8) -> 0 | G8: =SUMIFS('Daily Log'!$U$7:$U$377,'Daily Log'!$V$7:$V$377,$A8) -> 0 | H8: =SUMIFS('Daily Log'!$S$7:$S$377,'Daily Log'!$V$7:$V$377,$A8) -> 0 | I8: =IF($C8=0,"",$D8/$C8) | J8: =IF($H8=0,"",$E8/$H8) | K8: =IF(AND($G8>0,$H8=0),"pot not shared - no attendance marked",IF(AND($I8<>"",N($I8)>RejectAlarm),"reject rate high","")) | L8: =SUMIFS('Daily Log'!$G$7:$G$377,'Daily Log'!$V$7:$V$377,$A8) -> 0 | M8: =SUMIFS('Daily Log'!$H$7:$H$377,'Daily Log'!$V$7:$V$377,$A8) -> 0 | N8: =SUMIFS('Daily Log'!$I$7:$I$377,'Daily Log'!$V$7:$V$377,$A8) -> 0 | O8: =SUMIFS('Daily Log'!$J$7:$J$377,'Daily Log'!$V$7:$V$377,$A8) -> 0 | P8: =SUMIFS('Daily Log'!$K$7:$K$377,'Daily Log'!$V$7:$V$377,$A8) -> 0 | Q8: =SUMIFS('Daily Log'!$L$7:$L$377,'Daily Log'!$V$7:$V$377,$A8) -> 0 | R8: =SUMIFS('Daily Log'!$M$7:$M$377,'Daily Log'!$V$7:$V$377,$A8) -> 0 | S8: =SUMIFS('Daily Log'!$N$7:$N$377,'Daily Log'!$V$7:$V$377,$A8) -> 0 | T8: =SUMIFS('Daily Log'!$O$7:$O$377,'Daily Log'!$V$7:$V$377,$A8) -> 0 | U8: =SUMIFS('Daily Log'!$P$7:$P$377,'Daily Log'!$V$7:$V$377,$A8) -> 0 | V8: =SUMIFS('Daily Log'!$Q$7:$Q$377,'Daily Log'!$V$7:$V$377,$A8) -> 0 | W8: =SUMIFS('Daily Log'!$R$7:$R$377,'Daily Log'!$V$7:$V$377,$A8) -> 0 | X8: =IF($H8=0,0,ROUND($G8*L8/$H8,0)) -> 0 | Y8: =IF($H8=0,0,ROUND($G8*M8/$H8,0)) -> 0 | Z8: =IF($H8=0,0,ROUND($G8*N8/$H8,0)) -> 0 | AA8: =IF($H8=0,0,ROUND($G8*O8/$H8,0)) -> 0 | AB8: =IF($H8=0,0,ROUND($G8*P8/$H8,0)) -> 0 | AC8: =IF($H8=0,0,ROUND($G8*Q8/$H8,0)) -> 0 | AD8: =IF($H8=0,0,ROUND($G8*R8/$H8,0)) -> 0 | AE8: =IF($H8=0,0,ROUND($G8*S8/$H8,0)) -> 0 | ... AI8: =IF($H8=0,0,ROUND($G8*W8/$H8,0)) -> 0 | AJ8: =SUM(X8:AI8) -> 0 | AK8: =$AJ8-$G8 -> 0
A9: 46300 | B9: =$A9+6 -> 46306 | C9: =SUMIFS('Daily Log'!$C$7:$C$377,'Daily Log'!$V$7:$V$377,$A9) -> 0 | D9: =SUMIFS('Daily Log'!$D$7:$D$377,'Daily Log'!$V$7:$V$377,$A9) -> 0 | E9: =SUMIFS('Daily Log'!$E$7:$E$377,'Daily Log'!$V$7:$V$377,$A9) -> 0 | F9: =SUMIFS('Daily Log'!$F$7:$F$377,'Daily Log'!$V$7:$V$377,$A9) -> 0 | G9: =SUMIFS('Daily Log'!$U$7:$U$377,'Daily Log'!$V$7:$V$377,$A9) -> 0 | H9: =SUMIFS('Daily Log'!$S$7:$S$377,'Daily Log'!$V$7:$V$377,$A9) -> 0 | I9: =IF($C9=0,"",$D9/$C9) | J9: =IF($H9=0,"",$E9/$H9) | K9: =IF(AND($G9>0,$H9=0),"pot not shared - no attendance marked",IF(AND($I9<>"",N($I9)>RejectAlarm),"reject rate high","")) | L9: =SUMIFS('Daily Log'!$G$7:$G$377,'Daily Log'!$V$7:$V$377,$A9) -> 0 | M9: =SUMIFS('Daily Log'!$H$7:$H$377,'Daily Log'!$V$7:$V$377,$A9) -> 0 | N9: =SUMIFS('Daily Log'!$I$7:$I$377,'Daily Log'!$V$7:$V$377,$A9) -> 0 | O9: =SUMIFS('Daily Log'!$J$7:$J$377,'Daily Log'!$V$7:$V$377,$A9) -> 0 | P9: =SUMIFS('Daily Log'!$K$7:$K$377,'Daily Log'!$V$7:$V$377,$A9) -> 0 | Q9: =SUMIFS('Daily Log'!$L$7:$L$377,'Daily Log'!$V$7:$V$377,$A9) -> 0 | R9: =SUMIFS('Daily Log'!$M$7:$M$377,'Daily Log'!$V$7:$V$377,$A9) -> 0 | S9: =SUMIFS('Daily Log'!$N$7:$N$377,'Daily Log'!$V$7:$V$377,$A9) -> 0 | T9: =SUMIFS('Daily Log'!$O$7:$O$377,'Daily Log'!$V$7:$V$377,$A9) -> 0 | U9: =SUMIFS('Daily Log'!$P$7:$P$377,'Daily Log'!$V$7:$V$377,$A9) -> 0 | V9: =SUMIFS('Daily Log'!$Q$7:$Q$377,'Daily Log'!$V$7:$V$377,$A9) -> 0 | W9: =SUMIFS('Daily Log'!$R$7:$R$377,'Daily Log'!$V$7:$V$377,$A9) -> 0 | X9: =IF($H9=0,0,ROUND($G9*L9/$H9,0)) -> 0 | Y9: =IF($H9=0,0,ROUND($G9*M9/$H9,0)) -> 0 | Z9: =IF($H9=0,0,ROUND($G9*N9/$H9,0)) -> 0 | AA9: =IF($H9=0,0,ROUND($G9*O9/$H9,0)) -> 0 | AB9: =IF($H9=0,0,ROUND($G9*P9/$H9,0)) -> 0 | AC9: =IF($H9=0,0,ROUND($G9*Q9/$H9,0)) -> 0 | AD9: =IF($H9=0,0,ROUND($G9*R9/$H9,0)) -> 0 | AE9: =IF($H9=0,0,ROUND($G9*S9/$H9,0)) -> 0 | ... AI9: =IF($H9=0,0,ROUND($G9*W9/$H9,0)) -> 0 | AJ9: =SUM(X9:AI9) -> 0 | AK9: =$AJ9-$G9 -> 0
A10: 46307 | B10: =$A10+6 -> 46313 | C10: =SUMIFS('Daily Log'!$C$7:$C$377,'Daily Log'!$V$7:$V$377,$A10) -> 0 | D10: =SUMIFS('Daily Log'!$D$7:$D$377,'Daily Log'!$V$7:$V$377,$A10) -> 0 | E10: =SUMIFS('Daily Log'!$E$7:$E$377,'Daily Log'!$V$7:$V$377,$A10) -> 0 | F10: =SUMIFS('Daily Log'!$F$7:$F$377,'Daily Log'!$V$7:$V$377,$A10) -> 0 | G10: =SUMIFS('Daily Log'!$U$7:$U$377,'Daily Log'!$V$7:$V$377,$A10) -> 0 | H10: =SUMIFS('Daily Log'!$S$7:$S$377,'Daily Log'!$V$7:$V$377,$A10) -> 0 | I10: =IF($C10=0,"",$D10/$C10) | J10: =IF($H10=0,"",$E10/$H10) | K10: =IF(AND($G10>0,$H10=0),"pot not shared - no attendance marked",IF(AND($I10<>"",N($I10)>RejectAlarm),"reject rate high","")) | L10: =SUMIFS('Daily Log'!$G$7:$G$377,'Daily Log'!$V$7:$V$377,$A10) -> 0 | M10: =SUMIFS('Daily Log'!$H$7:$H$377,'Daily Log'!$V$7:$V$377,$A10) -> 0 | N10: =SUMIFS('Daily Log'!$I$7:$I$377,'Daily Log'!$V$7:$V$377,$A10) -> 0 | O10: =SUMIFS('Daily Log'!$J$7:$J$377,'Daily Log'!$V$7:$V$377,$A10) -> 0 | P10: =SUMIFS('Daily Log'!$K$7:$K$377,'Daily Log'!$V$7:$V$377,$A10) -> 0 | Q10: =SUMIFS('Daily Log'!$L$7:$L$377,'Daily Log'!$V$7:$V$377,$A10) -> 0 | R10: =SUMIFS('Daily Log'!$M$7:$M$377,'Daily Log'!$V$7:$V$377,$A10) -> 0 | S10: =SUMIFS('Daily Log'!$N$7:$N$377,'Daily Log'!$V$7:$V$377,$A10) -> 0 | T10: =SUMIFS('Daily Log'!$O$7:$O$377,'Daily Log'!$V$7:$V$377,$A10) -> 0 | U10: =SUMIFS('Daily Log'!$P$7:$P$377,'Daily Log'!$V$7:$V$377,$A10) -> 0 | V10: =SUMIFS('Daily Log'!$Q$7:$Q$377,'Daily Log'!$V$7:$V$377,$A10) -> 0 | W10: =SUMIFS('Daily Log'!$R$7:$R$377,'Daily Log'!$V$7:$V$377,$A10) -> 0 | X10: =IF($H10=0,0,ROUND($G10*L10/$H10,0)) -> 0 | Y10: =IF($H10=0,0,ROUND($G10*M10/$H10,0)) -> 0 | Z10: =IF($H10=0,0,ROUND($G10*N10/$H10,0)) -> 0 | AA10: =IF($H10=0,0,ROUND($G10*O10/$H10,0)) -> 0 | AB10: =IF($H10=0,0,ROUND($G10*P10/$H10,0)) -> 0 | AC10: =IF($H10=0,0,ROUND($G10*Q10/$H10,0)) -> 0 | AD10: =IF($H10=0,0,ROUND($G10*R10/$H10,0)) -> 0 | AE10: =IF($H10=0,0,ROUND($G10*S10/$H10,0)) -> 0 | ... AI10: =IF($H10=0,0,ROUND($G10*W10/$H10,0)) -> 0 | AJ10: =SUM(X10:AI10) -> 0 | AK10: =$AJ10-$G10 -> 0
A11: 46314 | B11: =$A11+6 -> 46320 | C11: =SUMIFS('Daily Log'!$C$7:$C$377,'Daily Log'!$V$7:$V$377,$A11) -> 0 | D11: =SUMIFS('Daily Log'!$D$7:$D$377,'Daily Log'!$V$7:$V$377,$A11) -> 0 | E11: =SUMIFS('Daily Log'!$E$7:$E$377,'Daily Log'!$V$7:$V$377,$A11) -> 0 | F11: =SUMIFS('Daily Log'!$F$7:$F$377,'Daily Log'!$V$7:$V$377,$A11) -> 0 | G11: =SUMIFS('Daily Log'!$U$7:$U$377,'Daily Log'!$V$7:$V$377,$A11) -> 0 | H11: =SUMIFS('Daily Log'!$S$7:$S$377,'Daily Log'!$V$7:$V$377,$A11) -> 0 | I11: =IF($C11=0,"",$D11/$C11) | J11: =IF($H11=0,"",$E11/$H11) | K11: =IF(AND($G11>0,$H11=0),"pot not shared - no attendance marked",IF(AND($I11<>"",N($I11)>RejectAlarm),"reject rate high","")) | L11: =SUMIFS('Daily Log'!$G$7:$G$377,'Daily Log'!$V$7:$V$377,$A11) -> 0 | M11: =SUMIFS('Daily Log'!$H$7:$H$377,'Daily Log'!$V$7:$V$377,$A11) -> 0 | N11: =SUMIFS('Daily Log'!$I$7:$I$377,'Daily Log'!$V$7:$V$377,$A11) -> 0 | O11: =SUMIFS('Daily Log'!$J$7:$J$377,'Daily Log'!$V$7:$V$377,$A11) -> 0 | P11: =SUMIFS('Daily Log'!$K$7:$K$377,'Daily Log'!$V$7:$V$377,$A11) -> 0 | Q11: =SUMIFS('Daily Log'!$L$7:$L$377,'Daily Log'!$V$7:$V$377,$A11) -> 0 | R11: =SUMIFS('Daily Log'!$M$7:$M$377,'Daily Log'!$V$7:$V$377,$A11) -> 0 | S11: =SUMIFS('Daily Log'!$N$7:$N$377,'Daily Log'!$V$7:$V$377,$A11) -> 0 | T11: =SUMIFS('Daily Log'!$O$7:$O$377,'Daily Log'!$V$7:$V$377,$A11) -> 0 | U11: =SUMIFS('Daily Log'!$P$7:$P$377,'Daily Log'!$V$7:$V$377,$A11) -> 0 | V11: =SUMIFS('Daily Log'!$Q$7:$Q$377,'Daily Log'!$V$7:$V$377,$A11) -> 0 | W11: =SUMIFS('Daily Log'!$R$7:$R$377,'Daily Log'!$V$7:$V$377,$A11) -> 0 | X11: =IF($H11=0,0,ROUND($G11*L11/$H11,0)) -> 0 | Y11: =IF($H11=0,0,ROUND($G11*M11/$H11,0)) -> 0 | Z11: =IF($H11=0,0,ROUND($G11*N11/$H11,0)) -> 0 | AA11: =IF($H11=0,0,ROUND($G11*O11/$H11,0)) -> 0 | AB11: =IF($H11=0,0,ROUND($G11*P11/$H11,0)) -> 0 | AC11: =IF($H11=0,0,ROUND($G11*Q11/$H11,0)) -> 0 | AD11: =IF($H11=0,0,ROUND($G11*R11/$H11,0)) -> 0 | AE11: =IF($H11=0,0,ROUND($G11*S11/$H11,0)) -> 0 | ... AI11: =IF($H11=0,0,ROUND($G11*W11/$H11,0)) -> 0 | AJ11: =SUM(X11:AI11) -> 0 | AK11: =$AJ11-$G11 -> 0
A12: 46321 | B12: =$A12+6 -> 46327 | C12: =SUMIFS('Daily Log'!$C$7:$C$377,'Daily Log'!$V$7:$V$377,$A12) -> 0 | D12: =SUMIFS('Daily Log'!$D$7:$D$377,'Daily Log'!$V$7:$V$377,$A12) -> 0 | E12: =SUMIFS('Daily Log'!$E$7:$E$377,'Daily Log'!$V$7:$V$377,$A12) -> 0 | F12: =SUMIFS('Daily Log'!$F$7:$F$377,'Daily Log'!$V$7:$V$377,$A12) -> 0 | G12: =SUMIFS('Daily Log'!$U$7:$U$377,'Daily Log'!$V$7:$V$377,$A12) -> 0 | H12: =SUMIFS('Daily Log'!$S$7:$S$377,'Daily Log'!$V$7:$V$377,$A12) -> 0 | I12: =IF($C12=0,"",$D12/$C12) | J12: =IF($H12=0,"",$E12/$H12) | K12: =IF(AND($G12>0,$H12=0),"pot not shared - no attendance marked",IF(AND($I12<>"",N($I12)>RejectAlarm),"reject rate high","")) | L12: =SUMIFS('Daily Log'!$G$7:$G$377,'Daily Log'!$V$7:$V$377,$A12) -> 0 | M12: =SUMIFS('Daily Log'!$H$7:$H$377,'Daily Log'!$V$7:$V$377,$A12) -> 0 | N12: =SUMIFS('Daily Log'!$I$7:$I$377,'Daily Log'!$V$7:$V$377,$A12) -> 0 | O12: =SUMIFS('Daily Log'!$J$7:$J$377,'Daily Log'!$V$7:$V$377,$A12) -> 0 | P12: =SUMIFS('Daily Log'!$K$7:$K$377,'Daily Log'!$V$7:$V$377,$A12) -> 0 | Q12: =SUMIFS('Daily Log'!$L$7:$L$377,'Daily Log'!$V$7:$V$377,$A12) -> 0 | R12: =SUMIFS('Daily Log'!$M$7:$M$377,'Daily Log'!$V$7:$V$377,$A12) -> 0 | S12: =SUMIFS('Daily Log'!$N$7:$N$377,'Daily Log'!$V$7:$V$377,$A12) -> 0 | T12: =SUMIFS('Daily Log'!$O$7:$O$377,'Daily Log'!$V$7:$V$377,$A12) -> 0 | U12: =SUMIFS('Daily Log'!$P$7:$P$377,'Daily Log'!$V$7:$V$377,$A12) -> 0 | V12: =SUMIFS('Daily Log'!$Q$7:$Q$377,'Daily Log'!$V$7:$V$377,$A12) -> 0 | W12: =SUMIFS('Daily Log'!$R$7:$R$377,'Daily Log'!$V$7:$V$377,$A12) -> 0 | X12: =IF($H12=0,0,ROUND($G12*L12/$H12,0)) -> 0 | Y12: =IF($H12=0,0,ROUND($G12*M12/$H12,0)) -> 0 | Z12: =IF($H12=0,0,ROUND($G12*N12/$H12,0)) -> 0 | AA12: =IF($H12=0,0,ROUND($G12*O12/$H12,0)) -> 0 | AB12: =IF($H12=0,0,ROUND($G12*P12/$H12,0)) -> 0 | AC12: =IF($H12=0,0,ROUND($G12*Q12/$H12,0)) -> 0 | AD12: =IF($H12=0,0,ROUND($G12*R12/$H12,0)) -> 0 | AE12: =IF($H12=0,0,ROUND($G12*S12/$H12,0)) -> 0 | ... AI12: =IF($H12=0,0,ROUND($G12*W12/$H12,0)) -> 0 | AJ12: =SUM(X12:AI12) -> 0 | AK12: =$AJ12-$G12 -> 0
A13: 46328 | B13: =$A13+6 -> 46334 | C13: =SUMIFS('Daily Log'!$C$7:$C$377,'Daily Log'!$V$7:$V$377,$A13) -> 0 | D13: =SUMIFS('Daily Log'!$D$7:$D$377,'Daily Log'!$V$7:$V$377,$A13) -> 0 | E13: =SUMIFS('Daily Log'!$E$7:$E$377,'Daily Log'!$V$7:$V$377,$A13) -> 0 | F13: =SUMIFS('Daily Log'!$F$7:$F$377,'Daily Log'!$V$7:$V$377,$A13) -> 0 | G13: =SUMIFS('Daily Log'!$U$7:$U$377,'Daily Log'!$V$7:$V$377,$A13) -> 0 | H13: =SUMIFS('Daily Log'!$S$7:$S$377,'Daily Log'!$V$7:$V$377,$A13) -> 0 | I13: =IF($C13=0,"",$D13/$C13) | J13: =IF($H13=0,"",$E13/$H13) | K13: =IF(AND($G13>0,$H13=0),"pot not shared - no attendance marked",IF(AND($I13<>"",N($I13)>RejectAlarm),"reject rate high","")) | L13: =SUMIFS('Daily Log'!$G$7:$G$377,'Daily Log'!$V$7:$V$377,$A13) -> 0 | M13: =SUMIFS('Daily Log'!$H$7:$H$377,'Daily Log'!$V$7:$V$377,$A13) -> 0 | N13: =SUMIFS('Daily Log'!$I$7:$I$377,'Daily Log'!$V$7:$V$377,$A13) -> 0 | O13: =SUMIFS('Daily Log'!$J$7:$J$377,'Daily Log'!$V$7:$V$377,$A13) -> 0 | P13: =SUMIFS('Daily Log'!$K$7:$K$377,'Daily Log'!$V$7:$V$377,$A13) -> 0 | Q13: =SUMIFS('Daily Log'!$L$7:$L$377,'Daily Log'!$V$7:$V$377,$A13) -> 0 | R13: =SUMIFS('Daily Log'!$M$7:$M$377,'Daily Log'!$V$7:$V$377,$A13) -> 0 | S13: =SUMIFS('Daily Log'!$N$7:$N$377,'Daily Log'!$V$7:$V$377,$A13) -> 0 | T13: =SUMIFS('Daily Log'!$O$7:$O$377,'Daily Log'!$V$7:$V$377,$A13) -> 0 | U13: =SUMIFS('Daily Log'!$P$7:$P$377,'Daily Log'!$V$7:$V$377,$A13) -> 0 | V13: =SUMIFS('Daily Log'!$Q$7:$Q$377,'Daily Log'!$V$7:$V$377,$A13) -> 0 | W13: =SUMIFS('Daily Log'!$R$7:$R$377,'Daily Log'!$V$7:$V$377,$A13) -> 0 | X13: =IF($H13=0,0,ROUND($G13*L13/$H13,0)) -> 0 | Y13: =IF($H13=0,0,ROUND($G13*M13/$H13,0)) -> 0 | Z13: =IF($H13=0,0,ROUND($G13*N13/$H13,0)) -> 0 | AA13: =IF($H13=0,0,ROUND($G13*O13/$H13,0)) -> 0 | AB13: =IF($H13=0,0,ROUND($G13*P13/$H13,0)) -> 0 | AC13: =IF($H13=0,0,ROUND($G13*Q13/$H13,0)) -> 0 | AD13: =IF($H13=0,0,ROUND($G13*R13/$H13,0)) -> 0 | AE13: =IF($H13=0,0,ROUND($G13*S13/$H13,0)) -> 0 | ... AI13: =IF($H13=0,0,ROUND($G13*W13/$H13,0)) -> 0 | AJ13: =SUM(X13:AI13) -> 0 | AK13: =$AJ13-$G13 -> 0
A14: 46335 | B14: =$A14+6 -> 46341 | C14: =SUMIFS('Daily Log'!$C$7:$C$377,'Daily Log'!$V$7:$V$377,$A14) -> 0 | D14: =SUMIFS('Daily Log'!$D$7:$D$377,'Daily Log'!$V$7:$V$377,$A14) -> 0 | E14: =SUMIFS('Daily Log'!$E$7:$E$377,'Daily Log'!$V$7:$V$377,$A14) -> 0 | F14: =SUMIFS('Daily Log'!$F$7:$F$377,'Daily Log'!$V$7:$V$377,$A14) -> 0 | G14: =SUMIFS('Daily Log'!$U$7:$U$377,'Daily Log'!$V$7:$V$377,$A14) -> 0 | H14: =SUMIFS('Daily Log'!$S$7:$S$377,'Daily Log'!$V$7:$V$377,$A14) -> 0 | I14: =IF($C14=0,"",$D14/$C14) | J14: =IF($H14=0,"",$E14/$H14) | K14: =IF(AND($G14>0,$H14=0),"pot not shared - no attendance marked",IF(AND($I14<>"",N($I14)>RejectAlarm),"reject rate high","")) | L14: =SUMIFS('Daily Log'!$G$7:$G$377,'Daily Log'!$V$7:$V$377,$A14) -> 0 | M14: =SUMIFS('Daily Log'!$H$7:$H$377,'Daily Log'!$V$7:$V$377,$A14) -> 0 | N14: =SUMIFS('Daily Log'!$I$7:$I$377,'Daily Log'!$V$7:$V$377,$A14) -> 0 | O14: =SUMIFS('Daily Log'!$J$7:$J$377,'Daily Log'!$V$7:$V$377,$A14) -> 0 | P14: =SUMIFS('Daily Log'!$K$7:$K$377,'Daily Log'!$V$7:$V$377,$A14) -> 0 | Q14: =SUMIFS('Daily Log'!$L$7:$L$377,'Daily Log'!$V$7:$V$377,$A14) -> 0 | R14: =SUMIFS('Daily Log'!$M$7:$M$377,'Daily Log'!$V$7:$V$377,$A14) -> 0 | S14: =SUMIFS('Daily Log'!$N$7:$N$377,'Daily Log'!$V$7:$V$377,$A14) -> 0 | T14: =SUMIFS('Daily Log'!$O$7:$O$377,'Daily Log'!$V$7:$V$377,$A14) -> 0 | U14: =SUMIFS('Daily Log'!$P$7:$P$377,'Daily Log'!$V$7:$V$377,$A14) -> 0 | V14: =SUMIFS('Daily Log'!$Q$7:$Q$377,'Daily Log'!$V$7:$V$377,$A14) -> 0 | W14: =SUMIFS('Daily Log'!$R$7:$R$377,'Daily Log'!$V$7:$V$377,$A14) -> 0 | X14: =IF($H14=0,0,ROUND($G14*L14/$H14,0)) -> 0 | Y14: =IF($H14=0,0,ROUND($G14*M14/$H14,0)) -> 0 | Z14: =IF($H14=0,0,ROUND($G14*N14/$H14,0)) -> 0 | AA14: =IF($H14=0,0,ROUND($G14*O14/$H14,0)) -> 0 | AB14: =IF($H14=0,0,ROUND($G14*P14/$H14,0)) -> 0 | AC14: =IF($H14=0,0,ROUND($G14*Q14/$H14,0)) -> 0 | AD14: =IF($H14=0,0,ROUND($G14*R14/$H14,0)) -> 0 | AE14: =IF($H14=0,0,ROUND($G14*S14/$H14,0)) -> 0 | ... AI14: =IF($H14=0,0,ROUND($G14*W14/$H14,0)) -> 0 | AJ14: =SUM(X14:AI14) -> 0 | AK14: =$AJ14-$G14 -> 0
A15: 46342 | B15: =$A15+6 -> 46348 | C15: =SUMIFS('Daily Log'!$C$7:$C$377,'Daily Log'!$V$7:$V$377,$A15) -> 0 | D15: =SUMIFS('Daily Log'!$D$7:$D$377,'Daily Log'!$V$7:$V$377,$A15) -> 0 | E15: =SUMIFS('Daily Log'!$E$7:$E$377,'Daily Log'!$V$7:$V$377,$A15) -> 0 | F15: =SUMIFS('Daily Log'!$F$7:$F$377,'Daily Log'!$V$7:$V$377,$A15) -> 0 | G15: =SUMIFS('Daily Log'!$U$7:$U$377,'Daily Log'!$V$7:$V$377,$A15) -> 0 | H15: =SUMIFS('Daily Log'!$S$7:$S$377,'Daily Log'!$V$7:$V$377,$A15) -> 0 | I15: =IF($C15=0,"",$D15/$C15) | J15: =IF($H15=0,"",$E15/$H15) | K15: =IF(AND($G15>0,$H15=0),"pot not shared - no attendance marked",IF(AND($I15<>"",N($I15)>RejectAlarm),"reject rate high","")) | L15: =SUMIFS('Daily Log'!$G$7:$G$377,'Daily Log'!$V$7:$V$377,$A15) -> 0 | M15: =SUMIFS('Daily Log'!$H$7:$H$377,'Daily Log'!$V$7:$V$377,$A15) -> 0 | N15: =SUMIFS('Daily Log'!$I$7:$I$377,'Daily Log'!$V$7:$V$377,$A15) -> 0 | O15: =SUMIFS('Daily Log'!$J$7:$J$377,'Daily Log'!$V$7:$V$377,$A15) -> 0 | P15: =SUMIFS('Daily Log'!$K$7:$K$377,'Daily Log'!$V$7:$V$377,$A15) -> 0 | Q15: =SUMIFS('Daily Log'!$L$7:$L$377,'Daily Log'!$V$7:$V$377,$A15) -> 0 | R15: =SUMIFS('Daily Log'!$M$7:$M$377,'Daily Log'!$V$7:$V$377,$A15) -> 0 | S15: =SUMIFS('Daily Log'!$N$7:$N$377,'Daily Log'!$V$7:$V$377,$A15) -> 0 | T15: =SUMIFS('Daily Log'!$O$7:$O$377,'Daily Log'!$V$7:$V$377,$A15) -> 0 | U15: =SUMIFS('Daily Log'!$P$7:$P$377,'Daily Log'!$V$7:$V$377,$A15) -> 0 | V15: =SUMIFS('Daily Log'!$Q$7:$Q$377,'Daily Log'!$V$7:$V$377,$A15) -> 0 | W15: =SUMIFS('Daily Log'!$R$7:$R$377,'Daily Log'!$V$7:$V$377,$A15) -> 0 | X15: =IF($H15=0,0,ROUND($G15*L15/$H15,0)) -> 0 | Y15: =IF($H15=0,0,ROUND($G15*M15/$H15,0)) -> 0 | Z15: =IF($H15=0,0,ROUND($G15*N15/$H15,0)) -> 0 | AA15: =IF($H15=0,0,ROUND($G15*O15/$H15,0)) -> 0 | AB15: =IF($H15=0,0,ROUND($G15*P15/$H15,0)) -> 0 | AC15: =IF($H15=0,0,ROUND($G15*Q15/$H15,0)) -> 0 | AD15: =IF($H15=0,0,ROUND($G15*R15/$H15,0)) -> 0 | AE15: =IF($H15=0,0,ROUND($G15*S15/$H15,0)) -> 0 | ... AI15: =IF($H15=0,0,ROUND($G15*W15/$H15,0)) -> 0 | AJ15: =SUM(X15:AI15) -> 0 | AK15: =$AJ15-$G15 -> 0
A16: 46349 | B16: =$A16+6 -> 46355 | C16: =SUMIFS('Daily Log'!$C$7:$C$377,'Daily Log'!$V$7:$V$377,$A16) -> 0 | D16: =SUMIFS('Daily Log'!$D$7:$D$377,'Daily Log'!$V$7:$V$377,$A16) -> 0 | E16: =SUMIFS('Daily Log'!$E$7:$E$377,'Daily Log'!$V$7:$V$377,$A16) -> 0 | F16: =SUMIFS('Daily Log'!$F$7:$F$377,'Daily Log'!$V$7:$V$377,$A16) -> 0 | G16: =SUMIFS('Daily Log'!$U$7:$U$377,'Daily Log'!$V$7:$V$377,$A16) -> 0 | H16: =SUMIFS('Daily Log'!$S$7:$S$377,'Daily Log'!$V$7:$V$377,$A16) -> 0 | I16: =IF($C16=0,"",$D16/$C16) | J16: =IF($H16=0,"",$E16/$H16) | K16: =IF(AND($G16>0,$H16=0),"pot not shared - no attendance marked",IF(AND($I16<>"",N($I16)>RejectAlarm),"reject rate high","")) | L16: =SUMIFS('Daily Log'!$G$7:$G$377,'Daily Log'!$V$7:$V$377,$A16) -> 0 | M16: =SUMIFS('Daily Log'!$H$7:$H$377,'Daily Log'!$V$7:$V$377,$A16) -> 0 | N16: =SUMIFS('Daily Log'!$I$7:$I$377,'Daily Log'!$V$7:$V$377,$A16) -> 0 | O16: =SUMIFS('Daily Log'!$J$7:$J$377,'Daily Log'!$V$7:$V$377,$A16) -> 0 | P16: =SUMIFS('Daily Log'!$K$7:$K$377,'Daily Log'!$V$7:$V$377,$A16) -> 0 | Q16: =SUMIFS('Daily Log'!$L$7:$L$377,'Daily Log'!$V$7:$V$377,$A16) -> 0 | R16: =SUMIFS('Daily Log'!$M$7:$M$377,'Daily Log'!$V$7:$V$377,$A16) -> 0 | S16: =SUMIFS('Daily Log'!$N$7:$N$377,'Daily Log'!$V$7:$V$377,$A16) -> 0 | T16: =SUMIFS('Daily Log'!$O$7:$O$377,'Daily Log'!$V$7:$V$377,$A16) -> 0 | U16: =SUMIFS('Daily Log'!$P$7:$P$377,'Daily Log'!$V$7:$V$377,$A16) -> 0 | V16: =SUMIFS('Daily Log'!$Q$7:$Q$377,'Daily Log'!$V$7:$V$377,$A16) -> 0 | W16: =SUMIFS('Daily Log'!$R$7:$R$377,'Daily Log'!$V$7:$V$377,$A16) -> 0 | X16: =IF($H16=0,0,ROUND($G16*L16/$H16,0)) -> 0 | Y16: =IF($H16=0,0,ROUND($G16*M16/$H16,0)) -> 0 | Z16: =IF($H16=0,0,ROUND($G16*N16/$H16,0)) -> 0 | AA16: =IF($H16=0,0,ROUND($G16*O16/$H16,0)) -> 0 | AB16: =IF($H16=0,0,ROUND($G16*P16/$H16,0)) -> 0 | AC16: =IF($H16=0,0,ROUND($G16*Q16/$H16,0)) -> 0 | AD16: =IF($H16=0,0,ROUND($G16*R16/$H16,0)) -> 0 | AE16: =IF($H16=0,0,ROUND($G16*S16/$H16,0)) -> 0 | ... AI16: =IF($H16=0,0,ROUND($G16*W16/$H16,0)) -> 0 | AJ16: =SUM(X16:AI16) -> 0 | AK16: =$AJ16-$G16 -> 0
A17: 46356 | B17: =$A17+6 -> 46362 | C17: =SUMIFS('Daily Log'!$C$7:$C$377,'Daily Log'!$V$7:$V$377,$A17) -> 0 | D17: =SUMIFS('Daily Log'!$D$7:$D$377,'Daily Log'!$V$7:$V$377,$A17) -> 0 | E17: =SUMIFS('Daily Log'!$E$7:$E$377,'Daily Log'!$V$7:$V$377,$A17) -> 0 | F17: =SUMIFS('Daily Log'!$F$7:$F$377,'Daily Log'!$V$7:$V$377,$A17) -> 0 | G17: =SUMIFS('Daily Log'!$U$7:$U$377,'Daily Log'!$V$7:$V$377,$A17) -> 0 | H17: =SUMIFS('Daily Log'!$S$7:$S$377,'Daily Log'!$V$7:$V$377,$A17) -> 0 | I17: =IF($C17=0,"",$D17/$C17) | J17: =IF($H17=0,"",$E17/$H17) | K17: =IF(AND($G17>0,$H17=0),"pot not shared - no attendance marked",IF(AND($I17<>"",N($I17)>RejectAlarm),"reject rate high","")) | L17: =SUMIFS('Daily Log'!$G$7:$G$377,'Daily Log'!$V$7:$V$377,$A17) -> 0 | M17: =SUMIFS('Daily Log'!$H$7:$H$377,'Daily Log'!$V$7:$V$377,$A17) -> 0 | N17: =SUMIFS('Daily Log'!$I$7:$I$377,'Daily Log'!$V$7:$V$377,$A17) -> 0 | O17: =SUMIFS('Daily Log'!$J$7:$J$377,'Daily Log'!$V$7:$V$377,$A17) -> 0 | P17: =SUMIFS('Daily Log'!$K$7:$K$377,'Daily Log'!$V$7:$V$377,$A17) -> 0 | Q17: =SUMIFS('Daily Log'!$L$7:$L$377,'Daily Log'!$V$7:$V$377,$A17) -> 0 | R17: =SUMIFS('Daily Log'!$M$7:$M$377,'Daily Log'!$V$7:$V$377,$A17) -> 0 | S17: =SUMIFS('Daily Log'!$N$7:$N$377,'Daily Log'!$V$7:$V$377,$A17) -> 0 | T17: =SUMIFS('Daily Log'!$O$7:$O$377,'Daily Log'!$V$7:$V$377,$A17) -> 0 | U17: =SUMIFS('Daily Log'!$P$7:$P$377,'Daily Log'!$V$7:$V$377,$A17) -> 0 | V17: =SUMIFS('Daily Log'!$Q$7:$Q$377,'Daily Log'!$V$7:$V$377,$A17) -> 0 | W17: =SUMIFS('Daily Log'!$R$7:$R$377,'Daily Log'!$V$7:$V$377,$A17) -> 0 | X17: =IF($H17=0,0,ROUND($G17*L17/$H17,0)) -> 0 | Y17: =IF($H17=0,0,ROUND($G17*M17/$H17,0)) -> 0 | Z17: =IF($H17=0,0,ROUND($G17*N17/$H17,0)) -> 0 | AA17: =IF($H17=0,0,ROUND($G17*O17/$H17,0)) -> 0 | AB17: =IF($H17=0,0,ROUND($G17*P17/$H17,0)) -> 0 | AC17: =IF($H17=0,0,ROUND($G17*Q17/$H17,0)) -> 0 | AD17: =IF($H17=0,0,ROUND($G17*R17/$H17,0)) -> 0 | AE17: =IF($H17=0,0,ROUND($G17*S17/$H17,0)) -> 0 | ... AI17: =IF($H17=0,0,ROUND($G17*W17/$H17,0)) -> 0 | AJ17: =SUM(X17:AI17) -> 0 | AK17: =$AJ17-$G17 -> 0
A18: 46363 | B18: =$A18+6 -> 46369 | C18: =SUMIFS('Daily Log'!$C$7:$C$377,'Daily Log'!$V$7:$V$377,$A18) -> 0 | D18: =SUMIFS('Daily Log'!$D$7:$D$377,'Daily Log'!$V$7:$V$377,$A18) -> 0 | E18: =SUMIFS('Daily Log'!$E$7:$E$377,'Daily Log'!$V$7:$V$377,$A18) -> 0 | F18: =SUMIFS('Daily Log'!$F$7:$F$377,'Daily Log'!$V$7:$V$377,$A18) -> 0 | G18: =SUMIFS('Daily Log'!$U$7:$U$377,'Daily Log'!$V$7:$V$377,$A18) -> 0 | H18: =SUMIFS('Daily Log'!$S$7:$S$377,'Daily Log'!$V$7:$V$377,$A18) -> 0 | I18: =IF($C18=0,"",$D18/$C18) | J18: =IF($H18=0,"",$E18/$H18) | K18: =IF(AND($G18>0,$H18=0),"pot not shared - no attendance marked",IF(AND($I18<>"",N($I18)>RejectAlarm),"reject rate high","")) | L18: =SUMIFS('Daily Log'!$G$7:$G$377,'Daily Log'!$V$7:$V$377,$A18) -> 0 | M18: =SUMIFS('Daily Log'!$H$7:$H$377,'Daily Log'!$V$7:$V$377,$A18) -> 0 | N18: =SUMIFS('Daily Log'!$I$7:$I$377,'Daily Log'!$V$7:$V$377,$A18) -> 0 | O18: =SUMIFS('Daily Log'!$J$7:$J$377,'Daily Log'!$V$7:$V$377,$A18) -> 0 | P18: =SUMIFS('Daily Log'!$K$7:$K$377,'Daily Log'!$V$7:$V$377,$A18) -> 0 | Q18: =SUMIFS('Daily Log'!$L$7:$L$377,'Daily Log'!$V$7:$V$377,$A18) -> 0 | R18: =SUMIFS('Daily Log'!$M$7:$M$377,'Daily Log'!$V$7:$V$377,$A18) -> 0 | S18: =SUMIFS('Daily Log'!$N$7:$N$377,'Daily Log'!$V$7:$V$377,$A18) -> 0 | T18: =SUMIFS('Daily Log'!$O$7:$O$377,'Daily Log'!$V$7:$V$377,$A18) -> 0 | U18: =SUMIFS('Daily Log'!$P$7:$P$377,'Daily Log'!$V$7:$V$377,$A18) -> 0 | V18: =SUMIFS('Daily Log'!$Q$7:$Q$377,'Daily Log'!$V$7:$V$377,$A18) -> 0 | W18: =SUMIFS('Daily Log'!$R$7:$R$377,'Daily Log'!$V$7:$V$377,$A18) -> 0 | X18: =IF($H18=0,0,ROUND($G18*L18/$H18,0)) -> 0 | Y18: =IF($H18=0,0,ROUND($G18*M18/$H18,0)) -> 0 | Z18: =IF($H18=0,0,ROUND($G18*N18/$H18,0)) -> 0 | AA18: =IF($H18=0,0,ROUND($G18*O18/$H18,0)) -> 0 | AB18: =IF($H18=0,0,ROUND($G18*P18/$H18,0)) -> 0 | AC18: =IF($H18=0,0,ROUND($G18*Q18/$H18,0)) -> 0 | AD18: =IF($H18=0,0,ROUND($G18*R18/$H18,0)) -> 0 | AE18: =IF($H18=0,0,ROUND($G18*S18/$H18,0)) -> 0 | ... AI18: =IF($H18=0,0,ROUND($G18*W18/$H18,0)) -> 0 | AJ18: =SUM(X18:AI18) -> 0 | AK18: =$AJ18-$G18 -> 0
... A59: 46650 | B59: =$A59+6 -> 46656 | C59: =SUMIFS('Daily Log'!$C$7:$C$377,'Daily Log'!$V$7:$V$377,$A59) -> 0 | D59: =SUMIFS('Daily Log'!$D$7:$D$377,'Daily Log'!$V$7:$V$377,$A59) -> 0 | E59: =SUMIFS('Daily Log'!$E$7:$E$377,'Daily Log'!$V$7:$V$377,$A59) -> 0 | F59: =SUMIFS('Daily Log'!$F$7:$F$377,'Daily Log'!$V$7:$V$377,$A59) -> 0 | G59: =SUMIFS('Daily Log'!$U$7:$U$377,'Daily Log'!$V$7:$V$377,$A59) -> 0 | H59: =SUMIFS('Daily Log'!$S$7:$S$377,'Daily Log'!$V$7:$V$377,$A59) -> 0 | I59: =IF($C59=0,"",$D59/$C59) | J59: =IF($H59=0,"",$E59/$H59) | K59: =IF(AND($G59>0,$H59=0),"pot not shared - no attendance marked",IF(AND($I59<>"",N($I59)>RejectAlarm),"reject rate high","")) | L59: =SUMIFS('Daily Log'!$G$7:$G$377,'Daily Log'!$V$7:$V$377,$A59) -> 0 | M59: =SUMIFS('Daily Log'!$H$7:$H$377,'Daily Log'!$V$7:$V$377,$A59) -> 0 | N59: =SUMIFS('Daily Log'!$I$7:$I$377,'Daily Log'!$V$7:$V$377,$A59) -> 0 | O59: =SUMIFS('Daily Log'!$J$7:$J$377,'Daily Log'!$V$7:$V$377,$A59) -> 0 | P59: =SUMIFS('Daily Log'!$K$7:$K$377,'Daily Log'!$V$7:$V$377,$A59) -> 0 | Q59: =SUMIFS('Daily Log'!$L$7:$L$377,'Daily Log'!$V$7:$V$377,$A59) -> 0 | R59: =SUMIFS('Daily Log'!$M$7:$M$377,'Daily Log'!$V$7:$V$377,$A59) -> 0 | S59: =SUMIFS('Daily Log'!$N$7:$N$377,'Daily Log'!$V$7:$V$377,$A59) -> 0 | T59: =SUMIFS('Daily Log'!$O$7:$O$377,'Daily Log'!$V$7:$V$377,$A59) -> 0 | U59: =SUMIFS('Daily Log'!$P$7:$P$377,'Daily Log'!$V$7:$V$377,$A59) -> 0 | V59: =SUMIFS('Daily Log'!$Q$7:$Q$377,'Daily Log'!$V$7:$V$377,$A59) -> 0 | W59: =SUMIFS('Daily Log'!$R$7:$R$377,'Daily Log'!$V$7:$V$377,$A59) -> 0 | X59: =IF($H59=0,0,ROUND($G59*L59/$H59,0)) -> 0 | Y59: =IF($H59=0,0,ROUND($G59*M59/$H59,0)) -> 0 | Z59: =IF($H59=0,0,ROUND($G59*N59/$H59,0)) -> 0 | AA59: =IF($H59=0,0,ROUND($G59*O59/$H59,0)) -> 0 | AB59: =IF($H59=0,0,ROUND($G59*P59/$H59,0)) -> 0 | AC59: =IF($H59=0,0,ROUND($G59*Q59/$H59,0)) -> 0 | AD59: =IF($H59=0,0,ROUND($G59*R59/$H59,0)) -> 0 | AE59: =IF($H59=0,0,ROUND($G59*S59/$H59,0)) -> 0 | ... AI59: =IF($H59=0,0,ROUND($G59*W59/$H59,0)) -> 0 | AJ59: =SUM(X59:AI59) -> 0 | AK59: =$AJ59-$G59 -> 0

Sheet Checks
A1: ◆ Donabay | C1: Home | D1: Daily Log | E1: Cash Ledger | H1: Weekly Pay | K1: Payslip | M1: Workers | O1: Settings | Q1: Guide | S1: · | T1: History | V1: Weeks | X1: Checks
A2: Checks
A3: The workbook checking itself. Everything should say OK before payday.
B5: Overall | C5: =IF(COUNTIF($C$8:$C$16,"OK")=9,"ALL CHECKS OK",(9-COUNTIF($C$8:$C$16,"OK"))&" check(s) need attention") -> ALL CHECKS OK
B7: Check | C7: Result | D7: Where to look
B8: Worker list is clean (names unique, status set) | C8: =IF((COUNTIF(Workers!$H$6:$H$17,"?*"))=0,"OK",(COUNTIF(Workers!$H$6:$H$17,"?*"))&" to fix") -> OK | D8: Workers
B9: Daily Log rows without problems | C9: =IF((COUNTIF('Daily Log'!$W$7:$W$377,"?*"))=0,"OK",(COUNTIF('Daily Log'!$W$7:$W$377,"?*"))&" to fix") -> OK | D9: Daily Log - Check column
B10: Cash Ledger entries are complete and valid | C10: =IF((COUNTIF('Cash Ledger'!$M$7:$M$1006,"?*")-COUNTIF('Cash Ledger'!$M$7:$M$1006,"Warning*"))=0,"OK",(COUNTIF('Cash Ledger'!$M$7:$M$1006,"?*")-COUNTIF('Cash Ledger'!$M$7:$M$1006,"Warning*"))&" to fix") -> OK | D10: Cash Ledger - Check column
B11: Every week's pot is shared out | C11: =IF((COUNTIF(Weeks!$K$7:$K$59,"pot*"))=0,"OK",(COUNTIF(Weeks!$K$7:$K$59,"pot*"))&" to fix") -> OK | D11: Weeks
B12: Worker shares add up to each week's pot | C12: =IF((SUMPRODUCT(--(ABS(Weeks!$AK$7:$AK$59)>12)))=0,"OK",(SUMPRODUCT(--(ABS(Weeks!$AK$7:$AK$59)>12)))&" to fix") -> OK | D12: Weeks
B13: A pay rate is set | C13: =IF((IF(COUNTIF(RateValues,">0")=0,1,0))=0,"OK",(IF(COUNTIF(RateValues,">0")=0,1,0))&" to fix") -> OK | D13: Settings
B14: Rate dates are in order, oldest first | C14: =IF((SUMPRODUCT((Settings!$B$14:$B$32<>"")*(Settings!$B$14:$B$32<=Settings!$B$13:$B$31)))=0,"OK",(SUMPRODUCT((Settings!$B$14:$B$32<>"")*(Settings!$B$14:$B$32<=Settings!$B$13:$B$31)))&" to fix") -> OK | D14: Settings
B15: Cash Ledger has room left | C15: =IF((IF(COUNT('Cash Ledger'!$B$7:$B$1006)>950,1,0))=0,"OK",(IF(COUNT('Cash Ledger'!$B$7:$B$1006)>950,1,0))&" to fix") -> OK | D15: Cash Ledger - nearly full, ask for a rebuild
B16: Worker slots left | C16: =IF((IF(COUNTA(Workers!$B$6:$B$17)>=12,1,0))=0,"OK",(IF(COUNTA(Workers!$B$6:$B$17)>=12,1,0))&" to fix") -> OK | D16: Workers - all slots used, ask for a rebuild
B18: Warnings (not errors)
B19: Advances bigger than what the worker had earned so far | C19: =COUNTIF('Cash Ledger'!$M$7:$M$1006,"Warning*") -> 0 | D19: Allowed - just so you know. Shows as debt carried forward.
B20: Weeks with a high reject rate | C20: =COUNTIF(Weeks!$K$7:$K$59,"?*")-COUNTIF(Weeks!$K$7:$K$59,"pot*") -> 0 | D20: Weeks

Sheet Project Notes
A1: Project Notes: to make a .md file, copy A3 to the last line into Notepad and save as Donabay_project_notes.md
A3: # Donabay – Project Notes (handover)
A5: _Last updated: 24 Sep 2026. File: **Donabay.xlsx**_
A7: Weekly pay workbook for a filler-block plant. The crew is paid **per good block** and the weekly pot is **shared by days worked**. Advances are logged in a cash ledger and taken off the next pay. Plain Excel only: no macros, no add-ins.
A9: ---
A11: ## 1. How the business rules work
A13: | Rule | How it works |
A14: |---|---|
A15: | Pay base | Only good blocks are paid: `Good = Moulded − Broken`. `Paid blocks = Moulded − MAX(0, Broken − BreakAllow × Moulded)`. BreakAllow is currently 0%, so paid = good. |
A16: | Pay rate | Settings rate table: so'm per paid block, each rate with a start date. The rate in force on each day is looked up, so old weeks keep their old rate. Current rate: **500 so'm from 2026-09-21**. |
A17: | Weekly pot | Sum of the week's daily pay values (paid blocks × rate). |
A18: | Split | Worker share = pot × (worker's days ÷ total crew-days). Attendance: `1` = full day, `0.5` = half day, empty = absent. |
... A113: - Optional: extend capacity (more worker slots or ledger rows) when Checks warns.
